{"local_id": "02009R0748-20130212", "direct_url": "https://eur-lex.europa.eu/legal-content/EN/TXT/?qid=1547506523483&uri=CELEX:02009R0748-20130212", "author": "European Commission", "eurovoc_descriptors": [], "subject_matters": [], "content": "2009r0748 \u2014 en \u2014 12.02.2013 \u2014 005.001 this document is meant purely as a documentation tool and the institutions do not assume any liability for its contents \u25bab commission regulation (ec) no 748/2009 of 5 august 2009 on the list of aircraft operators which performed an aviation activity listed in annex i to directive 2003/87/ec on or after 1 january 2006 specifying the administering member state for each aircraft operator (text with eea relevance) (oj l 219, 22.8.2009, p.1) amended by: official journal no page date m1 commission regulation (eu) no 82/2010 of 28 january 2010 l 25 12 29.1.2010 m2 commission regulation (eu) no 115/2011 of 2 february 2011 l 39 1 12.2.2011 m3 commission regulation (eu) no 394/2011 of 20 april 2011 l 107 1 27.4.2011 m4 commission regulation (eu) no 100/2012 of 3 february 2012 l 39 1 11.2.2012 \u25bam5 commission regulation (eu) no 109/2013 of 29 january 2013 l 40 1 9.2.2013 \u25bcb commission regulation (ec) no 748/2009 of 5 august 2009 on the list of aircraft operators which performed an aviation activity listed in annex i to directive 2003/87/ec on or after 1 january 2006 specifying the administering member state for each aircraft operator (text with eea relevance) the commission of the european communities, having regard to the treaty establishing the european community, having regard to directive 2003/87/ec of the european parliament and of the council of 13 october 2003 establishing a scheme for greenhouse gas emission allowance trading within the community and amending council directive 96/61/ec ( 1 ), and in particular article 18a(3)(a) thereof, whereas: (1) directive 2003/87/ec, as amended by directive 2008/101/ec ( 2 ), includes aviation activities within the scheme for greenhouse gas emission allowance trading within the community (hereinafter the \u2018community scheme\u2019). (2) in order to reduce the administrative burden on aircraft operators, directive 2003/87/ec provides for one member state to be responsible for each aircraft operator. article 18a(1) and (2) of directive 2003/87/ec contains the provisions governing the assignment of each aircraft operator to its administering member state. the list of aircraft operators and their administering member states (hereinafter \u2018the list\u2019) should ensure that each operator knows which member state it will be regulated by and that member states are clear on which operators they should regulate. (3) in establishing the list, the commission has taken into account comments received after it had published a preliminary list of aircraft operators and their administering member states on 11 february 2009. the list is based on data provided by eurocontrol using records of flight plans ( 3 ). (4) the requirements of directive 2003/87/ec apply to aircraft operators as defined in point (o) of article 3 of that directive. the inclusion in the community scheme is linked to the performance of an aviation activity only and is not subject to inclusion on the list. aircraft operators which perform an aviation activity listed in annex i to directive 2003/87/ec are therefore covered by the community scheme whether or not they are included in the list at the time of the activity. likewise aircraft operators which cease to perform an aviation activity are excluded from the community scheme once they cease to perform an aviation activity listed in annex i to directive 2003/87/ec and not at the time when they are removed from the list. (5) the list includes all aircraft operators which have undertaken a relevant aviation activity on or after 1 january 2006, and until 31 december 2008. as such, aircraft operators that have permanently or temporarily ceased to perform their aviation activities might appear on this list. it does not take into consideration whether aircraft operators are included on the community list of air carriers which, for safety reasons, are subject to an operating ban within the community in accordance with regulation (ec) no 2111/2005 of the european parliament and of the council of 14 december 2005 on the establishment of a community list of air carriers subject to an operating ban within the community and on informing air transport passengers of the identity of the operating air carrier, and repealing article 9 of directive 2004/36/ec ( 4 ). this regulation should therefore be without prejudice to decisions taken by the commission or member states in accordance with regulation (ec) no 2111/2005. (6) each aircraft operator should be attributed a unique code in the list. that code should enable to identify participants in the community scheme. has adopted this regulation: article 1 the list of aircraft operators which performed an aviation activity listed in annex i to directive 2003/87/ec on or after 1 january 2006 specifying the administering member state for each aircraft operator referred to in article 18a(3)(a) of directive 2003/87/ec is set out in the annex to this regulation. article 2 this regulation shall enter into force on the third day following that of its publication in the official journal of the european union . this regulation shall be binding in its entirety and directly applicable in all member states. \u25bcm5 annex list of aircraft operators that performed an aviation activity listed in annex i to directive 2003/87/ec of the european parliament and of the council on or after 1 january 2006 specifying the administering member state for each aircraft operator also taking into consideration the expansion of the union emission trading scheme to eea-efta countries belgium crco identification no. operator name state of the operator 123 abelag aviation belgium 7649 airborne express united states 33612 allied air limited nigeria 30020 aviastar-tu co. russian federation 31416 avia traffic company russian federation 908 brussels airlines belgium 25996 cairo aviation egypt 4369 cal cargo airlines israel 29517 capital avtn srvcs netherlands f11336 corporate wings llc united states 32909 cresair inc united states 32432 egyptair cargo egypt f12977 excellent investment llc united states f11102 fedex express corporate aviation united states 13457 flying partners cvba belgium 29427 flying service n.v. belgium 32486 fayard enterprises united states 24578 gafi general aviat switzerland 32737 great alliance world united kingdom f12983 green diesel llc united states 29980 hainan airlines (2) china 23700 hewa bora airways congo 27232 internet jet netherlands 28582 inter-wetall switzerland 9542 intl paper cy united states 27709 kalitta air united states 28087 las vegas charter united states 32303 master top linhas brazil 37066 meridian (airways) belgium 1084 mil belgium belgium 26688 newell rubbermaid united states 31207 n604fj llc united states f11462 n907ws aviation llc united states f10341 officemax inc united states 31660 ripplewood avtn united states 2344 saudia saudi arabia 27769 sea-air belgium 27975 sia cargo pte ltd singapore 29222 silverback cargo rwanda 39079 solarius aviation united states 35334 sonoco products co united states 26784 southern air united states 38995 stanley black&decker united states 28453 thomas cook arl belg belgium 27011 tnt airways belgium 34920 trident aviation svc united states 30011 tui airlines \u2014 jaf belgium 27911 ultimate acft servic united states 13603 vf corp united states 36269 vf international switzerland 37064 viper classics ltd united kingdom 20065 v l m belgium f11467 wilson & associates of delaware llc united states 37549 yiltas group turkey a11534 operator using tail nb: vpbdv unknown a11549 operator using tail nb: vqbha unknown bulgaria crco identification no. operator name state of the operator 27359 aerotrans kazakstan kazakhstan 27698 aerovista united arab emirates 33329 aero power ltd united kingdom 23962 air ban bulgaria 35743 air iberia ltd. georgia 26520 air libya 2 libya 11775 air via bulgarian bulgaria 33225 air victory georgia 34357 air west georgia georgia 31007 anikay air middle e jordan 36020 ararat international armenia 28818 asian spirit philippines 34563 asia airways united arab emirates 24508 baltic airlines uu russian federation 32131 beibars cjsc kazakhstan 28445 bh air bulgaria 27538 bulgarian air chrtr. bulgaria 29056 bulgaria air bulgaria 25981 cargo air ltd. bulgaria 32313 east wing kazakhstan kazakhstan 36884 fly adjara georgia 36995 gr avia s.a. guinea 10165 hemus air bulgaria 25134 internal ministry uu russian federation 28505 iranian air transpor iran, islamic republic of 31721 jordan int air cargo jordan 27345 khoriv avia ukraine 28246 kokshetau airline kazakhstan 32034 komiaviaviatrans 2 russian federation 31019 kremenchuk flight ukraine 38939 krunk aviation 2 ukraine 21448 moscow airlines jsc russian federation 30622 pmt air cambodia 37661 rgb enterprises llc united states 27203 rosavia air company ukraine 29085 rubystar belarus 32835 sayat air kazakstan kazakhstan 1830 senegalair senegal 32037 sky jet kazakhstan kazakhstan 32664 starline kz jsc kazakhstan 32347 taban air iran, islamic republic of 37954 tropical air (z) ltd tanzania, united republic of 37793 ukrspecexport ukraine 31648 vip-avia georgia 37987 yak air georgia 35082 zagros airlines iran, islamic republic of czech republic crco identification no. operator name state of the operator 7824 acl slovacky czech republic 35387 acs sa spain 16895 aero vodochody czech republic f11813 aersale inc united states 31304 aircraft industries czech republic 39019 airline cont.mntn eq united states 38060 air navigation lk czech republic 31433 alandia air ab finland 30203 atma airlines united arab emirates 34057 avtn specialties inc united states 35333 axis aviation group united states 22621 caa czech republic czech republic 34430 caimito enterp. ltd cyprus 859 czech airlines czech republic 36294 czech connect airlin czech republic f10182 executive flight services, inc. united states 33327 earth one limited united kingdom 38868 euro jet fzco united arab emirates 36242 georgian internation georgia 31631 global aviation liby libya 36746 holiday czech czech republic 35825 hyundai motor co korea, republic of 32231 ilin aircompany russian federation 30145 incledon enterprises cyprus 27908 job air sro czech republic 39009 jump-tandem czech republic 30825 lets fly sro czech republic 38713 little aviation ltd australia 32935 midamerica holdings united states 3597 mil czech republic czech republic 30743 norse air charter south africa 29976 nova chemicals united states 35361 okay holding as czech republic 24121 petropavlovsk air russian federation 38114 praga aviation s.r.o czech republic f10379 red.com united states 36763 retentura ltd. cyprus 2276 rockwell automation united states 32157 skydive lk czech republic 32812 sky diving for fun slovakia 27292 sky georgia georgia 31351 sky kg airlines russian federation 37554 sovereign express virgin islands, british 13702 stevens express united states f13143 tinber llc united states 24903 travel servis a.s. czech republic 25890 ukrainian pilot ukraine 32721 videotape center united states 38948 vietjet air s.r.o. viet nam a12699 operator using tail nb: n150rn united states denmark crco identification no. operator name state of the operator 33185 air alpha a/c sales denmark 3456 air alsie denmark 35623 air bishkek russian federation 22466 air greenland denmark 37856 air panama panama 34774 aligap a/s denmark 36866 alumeco a/s denmark 142 atlantic airways denmark 36122 aviation holdings united states 35753 a/s maersk aviation denmark 36842 brasilia jet center brazil 32921 canyon gate flt svcs united states 781 cimber stirling denmark 33047 citicapital locavia france f10500 duchossois industries, inc. united states 366 danish air transport denmark 27919 drt vertriebs gmbh denmark 35298 eagle helicopter mtc switzerland 25431 elmagal aviation sudan 26272 execujet europe a/s denmark 35478 first greenwich united kingdom f10218 gctpa, llc united states 37052 genchart b.v. netherlands 33254 ge capital solutions denmark 32364 global transervice united states 32595 graakjaer a/s denmark 36297 jet fleet intl united states 32158 jet time a/s denmark 34892 jjo invest aps denmark 33518 kirkbi invest denmark 31243 kirkbi trading denmark 36538 kirk aviation a/s denmark 34672 lao capricorn air lao people\u2019s democratic republic 38155 moens, g netherlands 38120 mongolian airlines mongolia 12230 nordic aviation capital a/s denmark 32541 naples flight mgmt united states 9914 nilan a/s denmark 38224 nuuk aircraft a aps denmark 34830 olga leasing ltd bermuda 33803 partnerselskabet denmark 23090 pharma nord denmark 35196 primera air scand denmark 33624 quad/air llc united states 29123 rheinland air serv. germany 31890 romanian airport svc romania 37008 scandinavia executiv denmark 9918 star air denmark 36191 sun way georgia georgia 4357 sun-air of scandinavia denmark 21484 thomas cook scand. denmark 38112 vincent aviation ltd new zealand 32655 vip partnerfly denmark 12327 weibel scientific denmark germany crco identification no. operator name state of the operator 24568 ebm-papst mulfingen gmbh & co. kg germany f10001 academy of art university united states 3647 adolf w\u00fcrth gmbh & co. kg germany 156 aeroflot \u2014 russian airlines russian federation 35126 aerologic gmbh germany 6802 aero personal s.a de c.v. mexico 21756 airtrans flugzeugvermietungs gmbh germany 32419 airbridgecargo airlines llc russian federation 28844 air astana jsc kazakhstan 8221 air berlin plc & co. luftverkehrs kg germany 33133 air china cargo co., ltd china 786 air china limited china 22317 air-service gmbh germany 8901 archer daniels midland company united states 19480 asiana airlines korea, republic of 27868 atlasjet airlines turkey 20979 atlas air, inc. united states 26507 aaa aviation & aircr germany 34963 acg air cargo germany 20017 acm air charter gmbh germany 33295 advanced av. logist germany 150 aerodienst germany 32334 aeroflot cargo russian federation 38865 aero bee airlines canada 11454 afi flight inspect. germany 31799 agrata aviation estonia 27692 ahsel hava turkey 32484 aircastle advisor united states 33817 aircraft asset mgt. germany 32868 aircraft general italy f11396 aircraft guaranty corp trustee united states 34984 aircraft mngmt ls switzerland 37424 aircraft partner germany 36019 aircraft rent a.s. czech republic 38063 aircraft solutions luxembourg 33852 airlift service d.o. macedonia, the former yugoslav republic of 24283 airphil express philippines 31390 airseven gmbh germany 34629 airvip ltd. bermuda 22484 air alliance gmbh germany 36344 air arabia egypt egypt 35195 air china business china 36986 air finkenwerder germany 36989 air fuhlsbuettel germany 32268 air hamburg germany 22378 air kuban russian federation 23463 air macau co. ltd. macao sar 5663 air namibia namibia 29743 air national corp new zealand 17595 air service berlin germany 31446 air transport intl 2 united states 36719 air 1 aviation united states 33836 ajwa aviation saudi arabia 5165 alpla air charter austria 38135 alsco united states 30361 al hokair switzerland 36165 al sahab limited bahrain 25435 al-thani qatar 36981 amentum capital ltd ireland 32684 amjet aviation united states 31290 aop air operating switzerland 34337 api holding germany 33706 arcas aviation gmbh germany 27073 artoc air egypt 38398 asg aviation germany 25551 asia continental kazakhstan 35310 asia continent avia kazakhstan 24940 asia today ltd china 32548 astron aviation ltd switzerland f11211 asw air-service werkflugdiesnt gmbh & co. kg germany 30698 atg swiss first switzerland 36360 augsburg airways gmb germany 29122 auron ltd bermuda 38352 avaz d.o.o. bosnia and herzegovina 37650 aviando services united states 31551 aviation cap grp united kingdom 35968 aviation investment germany 35708 aviation jolina sec canada 33093 aviation partners s honduras 38617 azt llc united states 516 bahag baus handelsgesellschaft ag zug/schweiz zweigniederlassung mannheim germany 25978 bauhaus gesellschaft f\u00fcr bau- und hausbedarf mbh & co. germany f10795 beef products inc./bpi technology inc. united states 23956 blue sky airservice gmbh germany 29090 blue wings ag germany 29389 bombardier preowned united states 31614 bombardier transportation gmbh germany 15176 bundespolizei-fliegergruppe germany 32874 business jet ltd new zealand 7897 bae systems flt syst united states 30586 ball corp united states 32840 barbedos group ltd nigeria 509 basf se germany 29137 batavia air indonesia 35233 bavaria internation germany 30306 bedo beteiligungs germany 17395 beechcraft berlin germany 38554 beratex group ltd russian federation 11646 berger julius nigeria 31886 bestair turkey turkey 11312 bizair flug gmbh germany f12963 black forest ventures llc united states 28042 blue sky group united states 14658 bmw ag germany 38111 boekhoorn m&a netherlands 6667 bombardier aerospace united states 36062 borajet havacilik turkey 37261 boston post leasing united states 37922 bournemouth air ltd. switzerland 34852 bremenfly gmbh germany 680 burda reiseflug germany 35021 chai ltd bermuda 35418 challenge aero ag ukraine 22448 cirrus airlines luftfahrtgesellschaft mbh germany f10709 colgan air services united states 824 condor flugdienst gmbh germany 12495 croatia airlines hrvatska zrakoplovna tvrtka d.d. croatia 33282 canjet airlines canada 34985 cape chamonix wine south africa 32482 carson air ltd canada 19823 ca \u2018air moldova\u2019 is moldova, republic of 26021 cebu pacific air philippines 30714 central mountain air canada 26782 china utd airline 2 china 35194 chongqing airlines china 28178 cirrus aviation germany 35527 classic services inc united states 36157 club saab 340 switzerland 4782 comfort air germany 23741 commander mexicana mexico 33189 continent airline uu russian federation 25210 cook aircraft united states 31333 corp jet svcs united kingdom 24481 ctl logistics s.a. poland 4484 delta air lines, inc. united states 8980 delta technical services ltd germany 1776 deutsche lufthansa ag germany 2044 dr august oetker kg germany 32731 danaher corporation united states 34179 dao aviation denmark 967 das direct air germany 28800 dateline overseas cyprus 30651 dauair germany 18003 dba luftfahrtgesell. germany f10558 dcs management services united states 26466 dc aviation gmbh germany 30996 deere & company united states 38547 dekalb farmers mark. united states 37580 dermapharm germany f10774 dfz, llc united states f10589 dh flugcharter gmbh germany 25139 dietz ag germany 37808 dietz aviation gmbh germany 35389 dievb gmbh & co.kg germany 18824 dlr braunschweig germany 28473 dogan havacilik turkey 27181 donavia jsc russian federation 35451 dornier no limits germany 37798 do-tec gmbh germany 28795 dulco handel gmbh germany 968 dussmann p united states 30726 dutch antilles expr. aruba 30461 d2 aviation united states 12213 emil capital partners, llc united states f10180 epps air service, inc. united states 36121 eat leipzig gmbh germany 34657 eea gmbh germany 31615 eichsfelder air germany 35749 eon aviation china 36507 erste asset invest. germany 19629 eschmann h d germany 17794 eurocopter deutschl. germany 1980 european air express germany 34011 euro air charter germany 3639 evergreen airlines united states 36357 execujet aviation south africa 31909 executive svcs (az) united states 8082 e.i. du pont de nemours and company united states 8272 farnair switzerland ag switzerland 23244 federal state unitary enterprise \u2018state transport company \u2018russia\u2019 russian federation 14557 firma steiner-film germany 1778 flugbereitschaft des bundesministerium der verteidigung (flbschft bmvg) germany 32678 fresena flug gmbh & co kg germany 4783 fai rent-a-jet germany 34640 falcon 007 s.a.r.l. france 28589 fancourt flugcharter gmbh & co kg switzerland 33077 fas gmbh germany 35937 finkcas germany 22238 flight calibration germany 32722 flight cal. malaysia malaysia 31012 flugschule hamburg germany 38804 flying technology russian federation 38912 fly alpha gmbh germany 26843 fmg-flugschule germany 1595 frenzel g germany 4232 frontier airlines united states 38973 fuenfte xr-gmbh germany 9243 germania fluggesellschaft mbh germany 28944 germanwings gmbh germany 34841 gibbs international, inc. united states f10232 gruss & company united states 33827 gabinette (ang) angola 36504 galaxias aviation virgin islands, british 22807 gas air service gmbh germany 25027 geko trade germany 3349 general motors united states 36747 geojet luftfahr. (2) germany 38591 germania express germany 31914 german sky airlines germany 33821 ge capital b.v. netherlands 35147 ge capital switzerl. switzerland 35803 ghassan ahmed al united arab emirates 25642 global avtn bermuda bermuda 34848 global a/c consult united states 38372 globo aviacao brazil 23743 gomel airlines belarus 22366 government croatia croatia 22370 government macedonia macedonia, the former yugoslav republic of 38832 greenway jets united states 2395 grob aircraft ag germany 32172 gulf jet united arab emirates 25111 g-92 kft hungary 28618 haworth transport united states 32953 heidelbergcement ag germany f11187 herc management services llc united states 33269 herrenknecht aviation gmbh germany 37030 hamburg airways germany 26105 hansgrohe se germany 32580 haslberger finanz. germany 37376 hatay air marmara turkey 31519 hawker hunter avtn united kingdom 31103 homac aviation ag germany 36597 hong wei co ltd taiwan 26281 htm helicopter trave germany 27680 hurkus havayolu tasimacilik ve tic a.s. (d.b.a. freebird airlines) turkey 24664 intermap technologies united states f10652 iac falcon holdings unknown 38692 ideavillage products united states 35785 ifm traviation gmbh germany 25785 ilyushin aviation russian federation 37757 infinum altido inc. russian federation 37194 interglobe aviation india 1528 iranair iran, islamic republic of 37529 ise information sys. germany 1562 jat airways serbia 21723 joint stock company ural airlines russian federation 35760 jeju air korea, republic of 2200 jetair flug gmbh germany 16761 jetflight aviation inc. switzerland 36889 jetstar pacific viet nam 38213 jetstream avtn (oe) saudi arabia 3328 jets executivos mexico 11307 jet executive int. germany 27505 jet group ltd israel 21462 johnson controls united states 28591 johnson ctrls switzerland 36272 jordan intnl china 32107 juneyao airlines china 36509 junker erwin grindi czech republic 23758 kimberly-clark corporation united states 25800 knauf astra ltd united kingdom 32568 kompass gmbh & co. kg germany 1610 karmann gmbh germany 31171 kazaviaspas kazakhstan 22239 kiev aviation plant ukraine 1652 korean air lines co., ltd. korea, republic of 21632 krasnojarsky airline russian federation 33182 kugu havacilik turkey 37720 k5-aviation gmbh germany 28399 liebherr gesch\u00e4ftsreiseflugzeug gbr germany 15456 luftfahrt-bundesamt germany 3857 lufthansa cargo ag germany 27838 lufthansa technik ag germany 36476 lanara ltd united kingdom 29352 langner e germany 35538 lear 45-086 hold cor united states 6383 lech-air flugzeug germany 20222 lgm luftfahrt gmbh germany 38914 libra flugzeug gbr germany 28576 libra travel switzerland f12832 lincare leasing llc united states 1767 ltu lufttransport germany 34372 lufthansa techn. ag germany 34305 lufthansa tech. vip germany 26498 luft avtn charter australia 35742 lwe vermietungs gmbh germany 38512 microstrategy services corporation united states 24270 montenegro airlines montenegro 21072 mahan air iran, islamic republic of 21878 makedonski aviotrans macedonia, the former yugoslav republic of 12521 marxer anlagen germany 36372 mat airways macedonia, the former yugoslav republic of 38074 mena aerospace (ob) bahrain 19999 menekse havayollari turkey 37597 meridian+ russian federation 37975 millennium aviation austria 28438 mlw aviation llc united states 25067 mng havayollari ve tasimacilik a.s. (mng airlines) turkey 3057 moellers maschinen germany 31944 myn aviation saudi arabia 38209 mz transportation germany f13551 m-bjep ltd isle of man 24502 m. bohlke veneer corp. united states 35125 nasser ltd cayman islands 12218 nike, inc. united states 26118 nasa ames center united states 33963 national legacy kuwait 30581 nayak aircraft serv. germany 34805 nayak international germany 11061 neumeyr fluggeraete germany 15551 new yorker group germany 24661 north american jet united states 29267 novellus systems united states 31791 novespace france f10785 n16fx trust united states f12724 n250rg llc united states 25059 omni air international united states 2073 ostfriesische lufttransport gmbh germany 567 obo jet-charter gmbh germany 33138 oca international germany 2061 omnipol czech republic 36743 orange aircraft (2) netherlands 8236 owens-corning united states 12648 pacelli-beteiligungs gmbh & co. kg germany 33666 pakistan aviators and aviation (pvt) ltd pakistan 29731 parc aviation ireland 775 pentastar aviation, llc united states 852 paragon ranch united states 23471 pct powder coating technologies intl. sarl switzerland 10690 pegasus hava tasimaciligi a.s. turkey 19475 peters gmbh germany 37609 petropavlovsk mc russian federation 4265 phifer wire products united states 5225 phoenix air gmbh germany 3085 picton ii ltd bermuda 30230 polet acft mngt bermuda 36251 pollard acft sales united states 37040 preiss-daimler germany 28157 presidential avtn united states 34505 princess aviation lebanon 29307 privatair gmbh germany 34553 private jet hold. virgin islands, british 12196 private wings germany 3343 p&p promotion germany 19750 quick air jet chartr germany f11900 rentair uk ltd united kingdom 27446 rhema bible church united states 606 robert bosch gmbh germany 37057 radic aviation saudi arabia 30124 rae \u2014 regional air germany 32083 ray enterprises united states 19436 regio air mecklenbrg germany 33032 reliance commercial united arab emirates 30938 riksos turizm lt turkey f13620 rnj gmbh. & co kg germany 32723 rsg rental services germany 29927 ruag aerospace serv germany 37464 ruag switzerland switzerland 36233 ruiz, l germany 38246 rusaero russian federation 9200 ryan intl airlines united states 38368 ryan intl airlines 2 united states f12122 safeway, inc. united states 24784 samsung techwin co., ltd korea, republic of f10701 servicios aereos regiomontanos, s.a. mexico 21734 siberia airlines russian federation 9354 skywork airlines ag switzerland f12005 spiral, inc. united states 29841 spirit of spices gmbh germany 10201 sunexpress (g\u00fcnes ekspres havacilik a.s.) turkey 28362 sun d\u2019or international airlines ltd israel 12878 s\u00fcdzucker reise-service gmbh germany f10788 sap america inc. united states 18991 sap ag germany 21282 schrott wetzel gmbh germany 5031 schwarzmueller austria 30971 searay bd100 south africa 35352 segrave aviation inc united states 31846 sg finans a/s norge sweden 27571 shanghai airlines china 29540 shenzhen airlines china 27735 sik-ay hava tasimacilik a.s. turkey 1034 sirte oil libya f12146 sirvair, s.a. de c.v. mexico 32179 skippers aviation australia 34392 skybus kazakhstan 32816 skybus airlines united states 19819 skyplan services canada 2477 sky jet switzerland 37940 sky swallows ltd. russian federation 25050 smatsa doo serbia 32544 sms aviation gmbh germany 31870 sm aviation germany 33747 somon air tajikistan f11331 southlake aviation llc united states 36224 spectra energy united states 26725 spirit airlines 2 united states 36094 ssp aviation india 23935 star aries shipmgmt cyprus 29368 star aviation ltd. bermuda 15526 state enterprise antonov design bureau ukraine 32361 strong aviation kuwait 30086 summit air charters canada 37379 sunexpress deutschl. germany 36720 swiss av consultants switzerland 28910 swiss global jet mgt switzerland 2681 thai airways international public company limited thailand f10445 thomas h. lee partners united states 14993 thyssenkrupp dienstleistungen gmbh germany 31353 tidnish holdings limited canada 2758 turkish airlines thy turkey 8360 taca el salvador 38118 tarona ltd virgin islands, british 35978 tathra international virgin islands, british 32576 tb invest group czech republic 31566 team aviation germany 33120 tec aircraft leasing austria 36210 tesla air switzerland 35936 tiger hercules corp taiwan 21908 tokoph d p south africa 37070 trevo aviation ltd united kingdom 1389 tuifly gmbh germany 33495 turbojet kft hungary 33979 turkuaz airlines turkey 36760 t\u2019way air co ltd korea, republic of 32741 ulla popken gmbh germany 8960 united parcel service co united states 27079 ukrainian mediterran ukraine 24948 uksatse ukraine f10464 usaa united states 29839 usa 3000 airlines united states 4692 us airways, inc. united states 26886 utair aviation, jsc russian federation 31669 vacuna jets limited bermuda f10791 vecellio management service united states 2833 viessmann werke gmbh & co. kg germany 18671 volga-dnepr airlines llc russian federation 31984 varig logistica sa brazil 37759 venture avtn group united states 5198 vhm schul & charter germany 31758 vivat trust ltd. united kingdom 31815 volaris mexico 2840 volkswagen ag germany 2812 vrg linhas aereas s/a brazil 30605 wheels aviation ltd germany 25225 windrose air jetcharter gmbh germany 27514 wirtgen bgmbh germany 36235 waterloo aviation canada 12066 wdl aviation germany 24113 weber management germany 1323 weka flugdienst gmbh germany 34391 whs consulting ag switzerland 10834 wiking helikopter germany 33317 winair austria austria 34169 wizzair ukraine llc ukraine 36967 woelbern flight 01 germany 37044 woelbern flight 02 germany 2930 world airways united states 31769 xl airways germany gmbh germany 32403 xrs holdings, llc united states 36920 xr-gmbh germany 5960 zeman ftl germany 33948 zeus taxi a\u00e9reo brazil 31485 328 support services germany a11495 operator using tail nb: n450t unknown a11501 operator using tail nb: n62914 unknown a11751 operator using tail nb: n77080 unknown a11508 operator using tail nb: n880gc unknown a11510 operator using tail nb: n903g unknown a12912 operator using tail nb: vpcbk cayman islands a11558 operator using tail nb: xafrd unknown estonia crco identification no. operator name state of the operator 34613 abelia trading ltd cyprus 22213 enimex estonia 18219 estonian air estonia 38113 fl technics ab lithuania 22574 mil japan japan 10937 mil russia russian federation 1117 mil switzerland switzerland 36227 police & board ee estonia 35109 small planet (ee) estonia 38604 smartlynx estonia estonia 30036 uls airlines cargo turkey 36496 zambezi airlines zimbabwe greece crco identification no. operator name state of the operator 20514 aegean airlines greece f12684 avenge inc united states 37967 aeolian airlines greece 35662 aerojet services united states 31367 aeroland greece 23232 aerosvit ukraine 24601 aero-kamov russian federation 31586 african express awys kenya 28539 aircraft supprt&srvc lebanon 30742 air columbus ukraine ukraine 29972 air link ukraine ukraine 37802 air traffic ltd kenya 31252 amref flying doctors kenya 37966 aspamia llc united states 34238 astra airlines greece 38330 aviation sciences co saudi arabia 26678 barrick gold explor. canada 28245 belair airlines ltd switzerland 34069 belrescueavia belarus 20501 bluebird aviation kenya 35368 blue bird airways greece 38646 business avtn asia china 31747 caac flight inspect china 35729 cassel invest ltd virgin islands, british 31895 centavia serbia 31412 comeravia venezuela, bolivarian republic of 36915 comlux exclusive switzerland 36113 conquistador helo united states 19644 costair ltd greece 29987 crimea universal ukraine 33761 dal group (sudan) sudan 36466 desinence ltd virgin islands, british 23372 diamonds of russia russian federation 25895 donbassaero ukraine 32795 dove air inc united states f11403 dragon leasing corp united states 30350 eagle air ltd uganda 35299 elite airlines greece 37223 engaly ltd ireland 31744 european air crane italy 35101 euro aviation greece 32903 executive airl.pty australia 35228 first airways greece 34427 flight options (aus) australia 31507 flying research uu russian federation 9532 fl aviation new jers united states 31722 gainjet aviation greece 31313 ghadames air transp libya 31659 ghalayini i egypt 33178 global avtn south africa 29050 goliaf air sao tome and principe 38025 gryphon airlines kuwait f10233 gs 150-217 llc united states f11417 gs200 inc trustee united states 24651 gulf helicopters co qatar f12006 hanwha chemical corporation korea, republic of 23443 hcaa greece 34731 helicopters (nz) new zealand 32243 hellenic imperial greece 25221 helog ag switzerland 36373 heritage acft ltd united kingdom 36043 heritage avtn dev. united kingdom 32668 interisland airlines philippines 38792 inter iles air madagascar, comoros, reunion 26787 intracom greece 31881 intralot united states 36434 islandsite invest. south africa 31621 jadayel aviation saudi arabia 31622 jet airlines jsc kazakhstan 33768 jp air ou estonia 32238 jubilant enpro pvt india 33560 kenrick ltd israel 30724 kaizen avtn united states 29503 ksenodoxeia ellados greece 29979 lao airlines lao people\u2019s democratic republic 29995 lexata greece 32949 life line aviat. (2) greece 35265 linair ltd. united kingdom 25549 macedonian airlines greece 32732 mckinley capital united states 29201 merpati nusantara 2 indonesia 1099 mil greece greece 21948 minair central african republic 29509 ministry extreme uk ukraine 33733 mojo avtn inc/n818lk brazil 36432 new tempus jets inc united states 34624 olympic air greece 2055 olympic airlines greece 24067 orascom egypt 21711 orenburg airlines russian federation 22404 oxy usa united states 30316 pakistan state pakistan 37162 paladin energy ltd australia 24760 palestinian airlines palestinian territory, occupied 22981 palmyra aviation ltd greece 38843 pan havacilik ve tic turkey 27002 paradise avtn greece 34445 pebuny llc united states 27649 pecotox air moldova, republic of 28119 polish morski poland 34853 port sivil havacilik turkey 32308 privilige jet airl. jordan 33252 proflight comm. svcs zambia 35750 quick flight limited india 37437 ram air services llc united states 30685 refuse equipmnt mftg saudi arabia 27798 reliance com.dea.ltd india 35603 rostvertol-avia russian federation 23672 russian sky airlines russian federation 37342 safari link kenya 33531 semeyavia jsc kazakhstan, kyrgyzstan 36327 seven x aviation montenegro 32636 short stop jet charter australia 34496 sikorsky aircraft 2 united states 29176 sincom avia ukraine 32837 skol airline russian federation 31109 sky express greece greece 31806 sky wings airlines greece 22361 southern acft consul united kingdom 29441 swiftair hellas greece 24773 swift flite aviation south africa 9012 s & k bermuda ltd bermuda 32418 tahe hava danismanli turkey 35475 taimyr airline jsc russian federation 31056 tamir airways israel 31819 trans aviation kuwait 28601 travco air egypt 9459 universal air link united states 38722 vaxuco viet nam 20044 veravia vernikos greece 35002 vertir armenia 37519 wcc aviation inc philippines 35700 wem lines sa greece 25058 world healing center united states 35842 world healing cent 2 united states 24805 yamal russian federation 7307 zahid tractor saudi arabia 29325 zen air llc united states 35716 zr aviation lebanon a11496 operator using tail nb: n517af unknown a11522 operator using tail nb: ppbir unknown a12908 operator using tail nb: vhwxc australia spain crco identification no. operator name state of the operator f10630 aerolider, s.a. de c.v. mexico 29159 airmax, llc united states f10006 air products & chemicals inc. united states f10612 al tameer co. ltd saudi arabia f10332 astra 136 llc united states f11141 averuca, c.a. venezuela, bolivarian republic of 19709 aerodata belgium belgium 36647 aerogal ecuador 29663 aerolane ecuador 160 aerolineas argentina argentina 26248 aerolineas sol mexico 20010 aerolineas tehuacan mexico 33221 aerolinea principal chile 38432 aeromaster del peru peru 38967 aeromaster taxi brazil 30520 aerotaxi los valles spain 2880 aerovias de mexico mexico 4648 aero angeles mexico 29534 afrique cargo serv senegal 36793 airlease corporation united states 34981 airlift usa llp united states 38204 airline comlux kz kazakhstan, kyrgyzstan 20066 airlink south africa south africa 29323 air amder mauritania 38846 air class lineas uruguay 24500 air comet s.a. spain 9345 air europa spain 36047 air logistics (lux) luxembourg 22380 air nostrum spain 31681 air tractor europe spain 36637 alba star s.a. spain 32075 alpema & tourism spain 35203 al jaber aviation united arab emirates 29581 amb group united states 26217 american flyers s.l. spain 38970 american jet s.a. argentina 31409 american king air fe united states 34891 andalus lineas aer. spain 14376 angel martinez ridao spain 26796 ansett worldwide australia 31725 antrak air ghana ghana 21575 arabasco aviation saudi arabia 32948 arkas s.a. colombia f12734 aspen trading corp united states 37408 associated avtn (2) nigeria 31605 astar (rch flights) united states 36022 atlas executive air spain 9456 audeli spain 35532 avex air training south africa 21660 aviacion comercial mexico 460 avianca colombia 31593 avionica suver s.l. spain 33149 avpro inc (2) united states 32450 awair united kingdom f10074 bank of america, na united states f12160 bank of utah united states 38518 benipaula inc united states f12165 bradleyville, ltd united states f11811 bank of utah trustee united states 38654 barragan miguel mexico 32565 bellon aviation ltd. switzerland 2621 binter canarias sa spain 32392 bionic aviation cc south africa 35545 brasil warrant brazil 19815 bristow heli nigeria f11870 caleton holdings cayman islands 32564 carabo capital united states f12156 carefusion corporation united states f11018 condor express s.a. argentina f10127 conforto empreendimentos e paricipacoes ltda brazil f10710 contessa premium foods united states f12168 corimon ca united states f10551 covington aviation united states 27598 cabo verde express cape verde 33475 calima aviacion sl spain 30834 canadian metro airl canada 38558 canarias airlines spain 35186 capiteq australia 23687 casa air services morocco 32893 caverton helicopters nigeria 29796 ceto marketing s.a. united kingdom f10567 citgo petroleum corporation united states f10706 ci-ten leasing corp. united states 36279 clearskies australia 38420 comp. nat. nav. sas france 37198 conf. brasileira brazil 36755 consorcio cjpp brazil 31644 conviasa venezuela, bolivarian republic of f11327 cook canyon (gp) llc united states 32284 corporate oil & gas nigeria 24180 corp ygnus air s.a. spain 35909 covington aviation united states 36833 coyaba llc united states 37293 cpc sa united states f11342 csc trust co of delaware trustee united states 31491 csim air united states 31613 c.s.p.societe mauritania f10136 dayco properties ltd united states 26776 dean foods united states 37252 delaware gg inc united states 29208 des r cargo express mauritania 35756 dnest aviation malaysia 3464 dodson aviation united states 33251 dornier nigeria nigeria f10915 electric boat corporation united states 736 eads casa spain f12879 eagle air services corp united states 8808 eastman kodak united states 35658 east coast jets inc united states 31715 ecuato guineana (2) equatorial guinea 6101 edelweiss suisse switzerland 37813 edifica 2000 spain f12753 edinton holdings usa inc united states 35209 eheim verwaltungs germany 30842 ejs-aviation service brazil 35607 elysian airlines guinea 38631 emb equipment llc united states f13610 emsi aviation united states 31186 enguia gen ce ltda brazil 24823 eurocontinental spain 38965 eurocopter espana sa spain 7968 eurocopter france france 38902 evolution asset mngt united states 38423 execuflight inc united states 27226 executive airlines spain 32736 executive air svcs united states 26852 executive skyfleet united states 31653 exec jet service (n) nigeria 31802 flo-sun aircraft, inc. united states 35238 fairmont avtn comp switzerland f12978 father & son air llc united states 18767 first intl avtn united states 35848 flana south africa 22596 flightline sl spain 38894 flight plans soluti united states 31915 flyant servicios aer spain 31970 flying falcon united states 26564 fl aviation florida united states 24821 formacion aerofan sl spain 32961 frapmag ltd united kingdom 31564 fugro aviat canada canada 36054 fuji dream airlines japan 35955 fuluca investments south africa f10221 ginnaire rental inc. united states f10226 glass aviation, inc. united states 4402 gestair spain f10220 gg aircraft llc united states 38732 global five holdings united states 32506 goal verwaltungs (2) germany 30962 gof air sa de cv mexico 28810 goldner d united states 28586 go ahead internation bermuda 34043 grand china express china 39058 grass green ii llc switzerland 28228 guarda costeira gv cape verde 27295 hagel w austria 32525 harpo inc united states 31805 harvard oil & gas canada 28012 hawkaire united states 38138 hebei airlines ltd china 37568 helitt lineas aereas spain 28448 helvetic airways switzerland 31991 hennig. south africa 34338 hispania flyjet spain f11786 hi flite inc united states 28615 hola airlines s.l. spain 33213 hollywood aviation united states 31093 hong kong express hong kong sar 34316 hyundai colombia colombia 31848 hyunday colombia colombia f11875 h&s air, llc. united states 1475 iberia spain 38329 iberia express spain 25406 iberworld s.a.u. spain 25843 ice bird switzerland 10117 ilfc united states 27097 inaer av.anfibios spain 1416 inaer heli.off-shore spain 4470 industrias titan spain 35945 insel air aruba 37049 insular class sl spain 36530 interaliment s.a.l. lebanon f12784 international aviation llc united states 32557 intl concerts virgin islands, british 31816 intl private jet switzerland 33401 intl trade holding kuwait 30947 irs airlines ltd nigeria 29121 islas airways spain 39033 itabira agro industr brazil 35962 i fly ltd russian federation f10912 jorge gregorio perez compac argentina f10284 jupiter leasing inc. united states 31247 jair south africa 38971 jazzya investments spain 38805 jcg air mexico f11143 jem investments llc united states 36363 jem investments united states 28372 j.w. childs associates united states 34608 kama aviation russian federation 22691 kavminvodyavia russian federation 34463 kaz air jet kazakhstan 32291 kelly corp united states 30722 king air & travels nigeria 22866 kogalymavia russian federation 34665 kunpeng airlines china 32826 lewis aeronautical united states 32518 lai venezuela, bolivarian republic of 1689 lan airlines sa chile 32926 lan peru sa peru 30440 lark avtn united states f12766 las eugenias aircraft holdings llc united states 34764 legacy acft holdongs united states 33087 lemco holdings ltd. bermuda 36906 lets fly sl spain f10606 lhf holdings inc. united states 35540 libyan caa libya 37675 lider aviacao brazil 8562 lider taxi aereo brazil 34815 lift ireland leasing ireland 32711 litoranea linhas aer brazil 34783 llc nord wind russian federation 32253 lth jet leasing brazil 38302 lufthansa technik germany f13442 michigan aviation llc united states f11439 macys corporate services inc united states 32725 mali air express mali 26115 medair charter south africa 26957 menajian united states 38791 menorca llc united states 38507 meraj air iran, islamic republic of 14322 mexicana mexico 34331 mikes airplane rent2 united states 1095 mil spain spain 38536 minoan air s.a. greece 26896 mobil nigeria 2 nigeria 10262 monarch gen aviation switzerland 35701 multipromotur s.l. spain f11397 m g a 546 leasing corp united states f12854 m&n equipment llc united states 35759 nal asset management ltd united kingdom 32502 nasair saudi arabia 604 naysa spain 37438 neo taxi aereo ltda brazil 31792 nht linhas aereas brazil f10331 nii holdings inc. united states 31834 nita jet united states 39070 nnp holding s/a brazil 36142 noar linhas aereas brazil 1997 nomads united states 30519 nordjet airlines sl spain 18907 norman aviation united states 32556 nygren u sweden f10321 n t air, inc. united states f11388 n450je llc united states 32396 oboden ibru united arab emirates 35840 oceanair taxi aereo brazil 24549 odyssey avtn united states 33704 orionair s.l. spain 23017 perm airlines russian federation 33299 palm aviation united arab emirates 37672 passaro azul taxi ae brazil 35266 pcs aviation services, llc united states f11164 pdvsa petroleo s.a. venezuela, bolivarian republic of 8455 personal jet florida united states 35295 phoenicia aviation lebanon 31257 pick n pay (2) south africa 32819 pirinair express sl spain 35542 portside intl ltd united kingdom 32241 presidential(n981bw) united states 32000 privilege style sa spain 32852 priyan foundation united states 37381 promerca intnl s.l spain 32480 pronair airlines sl spain 29378 pullmantur air s.a. spain 29804 punto-fa spain 27231 quantum air spain 34864 q jets aviation canada 33067 rainbow air venezuela, bolivarian republic of 35747 ramsay aircharter united states 12856 raytheon aircraft united kingdom f11770 real world tours inc united states 26960 red wings cjsc russian federation 32100 ring air united states 35605 rpk capital llc united states 34812 rpk capital mngt united states 33521 ryjet spain 37862 starwood management llc united states 38250 saeta sl spain 36517 saicus air s.l. spain 25502 sal express sao tome and principe 32602 santana textil brazil 29057 santa barbara (2) venezuela, bolivarian republic of 37768 sapetro aviation ltd united kingdom 37164 sasemar spain 29825 sas institute united states 32195 sata venezuela venezuela, bolivarian republic of 37785 sde sa belgium 36925 sea sa argentina 37250 senegal airlines ltd gabon 30170 serair transworld spain 37448 seripatri particip brazil 30674 sev aereo policia spain 36232 sienna corp services switzerland 34785 sierra nevada corp. united states 35494 skyplan fzc united arab emirates 35092 skyway ltd. georgia 33719 sky air world australia 32416 sky helicopteros sa spain 11926 sonair angola angola 33250 sosoliso a/l (2) nigeria 19182 sotan brazil 36602 south aviation inc united states 31632 south east asian philippines 4298 spanair s a spain 28727 spenaero united states 31936 squadron avtn svcs bermuda 1485 stockwood v united states 30064 streamline russia russian federation 27934 sugar pine aviation llc united states 34009 sunrider corporation united states 33679 svs aero costa azaha spain 11309 swiftair espana spain 2638 swiss air ambulance switzerland 23071 s argentina argentina f12239 tejria services limited, bermuda bermuda f11131 transportes aereos tauro, s.a. de c.v. mexico 31288 tag avtn espana spain 34933 tailwind airlines turkey 12249 tam avia\u00e7\u00e3o executiva e t\u00e1xi a\u00e9reo s/a brazil 22992 tatarstan airlines russian federation 31963 taxi fly group sa spain f12830 tdc management llc united states 37642 termo norte energia brazil 35745 tianjin airlines china 34310 tiger aircraft trad. united states 34198 titan avaition united arab emirates 37007 trabajos extremenos spain 35159 tramas textiles sa venezuela, bolivarian republic of 15453 transaero airlines russian federation 34609 transcon investments brazil 34330 transpais aereo mexico 36589 transp aereos xalapa united states 28247 trans aer boliviana bolivia, plurinational state of 38544 trim air charter united states 36812 trinidair uk ltd united kingdom 29974 turbor air cargo (2) senegal 34271 uaml air charter united states 24765 unicasa ind. moveis brazil 38903 unique jet aviation united states 36046 usn aviation llc united states 37185 utd bank of africa nigeria 8705 ver.schweiz.flieger switzerland 35913 vesey air llc united states 29086 vim airlines russian federation 35330 vircop jets s.l. spain 27339 virgin blue australia 38266 volotea s.l. spain 30190 vueling airlines spain f10475 westair corporation united states f12705 wca holdings iii llc united states 36955 wings jet ltd morocco 36586 win win services united states 35259 world wide ac ferry canada 34390 wtorre s.a. brazil 35374 xto energy inc united states 24793 zorex s.a. spain 24007 224th flight unit russian federation 26560 245 pilot services united states a11479 operator using tail nb: n142hc unknown a11488 operator using tail nb: n371fp unknown a11490 operator using tail nb: n410m unknown a11517 operator using tail nb: n9895 unknown a11523 operator using tail nb: ppbst unknown a12897 operator using tail nb: prfor korea, democratic people\u2019s republic of a11528 operator using tail nb: prgpa unknown a12901 operator using tail nb: prpsr korea, democratic people\u2019s republic of a12902 operator using tail nb: prpst korea, democratic people\u2019s republic of a11529 operator using tail nb: prptr unknown a11531 operator using tail nb: vhxcj unknown a12909 operator using tail nb: vpbhs bermuda a11552 operator using tail nb: vtstv unknown a11553 operator using tail nb: xaatl unknown a11556 operator using tail nb: xablz unknown a12919 operator using tail nb: xacmm mexico a11557 operator using tail nb: xacxw unknown a12920 operator using tail nb: xaeaj mexico a12921 operator using tail nb: xafem mexico a11559 operator using tail nb: xagmd unknown a12922 operator using tail nb: xagmo mexico a11563 operator using tail nb: xasky unknown a12925 operator using tail nb: xatei mexico france crco identification no. operator name state of the operator f10002 act two, inc. united states f10003 aerolineas centrales s.a. de c.v. mexico 32610 aerorio taxi aereo brazil 30304 air caraibes france 10054 air corsica france f12199 air fleet operations limited united kingdom 36155 alatheer aviation saudi arabia 36010 alpha jet (alabama) united states f10726 arcadia aviation llc united states f10038 au revoir air united states f10059 avenue distribuidora de veiculos ltda brazil f10060 aviation 604 ag switzerland 28417 aak company bermuda 38065 aar corp united states 31724 aas europe france 31439 abc aerolineas sa mexico 28588 abdullah said b. switzerland 36488 absolute aviation south africa 4306 accor sa france 31934 acft mgmt & trading united kingdom 31617 acft sarl 2 luxembourg 35097 actifly france f11808 adams office llc united states 30027 adam aviation united states 27910 advanced training sy united states 31600 aelis air services france 26891 aerogaviota cuba 33839 aerojet management germany 25901 aeromar airlines mexico 33014 aeronexus corp. ltd south africa 5461 aerostock france 30943 aero capital sas france 32371 aero jet corporate france 31785 aero saint exupery france 22257 aero services lf france 28041 aero svc corporate france 8491 aero svc executive france 30336 afrijet airlines(2) nigeria 28604 afriqiyah airways libya 36823 agcorp united states 1769 aigle azur france 2496 airbus oper. sas france 308 airbus sas france 24094 airbus transport france 4790 airby france 38148 airby france 38173 aircraft mgt svces belgium 30562 aircraft sale&lease luxembourg 32884 aircraft support lebanon 31015 airedale enterprise united arab emirates 18045 airfleet credit united states 18982 airflite united states 26897 airlinair france 182 air affaires gabon gabon 186 air algerie algeria 35192 air arabia maroc morocco 28684 air asia malaysia 29420 air austral 2 france 35175 air botswana co.bw botswana 30592 air burkina (2) burkina faso 29815 air cairo egypt 33288 air corporate france france 38966 air cote d\u2019ivoire c\u00f4te d\u2019ivoire 30879 air deccan india 32290 air division kazakh kazakhstan 227 air france france 231 air gefco france f877 air guyane france 35198 air guyane 2 france 32175 air horizon (togo) togo 30281 air ivoire (2) c\u00f4te d\u2019ivoire 31977 air king jet switzerland 32016 air leasing cameroon 252 air madagascar france 261 air mauritius mauritius 24636 air mediterranee france 12060 air nd france 24430 air print luxembourg 31913 air sarina switzerland 2564 air senegal intl senegal 5636 air seychelles seychelles 26152 air srpska bosnia and herzegovina 34196 air swift ltd. bermuda 25943 air tahiti nui france 31078 air turquoise sas france 12593 air vendee invest france 34296 air wing ltd belize 32481 air 26 angola 36825 akdn logistique france f10019 ala services, llc united states 21699 alcatel usa united states 17947 alenia aerospazio italy 32632 alljets capital avv russian federation 5117 all nippon airways japan f11476 aln (bermuda) ltd unknown 38428 alphaland corp. philippines 32601 alpha charlie united states 35733 alpha golf aviation monaco 34201 alpha star avtn svcs saudi arabia 37317 alpin skyjets ltd switzerland 26287 altona switzerland 2987 altria client svcs united states 35920 alwafeer air saudi arabia 8231 al anwae trading saudi arabia 28640 al misehal group saudi arabia 24197 al nassr ltd switzerland 30177 al-ghazzawi (n35gz) saudi arabia 27005 al-ghazzawi (n727gg) saudi arabia 38876 amac aerospace sg switzerland f836 american eagle united states 34234 american electric united states 8928 american home prod united states 25806 ameridair france 35837 amer group egypt f12696 aml leasing llc united states 32857 ancfcc morocco 32747 angodis angola 34393 anistante holding cyprus 38913 antares agropecuaria brazil 30530 aosky corporation united states f10036 apigroup, inc united states 984 apache aviation france 6188 apex oil united states 34185 aquarius aviation cayman islands 37184 argentre enterprise brazil 37878 arg ltda brazil 406 arkia israel al israel 22917 arlington acft (az) united states 28382 armavia aviacompany llc armenia 20337 artemis sa france 38575 art aviation flugbet austria 29210 asecna (senegal) senegal 8624 ashmawi aviation spain 38110 asyad holding co. saudi arabia 22135 atlanta jet united states 30506 atlas blue morocco 36380 avangard avtn ltd russian federation 17951 avdef france 34589 avel brao france 29467 avialair france 35748 aviamarket limited united kingdom f11782 aviation associates llc united states 29399 aviation capital grp united states 26160 aviation cmp canada 38193 aviation horizons saudi arabia 34340 aviation inc united states 38085 aviation link saudi arabia 33992 aviation partners 2 united states 33748 aviation starlink(2) canada 38198 aviatrax luxembourg 33558 avia treasury gmbh austria 25574 avient aviation zimbabwe 34211 avijet uk ltd united kingdom 36345 avionac france france f1026 avior unknown 23721 avirex gabon 33168 avtex air services australia 31420 awsaj aviation svcs libya 27710 axis airways france 36972 azul linhas aereas brazil f10079 beach capital management united states f10082 belair aviation llc united states f11004 billion mark ltd hong kong sar f10878 blue vista, llc united states f10647 bollor\u00e9 sa unknown f10834 boulder aviation management united states f13608 business jet access united states 37896 bam aviation llc united states 22230 banco safra sa brazil 12083 bangkok airways thailand 23830 bb aviation inc. switzerland 37668 beijing airlines co china 37358 beijing capital china 35267 bell financial corp venezuela, bolivarian republic of 7723 bell textron united states 28608 bergair switzerland 27140 berkut air kazakhstan 36116 best aero handling russian federation 32888 best aviation ltd bangladesh 35950 bf jet air ghana 27458 bhg flights llc united states 32788 bismillah airlines bangladesh 26292 bizair ltd united kingdom 25627 blue heron aviation switzerland 36583 blue horizon inv. cayman islands 28677 blue line france 36706 blue line 2 france 33691 bonel marketing s.a. switzerland 30067 bongrain benelux belgium 25099 boogie performance france 30550 bosnia airlines bosnia and herzegovina 35724 brasif sa brazil 34825 brassbox ukraine 34276 brass box ltd cyprus 21446 breitling switzerland 38488 bristow australia australia 637 britair france 8153 brume france 32896 bumi resources united arab emirates 36301 buquebus argentina 32260 bureau police aero. france 35325 burgan k kuwait 31315 burmester overseas virgin islands, british 32497 business aviation lg belgium 32630 business aviation 2 congo 37493 business jet travel ukraine 34152 busi jet intl. switzerland f10061 b h aviation ltd united states 34289 b2 flight llc united states f13111 cedel international investments, inc. united states 31812 cephalon united states f10556 challenger management llc united states f13215 cobalt resources, llc united states f10128 corporate flight alternatives, inc. united states 37649 caledonian hel. ltd united kingdom 32578 calvin klein studio united states 31994 canadian nat railway canada 37106 caoa montadora brazil 28583 capelink establish. switzerland 9122 cartier europe netherlands 34144 casam sarl france 37372 celina aviation ltd switzerland f12811 center air llc united states 29635 central managmt svcs united states 36944 certeco engineering austria 26842 cfpr france 35242 cfs air llc (n228kt) united states 20711 cgtm france 37115 chad government chad 29049 chc helicopters intl canada 29834 china cargo airlines china 12141 china eastern china 31087 churchill aviation united states 31221 churchill finance france 37193 clear sky associates taiwan f11398 cleveland peak llc united states 38305 club premier ltd switzerland 35400 club 17 s.a. russian federation 799 coca cola united states 35668 colt intl europe switzerland 36701 comfort jet avt united kingdom 4796 comilog gabon f826 commandement du transport aerien militaire fran\u00e7ais unknown 38652 comores aviation madagascar, comoros, reunion 28584 company tawiq switzerland 6535 consolidated contrts united kingdom 8338 copley newspapers united states 6369 corsair france france 12219 cox enterprises united states 35062 cpi aviation llc united states 31073 cp management united states 38602 credit suisse switzerland 3513 crown equipment united states 862 cubana cuba f12751 c & s aviation ltd united states 38938 c.a.group ltd virgin islands, british 5988 c.t.t.a. morocco f10134 dankjold reed aviation llc united states 27183 dartswift aviation, inc. united states 1139 dassault falcon jet united states 35657 d\u00e9dalus administra\u00e7\u00e3o e participa\u00e7\u00f5es ltda. brazil 7028 dow chemical company, the united states 27974 daallo airlines 2 djibouti 33242 dalcam llc united states 31467 dalia airlines luxembourg 3932 dallah albaraka saudi arabia 32855 dana executive jets united arab emirates 34168 darte holdings russian federation 18972 dassault aviation france 1058 dassault falcon serv france 37864 dda aviation united states 32809 dean phillips inc united states 11638 decaux france 35752 deccan cargo thailand 35353 delmun aviation svcs bahrain 31582 de roubin jean france 27665 diamair switzerland 32494 diexim expresso av. angola 35356 distant horizon israel 22389 douanes francaises france 38450 dsf flugzeugportfoli germany 24571 dswa united states 30876 dubrovnik airlines croatia 31133 dunmore homes united states 31577 d & d aviation united kingdom f10175 emax oil company united states 35820 eagles avtn mgnt united arab emirates 35705 eagle aviation europ france 9703 earth star united states 34303 eastindo indonesia 31743 east star airlines china 2850 easyjet switzerland switzerland 32591 ebony shine cayman islands 29279 ecuatorial cargo equatorial guinea 31985 egypt jet aviation egypt f12482 eiger jet ltd bermuda 25120 elbrus-avia air ent. russian federation 23028 eli\u2019s bread united states 1013 emerson electric united states 22291 enac france france 37188 enex aviation ltd united kingdom 36295 enhance aero france 38636 enhance aero groupe france 32775 equaflight service congo 34778 equajet congo 32084 equatorial guinea equatorial guinea 30005 eurl jc darmon france 34741 european flight sweden 27518 europe airpost france 34293 euro exec aviation services ltd united kingdom 35725 euro jet intl ltd united kingdom f10181 ewa holdings llc united states 36448 executive airshare united states 28587 executive jet a/c cayman islands 25073 executive jet chrtr germany 29282 executive jet srvcs denmark 26060 executive wings he egypt 32827 exec jet solutions united states 31131 express camel saudi arabia f12240 falconwing limited bvi virgin islands, british f10194 fjet management, llc united states f10203 fletcher jones management group united states f12819 falcon aircraft leasing llc united states 25553 falcon air express united states 15665 fal holdings arabia saudi arabia 31310 farner airwings switzerland 39047 fastjet tanzania tanzania, united republic of 37429 faycroft finance co. virgin islands, british 34313 fa 116 ou fa 137 inc switzerland 15911 fc aviation france 1147 federal express united states f12735 fg aviation llc united states f10191 fhc flight services llc united states 28540 fia (paris) france 34669 firefly malaysia 32846 first commercial united states 38268 first mandarin b.a china 38238 first reserve corp united states f10762 fj20-166, dba peregrine jet, llc united states 31665 fleet int avtn & fin united kingdom 35764 fleet mgt airways sa switzerland 21504 flicape pty ltd south africa 27942 flightexec canada 31640 flightinvest luxembourg 8542 flight levels united states 30136 flybaboo switzerland 30343 flying bird france 29223 flying finn oy finland 31775 flying m united states 33632 flymex mexico 30372 fly air sa france 34874 fly aviation svcs united arab emirates 28511 fly exec lebanon 33626 fly 18 switzerland 31116 focus air usa united states 32322 fortune air south africa 29147 fox aviation canada canada f12777 franklin lakes enterprises llc united states f11353 frc holding inc v united states f10651 freescale semiconductor, inc. unknown 35426 ftc consulting ag switzerland 2804 futura trading france 27867 future electronics canada 35173 f & l aviation united states f10223 glacial energy united states f12244 golden medal limited bvi virgin islands, british 32621 gabon airlines gabon 36117 gaetair sarl switzerland 38839 gaftren investments virgin islands, british 31746 galaxy airlines japan 36801 gama aviation fze united arab emirates 32749 geasa equatorial guinea 36630 gem aviation avv united kingdom 17928 genel havacilik turkey 34971 georgetown interstat united states 23693 georgian airways georgia 35885 georgian star georgia 9002 gie atr france 32233 gie-oder france 22850 giori roberto monaco 31182 giostyle llc united states 38481 gis aviation a.v.v. cyprus 37097 giv-sp air service russian federation f11804 global challenger llc united states 30539 global flight srvs united states 32997 global jet intl australia f12170 gold eagle ltd bermuda 32508 gough aviation south africa 22659 government montenegr montenegro 36865 go airlines (india) india f11352 great buy inc united states f12104 gwi asset management s.a. brazil f11448 gypsy baby llc united states 38975 gyro air ltd nigeria f11426 g & l aviation united states f10794 hagadone aviation llc united states 5362 halliburton united states f1434 horta, llc united states 37170 hospitalizacion clinico c.a. united states 31947 hagondale ltd united kingdom 31731 halcyonair cape verde 37326 hashim bin said saudi arabia 33959 hassanco s.a. switzerland 35878 hatta investments virgin islands, british 10105 hawker pacific pte singapore 33342 heavylift congo congo 37847 heda airlines ltd united kingdom 37863 heliconia ls france 36756 heliconia palmair morocco f11024 hendrick motorsports united states 36374 hermes executive virgin islands, british 37523 high performance 100 switzerland 21365 hill-rom united states 38899 hollyfrontier corp united states 38750 holypeak proprietary australia f10659 hsbc unknown 37195 hs air finance brazil 38904 hs air finance llc brazil f11464 hyperion air inc united states f10263 ithaca llc united states 24848 icec tour spol czech republic 37906 id air france 21442 ign inst geo nat lf france 29661 ikaros aviation avv ukraine 36740 imd airways spain 32492 india flysafe avtn india 31965 indigo (vi) india 36832 industry east europe switzerland 33071 industr. aeronautica colombia 33559 indycar aviation united states 34222 inlogs international undefined 23792 intercon usa united states 31081 interface ops llc united states 32801 interjet abc mexico 33654 inter american angola 37561 intl gaming tech united states 37780 inversiones davanic colombia 32524 investavia kazakhstan f11248 ip aviation l.p. canada f12706 island park aviation llc united states 33890 islena inversiones honduras 21879 israir airlines & tourism ltd israel 30038 ixair france f10277 jereissati participacoes s/a brazil f13613 jet select llc united states 28006 japat switzerland 31296 jazeera airways kuwait 32986 jbs consulting llc united states 31772 jcas switzerland 26998 jdp france france 36413 jereissati centros brazil 38453 jetalliance south austria 38847 jetstar japan japan 31137 jets rent avtn france 30713 jet aviation basel switzerland 30385 jet aviation fzco united arab emirates 26911 jet blue airways united states 37719 jet connections united kingdom 32217 jet cruising luxembourg 34614 jet direct aviation united states 33015 jet management sa switzerland 33769 jet one jsc kazakhstan 32848 jet premier one switzerland 38174 jet xpress c\u00f4te d\u2019ivoire 26479 jet 2000 russian federation 31581 jet4you morocco f12768 jimmie johnson racing ii inc united states f12712 joust capital iii llc united states 29395 jr executive lebanon f12041 key aviation llc united states 6510 kalair ltd. united states 34887 kalderon ltd united kingdom 28504 karthago airlines tunisia 34348 karthago private jet tunisia 38123 kas corporation ltd. lebanon 30709 kazavia kazakhstan 29190 kbbd united states 32381 kb home united states 12778 kelowna flightcraft canada 7129 kingdom holding co saudi arabia 34843 kostar airlines korea, republic of 35727 kredel international virgin islands, british 9858 kroll g switzerland f10290 kw flight, llc/central missouri aviation, inc. united states f10875 layla jet bermuda f13333 ligon air llc united states f10304 luciano antonio zogbi brazil 1971 laboratoire asl france 30455 las vegas jet united states 33111 layan intl. virgin islands, british 37923 la aviation switzerland 30595 leach capital united states 2816 legendair ltd. switzerland 13358 libyan air cargo libya 26342 lignes aer. congo. congo 4489 limited brands service company united states f904 lineas aereas sudamericanas colombia 1752 lockheed martin (ga) united states 25272 lotus air egypt 33450 lov\u2019air aviation france 24211 lowa ltd united states 28079 loyd\u2019s business jets poland f10303 lr enterprises management llc united states 37092 luis fuenmayor united states 31034 lukoil-avia swiss switzerland 29070 luxflight executive luxembourg 7764 lvmh services france 37071 lx aviation (spv)ltd virgin islands, british 19696 lyreco france f11360 lys llc united states f10306 macbens patrimonial ltda brazil f13614 mark anthony group inc canada f10420 marmalade skies llc united states 30280 marsico aviation, llc united states f12655 mass jet lease philippines f10313 mendota aircraft management united states 28010 mondoil united states 34423 macau jet intl macao sar 26383 magic condor ltd bermuda f11359 magic johnson entertainment inc united states 29993 mag aviation united states 34992 mainsail trading 93 south africa 32078 malibu consulting united states 34975 malu aviation congo 34019 mano river united states 37003 maritime investment monaco 1976 maritime investment and shipping co. ltd. bermuda 36263 maroc telecom morocco 1831 martin baker united kingdom 32707 masc air ltd cayman islands 27014 masterjet switz. switzerland 34840 maswings sdn. bhd. malaysia 33238 mauritania airways mauritania 37893 mauritanie airlines mauritania 27863 mayes & associates united states f12986 mb aviation llc united states 30315 mckinley acft hldng united states 31545 mda sas france 1855 mea air liban lebanon 38759 mega global air maldives 9689 melvin simon & associates, inc. united states 21443 meteo-france france 31140 me leasing united states f10316 mfp services llc united states 28986 mhs aviation sdn bhd malaysia 37403 miami ferry contract united states 36859 midas air united states 29971 middle east jet svcs lebanon 24019 mid east jet saudi arabia 34821 milletreize france 26724 million air salt lak united states 617 mil brazil brazil 702 mil canada canada 36031 mil ecuador airforce ecuador 1098 mil france france 35609 ministry def sloveni slovenia 36033 mish aviation svcs ghana 31556 mistral aereo canada 31331 mitre aviation ltd united kingdom 38259 mohamed bekkali morocco 35060 moiseev alex monaco 38782 montebello ltda brazil 32755 montrose global united kingdom 35455 mont blanc aviation bermuda 7058 morris communication united states 34441 moscow helicopter russian federation f11405 moss jerone s trustee united states 33834 m. square aviation bermuda f12094 naja loca\u00e7\u00e3o empresarial ltd brazil 32959 nofa aviation united arab emirates 34415 nomad aviation switzerland f1000 nam airlines united states 31025 natasha establisment united arab emirates 26668 national air service saudi arabia 28966 national aviation 2 egypt 34727 national city comm united states f11468 navair llc united states 38371 navintair inc united states 31097 nebula ltd. bermuda 38228 negri immobiliare italy 32626 newcastle aircraft united states 32424 new axis airways france 34651 new cairo real est egypt 35373 next generation vent united states 38125 nexus flt ops svcs saudi arabia 20855 nigerian police nigeria 35941 nile air egypt 31199 nissan nth america united states 32963 nordex air russian federation 38103 north star avtn ltd switzerland 10326 nouvelair tunisie tunisia 33212 npm management united states 22190 nwt aircraft united states 36629 nw nordwest switzerland 32861 ny jets transporter bermuda 31770 n304rj united states 32270 n349ba united states 32370 n72rk united states 29465 oakmont holdings, llc united states f10340 oakwood books, inc. united states 31395 outpost international, llc united states 32859 ovlas sa nigeria 30908 ocana assets ltd united states 38509 odyssee jet sa luxembourg 12316 oftc.inc. united states 28984 oldbury holdings united arab emirates 35132 omega vii france 34603 omya international switzerland 36166 onexp denmark 30957 one thirty nine luxembourg 32311 openskies france 31341 orient global avtn singapore 36943 orion air group united states 28050 outfitter aviation united states 4139 oyonnair france 31264 o air france f10350 pacific coast feather company united states 30188 pacific connection inc. united states 36039 paradox security sys canada f12236 power ease investments limited bvi virgin islands, british 31595 premier aviation russian federation 28189 proair charter germany 25856 pace cargo enterrp united states 31966 palmair aviation morocco 38406 paradox birds united kingdom 26289 paraffin air united states 12312 partnership 35 55 united states 36994 peabody energy united states 38284 peach aviation japan 37747 peregrine jet united states 35524 petro air libya 34403 pheebe limited united kingdom 33969 phenomair france 29691 pinnacle air group united states 32252 planet aviation uu russian federation f11455 pleasant aircraft leasing llc united states 2176 ppg industries united states 38693 premiair (wi) 2 indonesia 32060 premier air united states 36197 prestige jet jordan jordan 35261 prestoil sas france 32374 princely jets ltd. pakistan 35401 princess aviation dt tunisia 24429 privatair sa switzerland 35093 private jets luxemb. luxembourg 32346 profred partners llp united kingdom 36931 psd france f11206 pvm management llc united states 22432 qatar amiri flight qatar 38078 quest trading, llc united states 35828 related companies united states f10385 rex realty co united states f10387 rio bonito comunicacao ltda brazil f10391 roux investment mngt co united states 1427 rainin air united states 38278 rajshahi air ltd bangladesh 36817 rcr jets ag switzerland f11026 rd hubbard enterprises inc. united states 34087 real executive gmbh switzerland 37695 real fly sarl morocco 31655 reatex invest virgin islands, british 28265 regional cae france 2232 regourd aviation france 30061 reims aviation ind france 23719 rida aviation ltd bermuda 34680 rjh advisory united states 31630 rjm aviation chad f10973 rj corman aviation services llc united states 32627 rnw enterprises, llc united states 31978 romeo mike avtn united states 30374 ronso sa de cv mexico 31808 rotor trade 2 united states 31026 roust trading united arab emirates 36887 route 450 investment brazil 27737 roxbury technologies switzerland 258 royal air maroc morocco 37548 rsr-614rd united states 35879 rubicon aviation united kingdom f12601 sapphire international group, inc united states 37718 sfera jet llc russian federation 38579 sino jet management limited china f10403 skye gryphon, llc united states f12484 sonic financial united states f10419 stephens investment holdings llc united states f11008 success master ltd virgin islands, british 5967 synthes usa sales llc united states 33152 saad air ltd bahrain 22756 sabrina fisheries united states 38042 saby finance russian federation 27640 saesa spain 37497 safeguard solutions aruba f11791 saf flight llc united states 34967 saintex aero sarl france 25946 salem aviation saudi arabia 5373 satena colombia 36114 saucar limited united kingdom 5432 saudi oger saudi arabia 20462 sbd bretonne develop france 31959 sbm group united states 32560 scd bv netherlands 28744 schreiner cameroun cameroon 31358 scm aruba a.v.v. aruba 32411 scotts miracle-gro united states 22328 securite civile lf france 36018 segeris capital ltd brazil 1249 selia france 27881 serlux luxembourg 33112 seventh sense star bermuda 35652 sfd russia russian federation f12875 shadowfax llc united states 24337 shar ink russian federation f12810 shorenstein properties llc united states 38829 siam land flying ltd thailand 30513 sichuan airlines (3) china 5468 sigair ltd bermuda 34418 sigma aviation ireland f12744 silver lake aviation llc united states 32728 silver ventures inc united states 2466 sirius switzerland 32892 sirte oil company libya 24200 sit-set ag switzerland 35424 sj management llc united states 37810 skyfirst france 37558 skylux sa switzerland 38576 skyscraper ltd united kingdom 30105 skytraders pty australia 34050 skyway ltd russian federation 19462 skywork airlines switzerland 38247 sky liner aviation switzerland 27746 sk travel united states 35371 sl management united states 32149 smart aviation france 32805 smart aviation he egypt f13550 sme equipment leasing united states 29738 snc boetos france 30770 snc cavok france 37669 sns importadora brazil 31695 sn air mali mali 33859 sobeys capital incorporated canada 3517 sofaxis france 22730 sogerma france 26645 sonnig switzerland 38553 sorens group ltd russian federation 26378 southern airlines nigeria 21791 southern cross intl netherlands 5752 southern cross usa united states 35993 spacewing company saudi arabia 17921 specialised transp. united kingdom 37714 speedfly sarl france 27840 sphinx wings switzerland 32789 springway ltd russian federation 34595 spring mountain (2) united states 32899 sriwijaya world fuel singapore 26231 staff air service france 2574 starjet aviation switzerland 24204 starling aviation united arab emirates 32368 starlink aviation canada 31400 starr equipment united states 35477 star airways albania albania 35421 star jet ltd united states 28169 state air berkut kazakhstan 28156 steelcase united states 37550 steele aviation inc united states 32436 stensrud ventures united states 33040 stormjets sa switzerland 4488 strasbourg aviation france 35602 strategic air. sas france 35339 sukhoi civil acft russian federation 32592 sultan aviation united arab emirates 23210 sunrise (alshorook) egypt 31657 sun air (egypt) egypt 30157 super constellation switzerland 25392 swift-aero, jsc russian federation 30257 symphony master switzerland 33362 symphony master uae united arab emirates 38298 syphax airlines tunisia 22439 s algerie algeria 13351 s burkina faso burkina faso 22442 s congo (kin) congo 22575 s djibouti djibouti 22426 s gabon gabon 32125 s gambia (2) gambia 22438 s monaco monaco 22767 s namibia namibia 22524 s nigeria nigeria 22576 s senegal senegal 22977 s tchad chad 22656 s egypt egypt f10437 target corporation united states f10497 the yucaipa companies llc united states f10498 tracinda corporation united states f11188 trian fund management united states 38197 taa aviation ltd switzerland 27385 taf linhas aereas brazil 159 tag aviation suisse switzerland 26797 tak aviation uk ltd united kingdom 37224 tamara niger aviatio niger 4386 tam linhas aereas brazil 35843 tanela ventures ltd russian federation 26582 tassili airlines sa algeria 31962 tat leasing france 24156 taxi air jet-fret france 36518 terry brown canada 28634 thales france 21075 thermo fisher scientific united states 32042 the futura corp canada 30353 tiger airways singapore 31882 tiko air (2) madagascar 24764 total linhas aereas brazil 31535 toumai air tchad sa chad 31676 tower house consult. gambia 29860 tps united states 26086 tradlux luxembourg 8921 tranchant gaming france 34062 transair cargo svc congo 12193 transasia airways taiwan 32673 transavia france sas france f11432 transwestern transports llc united states 37172 trans aer mar cortes mexico 35158 tribeca avt partners united states 30112 trigana air service indonesia 21666 tudor saliba united states 2752 tunis air tunisia 31018 turnberry management united states 28237 twin jet france 28467 ty air inc united states 3329 united technologies corporation united states 28221 uas united aviation united arab emirates f10814 ueta, inc. united states 22150 ukraine air alliance ukraine 34820 unifox holdings ltd belize 32094 union pacific corp united states 38621 united avtn mgmt saudi arabia 28092 united healthgroup united states 33249 voyage international united arab emirates 24318 valavia france 28829 valiant aviation bermuda 10637 valmont united states 30253 ventura aviation monaco 34280 verein dc3 switzerland 37581 via jets ood.srl bulgaria 19445 vietnam airlines viet nam 33703 viking aviation ltd. united kingdom 23952 volare ukraine ukraine 38134 volpe aviation llc united states 27628 vulcan aviation united kingdom 23592 vulcan inc united states f10661 watersedge aviation llc unknown f10481 williams-sonoma, inc. united states 35615 wadi aviation saudi arabia 30891 waf ltd cayman islands 34990 waha capital united arab emirates 36777 walker air svcs australia 34886 watania airways kuwait 35351 waves jet lebanon 6924 wedge aviation united states 29491 wells aviation united states 34317 westjet falcon 50061 virgin islands, british f10476 wgl capital corporation united states 31779 whiskey romeo owner united states 31064 white lotus united states 32294 wilkes and mchugh united states 34191 williams intl co llc united states 31765 winds away united states 37331 windward aviation united states 36782 wings air indonesia 32929 wings over africa namibia 32063 wip trading switzerland 31938 wren acquisitions united states 23330 xl airways france france f10823 yet again, inc. united states 2941 yemenia yemen 11467 yum brands inc. united states 31488 yya aviation bermuda 35471 zest airways inc philippines 35614 zogbi luciano switzerland 32665 zyman aviation llc united states 29999 parc aviation bermuda 26915 171jc united states 34029 2m executive avtn virgin islands, british f11472 2 ts llc united states 24008 223rd flight unit russian federation 29177 900nb united states a789 operator using icao_code:aae unknown a791 operator using icao_code:ajt unknown a794 operator using icao_code:amf unknown a799 operator using icao_code:bcn unknown a802 operator using icao_code:bks unknown a808 operator using icao_code:bsq unknown a809 operator using icao_code:bul unknown a811 operator using icao_code:cey unknown a814 operator using icao_code:cfx unknown a816 operator using icao_code:cgc unknown a818 operator using icao_code:cgq unknown a819 operator using icao_code:cgt unknown a821 operator using icao_code:cpt unknown a823 operator using icao_code:csq unknown a825 operator using icao_code:ctl unknown a829 operator using icao_code:cut unknown a830 operator using icao_code:cxp unknown a833 operator using icao_code:del unknown a835 operator using icao_code:dra unknown a837 operator using icao_code:euf unknown a838 operator using icao_code:evo unknown a839 operator using icao_code:fac unknown a840 operator using icao_code:fad unknown a843 operator using icao_code:fav unknown a845 operator using icao_code:fgh unknown a846 operator using icao_code:fgi unknown a850 operator using icao_code:fiw unknown a851 operator using icao_code:fmi unknown a854 operator using icao_code:fof unknown a855 operator using icao_code:fog unknown a856 operator using icao_code:foh unknown a857 operator using icao_code:foi unknown a858 operator using icao_code:fot unknown a864 operator using icao_code:fwo unknown a865 operator using icao_code:fwr unknown a866 operator using icao_code:fwu unknown a867 operator using icao_code:fwx unknown a868 operator using icao_code:fwy unknown a860 operator using icao_code:fw0 unknown a871 operator using icao_code:gfi unknown a874 operator using icao_code:guf unknown a875 operator using icao_code:gui unknown a876 operator using icao_code:gut unknown a878 operator using icao_code:gwx unknown a879 operator using icao_code:hbj unknown a880 operator using icao_code:hdf unknown a881 operator using icao_code:hhd unknown a888 operator using icao_code:hpj unknown a889 operator using icao_code:hug unknown a893 operator using icao_code:inc unknown a901 operator using icao_code:ksb unknown a902 operator using icao_code:ktm unknown a906 operator using icao_code:ldu unknown a919 operator using icao_code:mar unknown a920 operator using icao_code:maw unknown a921 operator using icao_code:mei unknown a922 operator using icao_code:mpc unknown a924 operator using icao_code:mtn unknown a1002 operator using icao_code:ncb unknown a1011 operator using icao_code:pjw unknown a1013 operator using icao_code:ply unknown a1015 operator using icao_code:prs unknown a1016 operator using icao_code:pse unknown a1017 operator using icao_code:psv unknown a1019 operator using icao_code:ptl unknown a1023 operator using icao_code:rgf unknown a1024 operator using icao_code:rhi unknown a1028 operator using icao_code:ror unknown a1031 operator using icao_code:ruc unknown a1034 operator using icao_code:sbh unknown a1035 operator using icao_code:sbu unknown a1036 operator using icao_code:ser unknown a1038 operator using icao_code:skz unknown a1039 operator using icao_code:spc unknown a1041 operator using icao_code:svd unknown a1042 operator using icao_code:taf unknown a1044 operator using icao_code:tif unknown a1047 operator using icao_code:tke unknown a1053 operator using icao_code:tpq unknown a1063 operator using icao_code:vec unknown a1067 operator using icao_code:waj unknown a1068 operator using icao_code:wbs unknown a1069 operator using icao_code:wda unknown a1071 operator using icao_code:wia unknown a1073 operator using icao_code:wml unknown a1570 operator using tail nb:ac960 unknown a1794 operator using tail nb:af3943 unknown a1795 operator using tail nb:af3965 unknown a1796 operator using tail nb:af3967 unknown a2022 operator using tail nb:ahjt833 unknown a1507 operator using tail nb:arbv021 unknown a2023 operator using tail nb:arbv217 unknown a1509 operator using tail nb:bulg001 unknown a1104 operator using tail nb:cffev unknown a1582 operator using tail nb:cfgov unknown a1105 operator using tail nb:cfxcn unknown a1107 operator using tail nb:cgcgs unknown a1108 operator using tail nb:cgcmp unknown a1110 operator using tail nb:cgjln unknown a1586 operator using tail nb:cgktm unknown a1111 operator using tail nb:cglbb unknown a1112 operator using tail nb:cgrpm unknown a1589 operator using tail nb:cgtde unknown a1590 operator using tail nb:cgtkm unknown a1798 operator using tail nb:cg1501 unknown a1800 operator using tail nb:cg1707 unknown a1802 operator using tail nb:cg1712 unknown a1803 operator using tail nb:cg1719 unknown a1583 operator using tail nb:cg201 unknown a1804 operator using tail nb:cg2105 unknown a1805 operator using tail nb:cg2114 unknown a1806 operator using tail nb:cg2131 unknown a1591 operator using tail nb:cj950 unknown a1592 operator using tail nb:conde unknown a1571 operator using tail nb:c1501 unknown a1574 operator using tail nb:c1707 unknown a1575 operator using tail nb:c1712 unknown a1576 operator using tail nb:c1719 unknown a1577 operator using tail nb:c2001 unknown a1578 operator using tail nb:c2102 unknown a1579 operator using tail nb:c2105 unknown a1580 operator using tail nb:c2127 unknown a1594 operator using tail nb:dajgk unknown a1305 operator using tail nb:ev0065 unknown a1306 operator using tail nb:ev0068 unknown a1809 operator using tail nb:ev0681 unknown a1511 operator using tail nb:fav4402 unknown a1597 operator using tail nb:fbusn unknown a1598 operator using tail nb:fbvse unknown a1599 operator using tail nb:fbzcf unknown a1600 operator using tail nb:fd833 unknown a1601 operator using tail nb:fgatd unknown a1602 operator using tail nb:fghps unknown a1119 operator using tail nb:fgiei unknown a1603 operator using tail nb:fgizv unknown a1604 operator using tail nb:fgjan unknown a1606 operator using tail nb:fgoxa unknown a1608 operator using tail nb:fgusn unknown a1122 operator using tail nb:fgxes unknown a1610 operator using tail nb:fhcbm unknown a1611 operator using tail nb:fhfby unknown a2043 operator using tail nb:flint43 unknown a1613 operator using tail nb:fodsm unknown a1614 operator using tail nb:fodzh unknown a1615 operator using tail nb:fofly unknown a1616 operator using tail nb:fofqv unknown a1617 operator using tail nb:fogei unknown a1619 operator using tail nb:foghz unknown a1621 operator using tail nb:fognj unknown a1622 operator using tail nb:fogol unknown a1625 operator using tail nb:fogqx unknown a1627 operator using tail nb:fogva unknown a1628 operator using tail nb:fogxa unknown a1629 operator using tail nb:fogxb unknown a1630 operator using tail nb:fohqv unknown a1631 operator using tail nb:fohqx unknown a1632 operator using tail nb:fohqy unknown a1124 operator using tail nb:foijb unknown a1633 operator using tail nb:foije unknown a1125 operator using tail nb:foijf unknown a1634 operator using tail nb:foijg unknown a1635 operator using tail nb:foiji unknown a1636 operator using tail nb:foijp unknown a1638 operator using tail nb:foijs unknown a1639 operator using tail nb:foiju unknown a1640 operator using tail nb:foijy unknown a1642 operator using tail nb:foixa unknown a1128 operator using tail nb:foixd unknown a1643 operator using tail nb:foixp unknown a1644 operator using tail nb:fojgl unknown a1645 operator using tail nb:fojsr unknown a1646 operator using tail nb:fonly unknown a1129 operator using tail nb:foptp unknown a1130 operator using tail nb:forte unknown a1647 operator using tail nb:fosud unknown a1131 operator using tail nb:fotag unknown a1132 operator using tail nb:fotke unknown a1135 operator using tail nb:fraad unknown a1136 operator using tail nb:fraag unknown a1137 operator using tail nb:frada unknown a1138 operator using tail nb:fradb unknown a1139 operator using tail nb:fradc unknown a1142 operator using tail nb:fragl unknown a1143 operator using tail nb:fragx unknown a1086 operator using tail nb:frai unknown a1145 operator using tail nb:fraie unknown a1309 operator using tail nb:fraiin unknown a1146 operator using tail nb:fraij unknown a1147 operator using tail nb:frail unknown a1148 operator using tail nb:frain unknown a1149 operator using tail nb:fraio unknown a1150 operator using tail nb:fraiq unknown a1151 operator using tail nb:frait unknown a1152 operator using tail nb:fraiz unknown a1153 operator using tail nb:fraja unknown a1154 operator using tail nb:frajb unknown a1157 operator using tail nb:frapo unknown a1088 operator using tail nb:fraz unknown a1162 operator using tail nb:frazp unknown a1164 operator using tail nb:frazz unknown a1133 operator using tail nb:fra10 unknown a1134 operator using tail nb:fra12 unknown a1165 operator using tail nb:frbfa unknown a1166 operator using tail nb:frbfb unknown a1810 operator using tail nb:fr7495 unknown a1556 operator using tail nb:fuwf unknown a1171 operator using tail nb:fwfbw unknown a2044 operator using tail nb:fwio1fa unknown a2045 operator using tail nb:fwio3fc unknown a2046 operator using tail nb:fwio4fd unknown a1651 operator using tail nb:fwipg unknown a1811 operator using tail nb:fw23gw unknown a1648 operator using tail nb:fw231 unknown a1812 operator using tail nb:fw25gz unknown a1649 operator using tail nb:fw301 unknown a1650 operator using tail nb:fw311 unknown a1813 operator using tail nb:fw44hl unknown a1174 operator using tail nb:fzbcf unknown a1652 operator using tail nb:fzbcj unknown a1653 operator using tail nb:gu109 unknown a2047 operator using tail nb:gu109me unknown a1815 operator using tail nb:gu3675 unknown a2048 operator using tail nb:gu3677a unknown a2049 operator using tail nb:gu65745 unknown a2051 operator using tail nb:gy109bp unknown a1181 operator using tail nb:hbiux unknown a1182 operator using tail nb:hbjei unknown a1656 operator using tail nb:hhdct unknown a1184 operator using tail nb:hhdmx unknown a1658 operator using tail nb:hi657 unknown a1513 operator using tail nb:hi719ct unknown a1516 operator using tail nb:hi746ca unknown a2055 operator using tail nb:hi746ct unknown a1186 operator using tail nb:hi772 unknown a1517 operator using tail nb:hi772ct unknown a1659 operator using tail nb:hi776 unknown a1660 operator using tail nb:hi816 unknown a2056 operator using tail nb:hi816ct unknown a1661 operator using tail nb:hi819 unknown a1662 operator using tail nb:hi820 unknown a2057 operator using tail nb:hi820ct unknown a1663 operator using tail nb:hi830 unknown a2058 operator using tail nb:hi830ct unknown a1187 operator using tail nb:hi840 unknown a1188 operator using tail nb:hi851 unknown a1519 operator using tail nb:hk4492x unknown a1520 operator using tail nb:hk4493x unknown a1664 operator using tail nb:hu772 unknown a1666 operator using tail nb:ia370 unknown a1667 operator using tail nb:j6aaa unknown a1668 operator using tail nb:j6uvf unknown a1670 operator using tail nb:j8kim unknown a1671 operator using tail nb:j8slu unknown a1672 operator using tail nb:j8sun unknown a1674 operator using tail nb:j8vam unknown a1676 operator using tail nb:j8vbi unknown a1677 operator using tail nb:j8vbj unknown a1678 operator using tail nb:j8vbk unknown a1679 operator using tail nb:j8vbl unknown a1682 operator using tail nb:j8vbq unknown a1683 operator using tail nb:j8vbs unknown a1819 operator using tail nb:lcgtde unknown a2060 operator using tail nb:liat558 unknown a1689 operator using tail nb:li347 unknown a2061 operator using tail nb:llia558 unknown a1821 operator using tail nb:ln30lj unknown a1311 operator using tail nb:ln35dl unknown a1823 operator using tail nb:ln40pk unknown a2066 operator using tail nb:ln444wb unknown a1824 operator using tail nb:ln77nj unknown a2069 operator using tail nb:ln989al unknown a1691 operator using tail nb:lvmem unknown a1190 operator using tail nb:lvred unknown a1237 operator using tail nb:nasa4 unknown a1746 operator using tail nb:na011 unknown a1238 operator using tail nb:nxf61 unknown a1696 operator using tail nb:n093z unknown a1089 operator using tail nb:n1dg unknown a1192 operator using tail nb:n10sa unknown a1313 operator using tail nb:n109jz unknown a1312 operator using tail nb:n1093z unknown a1314 operator using tail nb:n110ha unknown a1316 operator using tail nb:n111wb unknown a1827 operator using tail nb:n114ax unknown a2074 operator using tail nb:n1144ax unknown a1829 operator using tail nb:n115br unknown a1828 operator using tail nb:n1157a unknown a1698 operator using tail nb:n122u unknown a1319 operator using tail nb:n128ab unknown a1321 operator using tail nb:n129wa unknown a1699 operator using tail nb:n13pa unknown a1322 operator using tail nb:n139cf unknown a1193 operator using tail nb:n14cg unknown a1834 operator using tail nb:n140wc unknown a1323 operator using tail nb:n143ga unknown a1835 operator using tail nb:n146cs unknown a1324 operator using tail nb:n150lr unknown a1837 operator using tail nb:n1547b unknown a1838 operator using tail nb:n155ac unknown a1523 operator using tail nb:n1610pr unknown a1326 operator using tail nb:n163pa unknown a1702 operator using tail nb:n17cd unknown a1842 operator using tail nb:n170pc unknown a1194 operator using tail nb:n173s unknown a1843 operator using tail nb:n176ws unknown a1330 operator using tail nb:n182gx unknown a1195 operator using tail nb:n184r unknown a1197 operator using tail nb:n19qc unknown a1090 operator using tail nb:n2jr unknown a1703 operator using tail nb:n20wn unknown a1847 operator using tail nb:n200lj unknown a1331 operator using tail nb:n201cr unknown a1849 operator using tail nb:n211bc unknown a1850 operator using tail nb:n212ba unknown a1333 operator using tail nb:n218ec unknown a1198 operator using tail nb:n22em unknown a1334 operator using tail nb:n221al unknown a1335 operator using tail nb:n221dg unknown a1704 operator using tail nb:n226w unknown a1851 operator using tail nb:n228rm unknown a1337 operator using tail nb:n229bp unknown a1852 operator using tail nb:n2321t unknown a1199 operator using tail nb:n24et unknown a1200 operator using tail nb:n24kw unknown a1201 operator using tail nb:n24ud unknown a1706 operator using tail nb:n24ys unknown a1339 operator using tail nb:n243ch unknown a1340 operator using tail nb:n245us unknown a1202 operator using tail nb:n260v unknown a1856 operator using tail nb:n262fx unknown a1342 operator using tail nb:n267bb unknown a1857 operator using tail nb:n270ax unknown a1707 operator using tail nb:n283s unknown a1343 operator using tail nb:n285cp unknown a1858 operator using tail nb:n288ka unknown a1708 operator using tail nb:n296l unknown a1370 operator using tail nb:n3dmrt unknown a1709 operator using tail nb:n30lj unknown a1862 operator using tail nb:n303cj unknown a1206 operator using tail nb:n31ga unknown a1865 operator using tail nb:n3120u unknown a1348 operator using tail nb:n315fv unknown a1349 operator using tail nb:n316ne unknown a1869 operator using tail nb:n317pc unknown a1352 operator using tail nb:n323lb unknown a1207 operator using tail nb:n326n unknown a1355 operator using tail nb:n328jk unknown a1874 operator using tail nb:n329fx unknown a1711 operator using tail nb:n33nj unknown a1875 operator using tail nb:n330fx unknown a1876 operator using tail nb:n336ad unknown a1357 operator using tail nb:n339ba unknown a1358 operator using tail nb:n344aa unknown a1877 operator using tail nb:n344cc unknown a1359 operator using tail nb:n345aa unknown a1209 operator using tail nb:n35dl unknown a1360 operator using tail nb:n350js unknown a1361 operator using tail nb:n358wc unknown a1882 operator using tail nb:n362mc unknown a1883 operator using tail nb:n36688 unknown a1884 operator using tail nb:n36742 unknown a1885 operator using tail nb:n36883 unknown a1886 operator using tail nb:n36994 unknown a1889 operator using tail nb:n377ga unknown a1887 operator using tail nb:n3776a unknown a1890 operator using tail nb:n381mq unknown a1892 operator using tail nb:n386mq unknown a1366 operator using tail nb:n393bd unknown a1893 operator using tail nb:n395my unknown a1895 operator using tail nb:n398dl unknown a1211 operator using tail nb:n398w unknown a1091 operator using tail nb:n4ea unknown a1212 operator using tail nb:n40pk unknown a1371 operator using tail nb:n4009l unknown a1374 operator using tail nb:n404jw unknown a1896 operator using tail nb:n404tl unknown a1898 operator using tail nb:n410mn unknown a1899 operator using tail nb:n411wb unknown a1375 operator using tail nb:n414rf unknown a1378 operator using tail nb:n41972 unknown a1380 operator using tail nb:n426rj unknown a1901 operator using tail nb:n428sc unknown a1381 operator using tail nb:n4297n unknown a1902 operator using tail nb:n430jt unknown a2077 operator using tail nb:n4324sb unknown a1382 operator using tail nb:n434sb unknown a1903 operator using tail nb:n4345b unknown a1907 operator using tail nb:n444wb unknown a1715 operator using tail nb:n45up unknown a1908 operator using tail nb:n458da unknown a1385 operator using tail nb:n458pe unknown a1910 operator using tail nb:n467jk unknown a1911 operator using tail nb:n4797n unknown a1717 operator using tail nb:n48hf unknown a1912 operator using tail nb:n487ue unknown a1915 operator using tail nb:n49occ unknown a1913 operator using tail nb:n490cc unknown a1914 operator using tail nb:n490ec unknown a1391 operator using tail nb:n491an unknown a1394 operator using tail nb:n502jl unknown a1918 operator using tail nb:n508cb unknown a1399 operator using tail nb:n515lr unknown a1919 operator using tail nb:n524fs unknown a1719 operator using tail nb:n53hj unknown a1214 operator using tail nb:n54cc unknown a1404 operator using tail nb:n544lr unknown a1405 operator using tail nb:n547lr unknown a1406 operator using tail nb:n555gl unknown a1924 operator using tail nb:n5561f unknown a1407 operator using tail nb:n561cm unknown a1925 operator using tail nb:n56672 unknown a1722 operator using tail nb:n59cj unknown a1410 operator using tail nb:n590fa unknown a1941 operator using tail nb:n6vafw unknown a1412 operator using tail nb:n601je unknown a1414 operator using tail nb:n601vh unknown a1416 operator using tail nb:n604hc unknown a1725 operator using tail nb:n61ma unknown a1417 operator using tail nb:n610pr unknown a1418 operator using tail nb:n614ba unknown a1419 operator using tail nb:n614fx unknown a1929 operator using tail nb:n616mr unknown a1930 operator using tail nb:n61788 unknown a1216 operator using tail nb:n64mp unknown a1217 operator using tail nb:n65rz unknown a1421 operator using tail nb:n650al unknown a1218 operator using tail nb:n66nj unknown a2078 operator using tail nb:n66715r unknown a1935 operator using tail nb:n6678f unknown a1422 operator using tail nb:n668mp unknown a1726 operator using tail nb:n67gh unknown a1219 operator using tail nb:n67gw unknown a1424 operator using tail nb:n671rw unknown a1936 operator using tail nb:n675mp unknown a1425 operator using tail nb:n676gh unknown a1426 operator using tail nb:n682db unknown a1428 operator using tail nb:n684qs unknown a1940 operator using tail nb:n688jb unknown a1728 operator using tail nb:n70lj unknown a1429 operator using tail nb:n700mp unknown a1430 operator using tail nb:n700ny unknown a1942 operator using tail nb:n700sl unknown a1221 operator using tail nb:n71nk unknown a1222 operator using tail nb:n71pg unknown a1431 operator using tail nb:n711nk unknown a1432 operator using tail nb:n719jp unknown a1943 operator using tail nb:n721rm unknown a1437 operator using tail nb:n729ta unknown a1945 operator using tail nb:n733ta unknown a1731 operator using tail nb:n75la unknown a1732 operator using tail nb:n75mc unknown a1946 operator using tail nb:n764xj unknown a1441 operator using tail nb:n7643u unknown a1442 operator using tail nb:n767fa unknown a1947 operator using tail nb:n769sk unknown a1734 operator using tail nb:n77fa unknown a1735 operator using tail nb:n77nj unknown a1736 operator using tail nb:n782t unknown a1949 operator using tail nb:n783ml unknown a1445 operator using tail nb:n797cb unknown a1446 operator using tail nb:n799ww unknown a1950 operator using tail nb:n800al unknown a1447 operator using tail nb:n800el unknown a1951 operator using tail nb:n800ns unknown a1449 operator using tail nb:n800wa unknown a1450 operator using tail nb:n801pn unknown a1952 operator using tail nb:n811am unknown a1953 operator using tail nb:n815ma unknown a1956 operator using tail nb:n828kd unknown a1453 operator using tail nb:n841ws unknown a1737 operator using tail nb:n860s unknown a1961 operator using tail nb:n863pa unknown a1561 operator using tail nb:n87v unknown a1962 operator using tail nb:n874jd unknown a1562 operator using tail nb:n88d unknown a1738 operator using tail nb:n8862 unknown a1965 operator using tail nb:n8862f unknown a1460 operator using tail nb:n888aq unknown a1462 operator using tail nb:n890cw unknown a1463 operator using tail nb:n898ew unknown a1563 operator using tail nb:n9up unknown a1226 operator using tail nb:n90aj unknown a1971 operator using tail nb:n901pc unknown a2079 operator using tail nb:n901qds unknown a1466 operator using tail nb:n9053t unknown a2080 operator using tail nb:n9098jb unknown a1975 operator using tail nb:n915gm unknown a1470 operator using tail nb:n916lx unknown a1976 operator using tail nb:n9176s unknown a1471 operator using tail nb:n921cc unknown a1473 operator using tail nb:n929jh unknown a1977 operator using tail nb:n929kd unknown a1742 operator using tail nb:n93rs unknown a1978 operator using tail nb:n933dr unknown a2081 operator using tail nb:n9339ck unknown a1979 operator using tail nb:n939ck unknown a1980 operator using tail nb:n940ae unknown a1981 operator using tail nb:n940cc unknown a1477 operator using tail nb:n951db unknown a1232 operator using tail nb:n96nb unknown a1984 operator using tail nb:n972qj unknown a1234 operator using tail nb:n98cg unknown a1986 operator using tail nb:n988sb unknown a1486 operator using tail nb:n989al unknown a1236 operator using tail nb:n99cn unknown a1744 operator using tail nb:n99nj unknown a1235 operator using tail nb:n990m unknown a1987 operator using tail nb:n991al unknown a1487 operator using tail nb:n995cr unknown a1747 operator using tail nb:oehub unknown a1240 operator using tail nb:oywet unknown a2082 operator using tail nb:pasteur unknown a2083 operator using tail nb:pegasus unknown a2084 operator using tail nb:pegasuz unknown a1748 operator using tail nb:pjweb unknown a1246 operator using tail nb:ppeic unknown a1248 operator using tail nb:ppetr unknown a1251 operator using tail nb:ppmis unknown a1754 operator using tail nb:ppxvj unknown a1252 operator using tail nb:prain unknown a1255 operator using tail nb:prdri unknown a1755 operator using tail nb:prgkj unknown a1257 operator using tail nb:prodt unknown a1258 operator using tail nb:prsce unknown a1756 operator using tail nb:prspr unknown a1757 operator using tail nb:prtna unknown a1263 operator using tail nb:ptlms unknown a1264 operator using tail nb:ptlnc unknown a1266 operator using tail nb:ptluk unknown a1267 operator using tail nb:ptora unknown a1269 operator using tail nb:ptscr unknown a1274 operator using tail nb:ptwjs unknown a1278 operator using tail nb:ptxgs unknown a1280 operator using tail nb:ptzma unknown a1760 operator using tail nb:pztst unknown a1761 operator using tail nb:pztsv unknown a1241 operator using tail nb:p4fly unknown a1992 operator using tail nb:recto1 unknown a2085 operator using tail nb:recto21 unknown a1282 operator using tail nb:rssa1 unknown a2089 operator using tail nb:sebator unknown a1525 operator using tail nb:shell01 unknown a1762 operator using tail nb:tibbn unknown a1526 operator using tail nb:tif375a unknown a2094 operator using tail nb:tn733ta unknown a2095 operator using tail nb:tn890cw unknown a1994 operator using tail nb:tx9512 unknown a1284 operator using tail nb:tztac unknown a1285 operator using tail nb:ujt17 unknown a1490 operator using tail nb:ujt300 unknown a1286 operator using tail nb:un450 unknown a1763 operator using tail nb:uy209 unknown a1777 operator using tail nb:vpaaa unknown a1778 operator using tail nb:vpaaf unknown a1288 operator using tail nb:vpbdb unknown a1289 operator using tail nb:vpbjv unknown a1779 operator using tail nb:vpblr unknown a1290 operator using tail nb:vpbms unknown a1780 operator using tail nb:vpbvg unknown a1781 operator using tail nb:vpbze unknown a1294 operator using tail nb:vpcvi unknown a1765 operator using tail nb:v2ldi unknown a1766 operator using tail nb:v2ldl unknown a1769 operator using tail nb:v2ldu unknown a1770 operator using tail nb:v2lel unknown a1771 operator using tail nb:v2lfc unknown a1772 operator using tail nb:v2lfl unknown a1775 operator using tail nb:v2lft unknown a1776 operator using tail nb:v2lgh unknown a2097 operator using tail nb:warloc1 unknown a1295 operator using tail nb:xaaex unknown a1297 operator using tail nb:xaesc unknown a1786 operator using tail nb:xayyy unknown a1997 operator using tail nb:x6vafw unknown a1301 operator using tail nb:yrcjf unknown a1528 operator using tail nb:yv1004c unknown a1491 operator using tail nb:yv1005 unknown a1492 operator using tail nb:yv1008 unknown a1493 operator using tail nb:yv1009 unknown a1494 operator using tail nb:yv1010 unknown a1495 operator using tail nb:yv1083 unknown a2000 operator using tail nb:yv1212 unknown a2001 operator using tail nb:yv128t unknown a1496 operator using tail nb:yv1401 unknown a2002 operator using tail nb:yv1456 unknown a2003 operator using tail nb:yv1518 unknown a2004 operator using tail nb:yv155t unknown a2104 operator using tail nb:yv174cp unknown a2005 operator using tail nb:yv174t unknown a2006 operator using tail nb:yv1844 unknown a1499 operator using tail nb:yv1850 unknown a2007 operator using tail nb:yv188t unknown a1500 operator using tail nb:yv1929 unknown a1502 operator using tail nb:yv2073 unknown a2008 operator using tail nb:yv218t unknown a2010 operator using tail nb:yv2286 unknown a1505 operator using tail nb:yv2421 unknown a1506 operator using tail nb:yv2422 unknown a2011 operator using tail nb:yv268t unknown a1533 operator using tail nb:yv292cp unknown a1789 operator using tail nb:yv401 unknown a2012 operator using tail nb:yv42cp unknown a1534 operator using tail nb:yv450cp unknown a1535 operator using tail nb:yv455cp unknown a1537 operator using tail nb:yv778cp unknown a2110 operator using tail nb:yv815cp unknown a1302 operator using tail nb:zsepb unknown a1303 operator using tail nb:zsoee unknown a1304 operator using tail nb:zspza unknown a11755 operator using tail nb: ggjmb unknown a12733 operator using tail nb: n292cs unknown a11506 operator using tail nb: n829cs unknown a11512 operator using tail nb: n915av unknown a11525 operator using tail nb: pragp unknown a11527 operator using tail nb: prdnz unknown a12903 operator using tail nb: prroz korea, democratic people\u2019s republic of a11533 operator using tail nb: vpbbo unknown a11541 operator using tail nb: vpcta unknown a11542 operator using tail nb: vpczk unknown a11545 operator using tail nb: vqbfn unknown a11546 operator using tail nb: vqbfp unknown a11547 operator using tail nb: vqbfq unknown a11554 operator using tail nb: xaavz unknown a12918 operator using tail nb: xache mexico a11562 operator using tail nb: xapil unknown a12707 operator using tail nb: n169fj united states a11748 operator using tail nb: 5yjlf unknown a1564 operator using tail nb:3bssd unknown a1097 operator using tail nb:3dmrw unknown a1098 operator using tail nb:3drmw unknown a1791 operator using tail nb:3s9402 unknown a1100 operator using tail nb:4xcmy unknown a1102 operator using tail nb:6vafw unknown a1085 operator using tail nb:6152 unknown a1792 operator using tail nb:7v2lgh unknown a1567 operator using tail nb:8rgfi unknown iceland crco identification no. operator name state of the operator f13607 almond forest investments llc united states 33277 altbridge projects ltd russian federation f10803 american seafood\u2019s group united states 36230 acernus aero new zealand 38156 action aviation uk united arab emirates 36520 ac lm resta voghera italy 499 aerodata aktienges 1 germany 23200 aerodynamics usa united states 38433 aerojet ukraine ukraine 36014 aeromaritime inc united states 33160 aeromil pacific australia 37866 aerovol corporation china 32255 aero gmbh germany 38738 aero jet intl inc. united states 38439 aero sky s.l. spain 35263 af air s.r.l. italy 38219 airboss of america canada 33255 airon air denmark 34802 air ambulance spec united states 1502 air atlanta iceland 34851 air business travel austria 34301 air cannes france 35659 air capital pilot united states 32461 air chateaux france 34407 alci aviation canada 32761 alias patrick united states f11420 altex llc united states 36442 amber falcon south africa f12848 amts aircraft holdings llc-n40dk united states f10024 am general, llc united states 33519 anpartsselskabet denmark 35335 arnet switzerland 34668 ar airways pvt ltd india 34124 ashall michael l united kingdom 30047 ashton aviation united states 14399 astar usa llc united states 35809 astonjet ltd ireland 31689 avangard avtn avv russian federation 32918 avangard malz ag germany 33503 aviation inventory united states f12726 aviation services & sales inc united states 38160 avon aviation llc united states 32522 avstar intl corp united states 34980 avtn capital grp (2) united states 37888 avtn consultants inc united states 35734 avtn partn. america united states 32830 aza air llc united states 36035 aziz hassanali united states 36066 azolla bvba belgium f10063 bacchus consulting, llc united states f10075 banknote aviation corp. united states f13145 bar-aero llc united states f10077 basic capital majestic united states f10977 biotek instruments, inc. united states 37168 bravo bravo investments llc united states 35163 buddy 4, llc united states 24074 babcock and brown united states 37056 bbjet aviation b.v. netherlands 911 beechcraft augsburg germany 33013 bevrick south africa 34760 bf grupo portugal 33373 bikkair b.v. netherlands 35484 blink ltd united kingdom 27616 bluebird cargo iceland 5169 bombardier canadair canada 2595 boyd munro united states 12871 buchholz germany 33001 bulow-nicolaisen united states 28620 buraq air libya f12473 b.f. limited partnership united states f10102 cambridge flight support, llc united states f10119 chris james bahamas f10895 cooper industries united states 33307 canadian north canada 34660 caribou industries united states 37628 carwil llc united states 37062 castleblue limited cyprus 34294 cervinka switzerland 34109 cezanair b.v. netherlands 37758 chestnut holding germany 33272 cirrus air club united states 35180 cj3 charter llc united states 31719 click mexicana mexico 36331 clm srl italy 32604 close air united kingdom 35366 comfort line ltd united states 38139 compagnie phalsbourg france f12972 congo mining & services united states 28196 cormack acft service united kingdom 27760 corporate acft ls switzerland 39053 corporate air svcs united states 33082 cumulus inv. hol.ltd united kingdom f12181 c&s wholesale grocers, inc united states 35121 c.l.a invest poland 33155 c3j charter llc united states f12664 douglas solutions ltd united states f11451 daedalus group llc united states 34678 dana air nigeria 34658 dating.dk aps denmark 38130 dfass united states 34791 dornier seawings ag germany 30049 dove air united states 11028 duncan aviation united states 2766 dynamic partners bv netherlands 36445 estrella aviation united states 32738 east air tajikistan 32633 eclipse aviation united states 17105 efs aircraft germany 36431 elana keats monaco 37105 elite jet australia 37479 ellerhold ag germany 35992 emfly gmbh germany 33139 enex aviation sa monaco f11774 engage aviation llc united states 30789 euroline aircompany georgia 31497 exellair luxembourg 4532 exo -2t allemagne germany 4544 exo -2t autres pays australia 4540 exo -2t n&s america united states f11142 fine line, l.p. united states f10608 flight management services united states 1403 falko regional acft united kingdom 33202 fast air ltd canada 34667 felix airways yemen 37036 fidji air france 36378 first gear switzerland 37075 flightworx aviation united kingdom 27296 flight managmnt llc united states 3176 flugfelag islands iceland 37943 fluocel pty ltd south africa 36160 fly away aviation united states 36774 fly mustang ltd united kingdom 32201 fountain air united kingdom 35381 frost james c united states 19330 gantenbrink germany 36960 gc air llc united states 6331 gemue gmbh switzerland 34954 ge capital solution united kingdom 29477 gifford d united states 37447 ginnaire rental inc united states 37952 glass cockpit avtn. france 34143 global acft solution united states 38280 global air chrtrs united states 37726 global wings llc united states 31906 glr aviation united states 17957 greenleaf united states 36820 gulbrandsen chemical united states 34908 gulevich charter spain f10800 herzog contracting corp. united states f12242 hope million ltd bvi virgin islands, british 38218 happy air travellers thailand 23127 harris air utah united states 19833 hawker pacific 2 australia 37851 hayat hava ve arac turkey 30256 hello switzerland 35908 high over rockies united states 37356 high precision acft united states f10985 hmc interests llc united states 36897 holding terry a united kingdom 26436 holiday retirement united states 26317 howell j united kingdom 36115 hz aviation ltd israel f10258 indefensible corporation (djmd corporation) united states 35682 investair 300, llc united states 1479 icelandair iceland 12046 iceland coast guard iceland 29722 idroscalo turistico italy 33264 inovex charter gmbh germany 33477 integra map spain 25459 intl jetclub ltd united kingdom 34221 inyoni air ltd south africa 31393 itab (2) congo 30482 its fabry uk united kingdom 34334 ittag llc united states f11407 it aviation llc united states f10903 jesse duplantis ministries united states 32342 jag communications united kingdom 9539 jai aviation a/s denmark 37612 janzen ventures united states 36959 jb aviation llc * united states f12816 jce leasing llc united states 25830 jedinak r and r canada f11391 jefferson financial company united states f12803 jem aviation llc united states 36921 jetaviva llc united states 30465 jetworks united states f11814 jet air aircraft leasing llc united states 31939 joklaflug iceland 36618 jpats united states 37625 js aviation llc united states f13350 jt aviation leasing co. llc united states 35444 koch industries united states 14108 kaut germany 37333 kavan llc united states 35730 kirland 41025 llc united states 30456 kmi management united states f10902 landow 101 inc. united states f10996 laurence di francesco united states f11216 logistics business services llc united states 34973 lamont sea maritime united states 27994 liftwood united kingdom 29204 limabeech france 37335 lionair inc philippines f10301 lkm, inc. united states 25415 lloyd i g united kingdom f11783 l60-215 holdings llc united states f12191 mr chow enterprises, ltd united states f10320 mutual of omaha united states 36423 mach air limited united kingdom 26857 maine aviation sales united states f11446 marigot llc united states f12845 mari llc united states 37082 mark iv aviation ltd bahamas 32248 marron ventures switzerland f11780 mcdonnell douglas aircraft co united states 35405 mcsweeney william f united kingdom 34772 mc lean south africa f12795 mercer air llc united states 35337 midland aviation united kingdom 36609 mig aviation (uk)ltd united kingdom 34089 mike osborne props united kingdom 7907 mil egypt (3) egypt 1105 mil israel israel 1111 mil norway norway 5556 mil saudi arabia saudi arabia 19955 mil ukraine ukraine 2799 mil usa united states 823 mil us navy united states 34489 mineag south africa 30154 missionair s.l. spain 34292 mk aircargo (2) united kingdom 35854 mmr-group nv belgium 35414 modena capitale fin italy 36323 morina antonello italy f11373 mountain shadow ventures llc united states 34584 munster jet partner ireland 35717 mustang n625tx. inc switzerland 25977 mystair united states 36411 m-kick lp united kingdom 35669 nato airlift luxembourg 36311 newton air llc united states 37436 nextant aerospace united states 31005 nin air srl italy 35419 norlandair iceland f12488 onni airways ltd canada 36452 ocean continental cyprus 32355 omega world wide united states 33758 optima leasing d.o.o croatia 30419 osm group norway 31976 otter inspirations united states 34202 oxley aviation australia 30279 papier mettler germany 25580 pioneer private aviation united states f10370 pyle group llc united states 27784 pacific jet united states 33063 panadero energy llc united states 39027 peak pacific global china f11817 pegasus aviation ii inc united states 9516 peregrine aviation united states 38365 poseidon finance virgin islands, british 36905 prd france 29769 premiere flight united states 30137 primera air iceland 35611 prof jet solutions united arab emirates 28794 progress solutions switzerland 28212 provincial airlines canada f10763 raven aviation llc united states f10380 redleaf management company, llc united states 31967 radioactive united states 36291 rafan holding bv netherlands 31179 rb avtn usa united states 38098 rh-flugdienst gmbh & co. kg switzerland 33695 ross aviation inc united states 34685 royal albatross south africa 33089 runge aviation australia 28691 rushton m united states f11884 saratoga, inc. united states 20236 sequoia properties, llc united states 28475 silk way airlines azerbaijan f12111 supervalu inc. united states 35130 switchback argentina, llc united states 29518 saab acft of america united states 34163 seajet services singapore 33986 selva ltda. colombia 38122 servicios aer. prof. dominican republic 32463 shephard avtn united kingdom 36425 singapore flying c. singapore 32244 sky jet avtn uganda uganda 32799 sky king inc united states 38981 sky research inc united states 27489 sky river management united states 24369 sk-air slovakia 32954 slw international united states 25560 socata aircraft usa united states 10064 socata sas france 38026 solstice avia bvba belgium 32599 southern air systems united states 34410 southside aviation united kingdom 32603 spring air united kingdom 28353 starcraft eurl france 37013 stevenson leasing united states 36199 stibbe, p netherlands 36338 strategic moves united states 34530 summer sun trading south africa 8397 suncoast aviation united states 37653 sunrise airways tanzania, united republic of 34627 swiftjet inc. canada 23948 s gouv.du quebec canada f11002 titan international inc. united states f10447 town fair tires united states 30863 taby air maintenance sweden 30936 tango-lima aviation france 39039 telescope capital united states 34842 tinkler group avtn australia 31974 tower avtn of readin united states 32766 tradewind avtn united states 38201 tronos canada canada 32928 tunisair express tunisia 25448 ukraine cargo airway ukraine 35124 unicredit global austria 36942 united acft services united states 35464 universal air svcs united kingdom 28951 us epperson underwrt united states f11852 valor aviation llc united states 32186 visinescu d mces netherlands 20609 volkswagen usa united states 32395 von loehneysen e germany 30977 voyag\u2019air france f11345 vs management llc united states f11839 western air crews united states f12486 wolrd heir, inc united states 36780 walenz steve united states 33375 waylock overseas ltd russian federation 38980 waypoint aeronautic. united states f11376 western asset management co united states f11383 westwind brothers inc united states f11029 white lodging services united states 38716 worldwide acft svcs united states 6357 world wide aircraft canada f10841 w&j air, llc united states 33400 yippee atw gmbh germany 37431 zain sd fze united arab emirates 34395 zapolarye russian federation 37639 650584 alberta inc canada a11742 operator using tail nb: n1459a unknown a11480 operator using tail nb: n1667j unknown a11492 operator using tail nb: n428cc unknown a11516 operator using tail nb: n988t unknown a11524 operator using tail nb: ppprr unknown a11530 operator using tail nb: pttfk unknown a11521 operator using tail nb: p4tco unknown ireland crco identification no. operator name state of the operator f10007 air reese, llc united states f10765 alaska eastern partners united states 36324 altis ireland 33209 altivia flight singapore f12155 amalgamated consolidated, inc. united states f12108 ambassador marketing international inc. united states f13095 asheville jet charter & management united states 35023 acft finance trust ireland 31510 acp jets united states f11447 adc aviation llc united states f10775 adp aviation, llc united states 28509 aerolineas damojh mexico 28752 aeromanagment group united states 29293 aero timber partners united states 23714 aero toy store llc united states 29670 aero ways inc united states 131 aer arann ireland 132 aer lingus ireland 30118 aircraft intl rent ireland 32813 air blessing united states 298 air contractors ireland 7057 air shamrock united states 32218 air tahoma united states 28432 air trek united states 38630 akm management united states 34285 alchemist jet air llc united states f12838 aledo sub llc united states 26140 alltech united states 30995 alpha one flight services united states f12957 amc 50 llc united states 27173 apache corp united states 38618 ar investments llc. united states 29280 astor street asset united states 33136 atlantic av kteb united states 36309 avianova (russia) russian federation 20800 aviation consult inc united states 33008 avia partner denmark denmark f11798 avion sales llc united states f12103 benson football, llc united states 35372 bindley capital partners united states f12682 bombardier new aircraft united states 36888 boston scientific corp united states 34053 bank of nova scotia canada 1868 bard united states 31686 barnard aviation united states 1537 baxter health care united states 34487 bazis intl inc. canada 33090 beacon aviation ireland f11361 beauty central llc united states 25114 becker group united states 32660 bedek aviation israel 38915 bel air llc united states 33557 big play flight svcs united states 33247 blue city holdings united states 37316 boliviana aviacion bolivia, plurinational state of f11410 borg holdings llc united states 31975 boulder us united states 37279 business a.centre co thailand 26369 b&g leasing united states f13609 center for disease detection llc united states f12458 codale electric supply inc. united states f10129 corporate flight services, llc united states 30753 covidien united states f10987 cozzens and cudahy air united states f10777 crow family inc. united states 30615 carlisle holdings llc united states 30896 cca air charter united states 29250 centurion avtn srvcs united states 36860 cessna finance corp united kingdom f11418 cessna finance corp united kingdom 5078 cintas united states 21455 cityjet ireland 36082 cmc group inc united states 32549 constellation prod. united states 32509 cook aircraft leasng united states 19036 corporate jets pa united states 28444 cross avtn united kingdom f11386 cuna mutual insurance society united states f11899 c c media holdings inc united states 38620 c&s wholesale grocer united states 35160 c. dot aviation, llc united states f10650 darby holdings unknown f11469 delaware global operation llc united states 31690 delta jet usa united states 24235 deniston enterprises united states 30715 dmb aviation united states 35370 dominos pizza (2) united states 28485 dow corning united states f12713 dss214 llc united states 27997 dynamic aviation services inc united states f10176 energy corporation of america united states f10183 executive flight solutions, llc united states 35072 eac air llc united states 8339 eaton united states 1009 eli lilly united states 23828 emc ireland ireland 23627 emercom russia russian federation 33649 encore 684 llc united states f11381 encore/sb aviation llc united states f12801 european aircraft charter inc united states f10208 flightstar corporation united states f11889 futura travels limited india 33361 fagen inc united states 29521 fairmont aviation se canada 34792 fastnet jet alliance ireland 32271 fast link egypt egypt 21578 federal mogul united states 28181 ferro corp united states 30469 first virtual air united states 31774 flying squirrel united states 34371 freebird mngmt ltd. ireland 3826 friedkin intl united states f11239 gamestop, inc united states f13449 general dynamics land systems united states f12159 gilead sciences united states 10229 goodman real estate, inc. germany f10229 goodman real estate, inc. united states f10231 graham brothers construction co., inc united states f13612 guthy renker aviation united states 39022 gaughan flying llc united states 38550 gc international llc united states 26624 general mills sales united states 38543 george gund 3 united states 22286 ge capital-gecas ei ireland f12778 giv exec jet llc united states 36512 global jetcare united states 23814 global wings ltd switzerland 3964 goodyear united states f10230 gpair limited canada f12820 greenbrier capital llc united states 26847 greenhill avtn united states f11374 green chair productions inc united states 22958 group holdings united states 31561 gulf pacific avtn sv united states f10901 hormel foods corporation united states 37187 hac aviation united states 28219 harley-davidson united states 31054 heavylift int. united arab emirates 35241 highfields cap mgmt united states 33420 howard holdings plc ireland 5170 humana united states f11193 iamaw united states f12877 idgaf llc united states 24747 ifftg united states 32500 ilfc ireland ltd ireland f11378 indigo management co united states 38979 iomax usa inc united states 21409 irving air service canada 34314 jet direct aviation (filed for bankruptcy on 25.02.2009) united states f10282 john m. connors, jr. united states 35520 jones international aviation llc united states 31850 jarden corp united states 22094 jeppesen uk ltd united kingdom 27861 jep leasing united states 38357 jetgo australia australia 35926 jet logistics inc united states 35981 jet shares only united states 32652 jet smart inc united states 30210 jet-a-way charters united states 34915 jkb jet holdings llc united states 1584 johnson & johnson united states f10287 kenair, inc. united states f11016 kendall jackson wine estates united states f10713 konfara company united states f10702 keb aircraft sales, inc. united states 8180 kellogg united states f12693 kire aviation llc united states f11341 kkn transportation leasing llc united states f10295 leco corporation united states 29729 letica leasing llc united states f10302 lower cross aircraft corp. united states 31706 lcg enterprises united states 35616 leonard green & part united states 32207 lisbon limited bermuda 38705 logistics svcs llc united states 28852 london city jet united kingdom 36958 luna entertainment united states f12230 mannco llc united states f10507 midland financial co. united states f12940 motorola solutions, inc. united states f10968 mozart investments, inc. united states 37122 macquarie acft leasg ireland 36961 magellan a/c svcs ireland 30454 majjec jhett united states 32345 mandala airlines 3 indonesia 26422 mandan united states 38653 manhag ag switzerland 27630 mercury engineering ireland 30050 mhs travel & chtr united states f13615 mides sem de cv el salvador 1104 mil ireland ireland f10317 mmb management advisory services united states 31703 mmrb services united states 35625 modesto exec air chr united states f11411 monavie aircraft leasing llc united states 36426 mpw industrial svcs united states 32479 mva aviation ltd. united kingdom 38901 m&m aviation group united states f13128 nevada pacific conculting, llc. united states f10919 noble energy, inc. united states f10334 noel group aviation united states f12093 nustar logistics united states f10328 ncr corporation united states 18352 nestle purina petcar united states 29867 next flight jets united states 32930 ninety eight avtn united states 37562 nonstop aviation united states 11930 north american airl united states f10962 north american flight services united states 26985 north star avtn united states f12769 n48kz llc united states 18796 n728lw llc united states f11106 orange crimson aviation, llc united states 32397 office depot united states 37310 okay airways china 9116 omega air (usa) united states 39090 omni air united states 7079 orbis intl united states 35897 oslo express united states 2079 owens illinois united states 3252 pepsico, inc. united states 34422 premier executive jets ltd ireland 31045 privatesky aviation llc united states 33261 pacific sky canada 8792 palmer a united states 29783 pegasus aviation ca united states 36816 phillips edison & co united states 32055 pioneer adventures new zealand f10361 pnc financial services group united states f11419 polar bear express ii llc united states 32096 prime aviation jsc kazakhstan 34180 professional care united states 38672 project orbis intl united states 10012 p & e properties united states 26605 quest avtn united states 32706 rbgt llc united states f10978 reaud morgan quinn united states 31234 red barn farms united states f10389 rkk management, inc. united states f11777 robinson leasing inc united states f12988 robson communities inc united states 23899 rollins inc. united states 29788 roro 212 united states 31502 rotor trade (arc) united states 2292 rowan companies plc united states 38726 rsvp jet inc united states 30090 rusaviation united arab emirates 8651 ryanair ireland f10397 select management resources, llc united states f10824 seminole tribe of florida united states f13116 standridge color corporation united states f10501 sunoco inc. united states 28054 safeway united states 31347 safe flight instrmt united states f12851 sdl management company llc united states 34898 sd vermogensverwalt germany 871 seagull aircraft corp united states 24869 sierra pacific ind united states 36640 sim sas france f12817 sitrick and co united states 31192 southern jet mgmt united states f12106 spg frank group (spg management, llc and frank group, llc) united states 37778 squadron leasing ireland 31823 starship enterprise united states f10874 tashi corporation united states f10441 the sherwin-williams company united states 32156 tallwood managemnt united states 3696 texas instruments united states f11309 third security llc united states f12991 tony downs foods united states 9788 transit air srvc united states 36922 trans ejecutivo aere mexico 26406 trans west air srvcs united states 29623 tricycle aviation united states 35071 t2 aviation management, llc united states 9252 university corporation for atmospheric research (ucar) united states f12692 unicorp aviation llc united states 2797 united states steel united states 9275 vallejo investments united states f11803 valley jet llc united states 29120 ven air ireland 32119 via feliz ii united states 24690 victory avtn florida united states 28043 village equipment united states 29580 voyager jet center llc united states 36447 vtb leasing (europe) russian federation 36499 warner chilcott (us), llc united states f10815 washington penn plastic company united states f10789 wells fargo bank northwest, c/o morgan & morgan united states f10792 werner enterprises inc. united states f10784 wilmington trust united states 5187 weldbend united states 35439 wells fargo bank nw united states 31125 weston ltd ireland 38797 wildgoose llc united states 28282 wingedfoot avtn united states 38212 wings aviation (de) united states 32453 wings of lebanon lebanon 33542 wing financial llc united states 29233 wrenair ireland 32454 xjet usa united states 24497 zorlu air havacilik turkey 31649 z1 holdings united states 34931 blue nightingale trading south africa 32901 142955 ontario ltd canada 37435 921be llc united states a11477 operator using tail nb: hp1a unknown a11491 operator using tail nb: n415mx unknown a12818 operator using tail nb: n786jb unknown a12861 operator using tail nb: n920js unknown a12917 operator using tail nb: xabeg mexico italy crco identification no. operator name state of the operator f11555 aero taxis metropolitanos unknown f10307 airbar llc united states f10004 air mercury, ltd bermuda f10022 alcoa, inc. united states 31568 alenia aermacchi s.p.a. italy 37425 abberton ltd united arab emirates 24650 abu dhabi aviation united arab emirates 35991 aerokaluz sa de cv mexico 29651 aeromanagement europ italy 31391 aeronord-group moldova, republic of 36738 aeropa s.r.l. italy 30371 aeroportul marculest moldova, republic of 19195 aerotransportes priv mexico 35660 aeroyacht investment italy 22368 agusta westland spa italy 29450 aic canada canada 30283 aircraft properties united states 32513 aircraft system south africa 27328 airstars airway russian federation 11479 air dolomiti italy 32715 air four s.p.a. italy 30965 air italy italy 36964 air mandaly 2 undefined 31884 air prestigio united states 35312 air spea s.r.l. italy 36050 air team excutive italy 34676 air uganda uganda 9953 air vallee italy 33278 air wing s.p.a. italy 23132 albanian airline albania 37604 albatros acft corp canada 30526 albatros airways albania 9303 alberto culver united states 34831 alitalia c.a.i. spa italy 28123 amrash united states 36508 aviation capital sol united kingdom 24261 avio nord italy 36451 axsoa s.p.a. italy f13502 biotab nutraceuticals united states f10086 black diamond aviation united states 29878 balmoral air pty australia 31999 bashkortostan air russian federation 34857 bb fly s.r.l. italy 20198 belavia airlines belarus 31421 belle air albania 36730 belle air europe srl italy 32891 berjaya air sdn (2) malaysia 36408 bluebair jet switzerland 32734 blue jet united states 31928 blue mercury s.r.l. italy 26015 blue panorama li italy 38958 blue panorama (2) li italy f11338 blue star management services corp united states 37770 boeing wichita ids united states 38549 bombardier learjet united states 37190 border guard ep poland 35243 braathens training sweden 39045 brazil trading ltda brazil 32566 brenzil pty australia 27675 buddha air nepal 35914 business air parts united states f12602 cartera de inversiones venezola c.a. united states 19019 cableair united states 5083 cai italy f11308 candybar aviation llc united states 32079 caremark aviation united states 31766 cargoitalia italy 35318 cargolux italia italy 26954 carnival corp united states 38117 caropan company sa virgin islands, british 31898 catex usa united states 36292 ceramica cleopatra egypt 36770 chemiplastica united kingdom 24759 cnh america llc united states 35645 cn aviation united states 30812 consolidated investm united states 35761 corpo forrestale italy 38402 coteminas brazil 36979 c fly s.r.l. italy f10100 c. cary patterson united states 29468 dillard\u2019s inc. united states 37371 dako airlines sa luxembourg 32598 delia a/s denmark 36591 delmar systems inc. united states 36268 delton group inc. russian federation 27358 di air montenegro 18428 dole foods united states 28426 dolphin air express italy 9322 domus italy f11470 double v resources llc united states 30245 drax group united states 31864 ds aviation israel 23676 dudmaston ltd switzerland f12669 elk mountain consulting llc united states f11891 encanto investment inc united states 36588 eagles airlines italy 24307 eliticino sa switzerland 27824 eliwork srl italy 8149 enav italia italy 34700 ep aviation llc united states 1039 ethiopian airlines ethiopia 5051 eurofly service italy f12110 eurojet holdings ltd bermuda 29693 eutelia s.p.a. italy 36996 execujet charter svc united states 39049 e c menzies aviation united states 33586 e + a aviation switzerland f10871 fort calumet company united states f12234 full hill limited hong kong hong kong sar f12550 full wing holdings limited virgin islands, british f12791 fertitta entertainment llc united states 31996 fiba air hava turkey 24342 fininvest italy 32391 flightpartner united kingdom 31464 fligh test associate united states 21557 flynor jet italy 36118 fly540 kenya 38931 forte aviation parts united states 37983 fri-el green power italy f10228 golden gaming united states 34858 galaxy airways inc. canada 37037 gamay enterprises lt brazil 35213 gedeam tourism s.a. luxembourg 30273 gefa leasing gmbh germany 29961 general work guinea equatorial guinea 36315 geo logistica italy 36948 gianair ltd ghana 36179 glenn eagles researc united kingdom f12981 global management consulting ltd united states 33783 globus llc russian federation 27805 gmg airlines ltd bangladesh 32024 gmr industry ltd india 29615 golden air srl italy 32887 gp aviation svcs united states 36873 graskop aviation llc brazil f11463 gr1040 inc united states 31017 gulf aviation united arab emirates 32263 gutmen inc. brazil 32161 g350 leasing llc united states 31089 hawker aviation llc united states f12241 hermes capital limited bermuda bermuda 32296 hansung airlines korea, republic of 34031 hawker 700ltd united kingdom f10248 hga, llc united states 37563 high tech aircraft 2 united states 22863 hubbard enterprises united states f10259 inversiones far west inc. united states 37842 ibex air charter lebanon 25061 inaer aviation italia s.p.a. italy 36788 indonesia air tra(2) indonesia 26580 interfly srl italy 36455 intl aviation llc united states 27510 italease italy 37841 jbs s/a brazil 38415 jb aviation ii llc united states 32677 jetalliance east jsc russian federation 38438 jetcom s.r.l. italy 34346 jetdirect avtn inc united states 32062 jetex flight support libya 30695 jetlink express kenya 34576 jetplanet s.r.l. italy 35564 jet aviation (va) united states 38551 jet aviva llc united states 25029 jet plane corp denmark 31941 jet support group cayman islands f12752 jk aviation llc united states f12763 joda llc united states 30609 jsc nordavia-ra russian federation f10283 jsm at falcon, llc united states 36322 karnavati aviation india 38012 kaup\u00e9 aviation ltd switzerland 29205 knd aircraft leasing united kingdom 32068 k & m aviation united states f10999 latam llc united states f10839 leonard green and partners, l.p. united states f10781 lucky fives llc united states 32713 lauther-phillips united states 37126 leader s.r.l. italy 29027 leading edge united states 38276 leila jet ltd. united arab emirates 30044 lemoine investments united states 31451 lennar united states 35667 lfg services pty australia 36390 libo air cargo libya 23188 libyan air ambulance libya 39036 lifejet ltd. malta 18942 lindstroem enar sweden 33253 linus airways indonesia 28628 lukoil avia russian federation 22416 lvov airlines ukraine f11389 l & l leasing iv llc united states f10828 marnell corrao associates united states 35314 mae aircraft mgmt. bahrain 36367 magellan aviation ireland 36491 management services united states 36421 marcplan charter australia 27891 mass mutual life united states 35469 mazag cayman islands 38206 melo participacoes brazil 11698 meridiana fly italy 32051 meridian aircompany ukraine 37676 millennium labs united states 1106 mil italy italy 24266 ministero interno italy 36406 mister jet germany 8487 mistral air roma italy 31311 msc aviation switzerland f10769 mss falcon 900llc united states 37803 m-nice limited switzerland f12605 net medical, c.a. united states 26129 new world aviation, inc. united states f10633 northwestern mutual life ins. co. united states 36980 nand aviation saudi arabia 33889 navellier & assocs united states 28484 neos italy 36477 nesma airlines egypt 35377 netjets middle east saudi arabia f12702 netjets sales inc united states 33201 newco management grp united states 38345 new livingston spa italy 26030 next century avtn united states 31499 nikair srl italy 29756 noevir aviation united states 28892 n90bj united states 27302 oak management united states 35934 odyssey adventures united states 37412 opi servizi s.r.l. italy 36149 ozark management (2) united states f10557 penobscot properties, llc united states f10357 pinehurst meadows llc united states 32200 pablo air line srl italy 32786 pacific information aruba 31079 pafo united states 35642 pelican development united states 32710 penn national gaming united states 37380 petra airlines jordan 31232 petroff air russian federation 36592 pfp associates llc united states 36071 phoenix avtn mngment egypt 28946 pittco united states f11406 platinum equity llc united states 34770 pl logistics corp south africa 30442 precision air svcs tanzania, united republic of 23692 precision air svcs. tanzania, united republic of 25235 provincia autonoma italy f10373 raptor group holdings lp united states f10390 rochester aviation, inc. united states f11465 ramsey asset management llc united states 33019 reali taxi aereo brazil 37772 remorex pty ltd aus australia 22653 renco usa united states 27572 rhea vendors italy 32661 rooney holdings inc united states 33024 royal falcon jordan f11347 rsi holding llc united states 36748 rwandair express rwanda f10372 r.o.p. aviation, inc. united states f10399 sentry insurance a mutual company dba sentry aviation services llc united states f10400 servicios aereos sudamericanos s.a. argentina f10643 servicios aereos surtep s.a. de c.v. mexico 37964 sky wings ltd germany 31505 springway russian federation 29126 star aircraft leasing s.a. united states f10414 state farm mutual automobile insurance co. united states 37243 stryker corp united states 31740 sunstate aviation and leasing, llc united states f12989 safeguard enterprises llc united states 37839 sardinian sky servic italy 35774 saso air llc brazil 28283 scs services united states 25882 sequoia millennium united states 36271 service corp intl united states 23243 servis air hava turkey 10356 servizi trasporti italy 28179 sevastopol avia ukraine 37392 sgc aviation gmbh austria 36742 silver bird int. germany 8484 sirio italy 31624 skykar aviation united states 10748 skyservice airlines canada 37931 sky beyond singapore 35899 sky line srl italy 37521 small planet (li) italy 34027 sophia airlines c\u00f4te d\u2019ivoire 34631 sorena export ltd. ukraine 30462 southern air system united states 36438 south african exp. south africa 36112 span air pvt ltd india 30747 springline russian federation 34744 star up s.a. peru 25832 stephenson air svcs united states 31789 sydney jet charter australia f10435 symax llc united states 29524 s.k.m. bermuda 36364 time warner cable enterprises llc. united states f12493 titlemax aviation, inc. united states f11186 trinity broadcasting of fl., inc. united states 22663 tavistock avtn united states 38643 tessitura robecchett italy 31381 trip linhas aereas 2 brazil 37276 tri marine logistics united states 33685 trt equity advisors llc united states 35594 united airgroup cor. virgin islands, british 35073 united aviation libya f11404 united healthcare services inc united states f12469 upmc united states f11414 verde capital corp united states 29884 vizavi-avia ltd russian federation 32561 vk aviation usa united states 32987 voliamo switzerland f12001 v1 aviation inc. united states f10568 westbury group ltd bermuda f10872 westwind aquisition united states 35634 walker air australia 34937 wellard aviation australia f11301 wells fargo delaware trust co na trustee united states 30275 western stone &metal united states 8586 whirlpool united states 38875 white tail avtn avv united states 26545 wideworld srvcs argentina 33364 windrose aviation uk ukraine 29423 wind jet spa italy 38045 win air bus. jets taiwan f13019 xcoal energy & resources united states 35438 xla aviation switzerland 28383 yakutia aircompany j russian federation f12167 251 finance inc united states 37781 43 air school south africa 39001 546 participacoes brazil a12896 operator using tail nb:prfnp korea, democratic people\u2019s republic of a11754 operator using tail nb: geloa unknown a11498 operator using tail nb: n577da unknown a12869 operator using tail nb: n966bw united states cyprus crco identification no. operator name state of the operator 35731 agrevia holdings greece 27258 aim aviation israel 37309 airline allied svcs india 34989 air executive cyprus 32393 air one corp switzerland 33059 alliance air india 36209 ark airways armenia 37959 arrow aviation ltd israel 31856 aviation svcs guam united states 25193 aviators india india 32427 ayeet aviation israel 37570 azur aviation france 33683 a&s world aircraft united states 31603 british gulf intnl united arab emirates 31988 business-aero ooo russian federation 37660 centauri rp aviation united states 33580 centrafrique air exp central african republic 12148 chim nir aviation israel 34081 comair (kulula) south africa 20324 csm aviation cyprus 866 cyprus airways cyprus 33534 doiyatec comms ltd nigeria 27554 edt shipmanagement cyprus 16417 eurocypria cyprus 31008 falcon express cargo united arab emirates 34679 fallbrook pty ltd australia 34823 first kuwaiti kuwait 31112 flair aviation gmbh germany 37354 fly me maldives 8214 funair united states f10827 glenn eagles research llp united kingdom 36929 global jet dubai united arab emirates 35606 global projects india 7978 globe aero (3) united states 31245 globe jet lebanon 32491 goairlines india india 34421 gulf jet (dubai) united arab emirates 29619 hamra air united arab emirates f12985 helmsbriscoe united states 36429 hindustan construct. india 35562 integrated aviation jordan 31523 interlink airlines south africa 5292 jenson & nicholson singapore 7132 joannou paraskevaide united kingdom 36427 jsw steel ltd india 30932 kingfisher airlines india 30973 marsland aviation sudan 31441 mega kazakhstan 1090 mil denmark denmark 1102 mil netherlands netherlands 28698 national acft leasin united states 26103 nefteyugansk avia russian federation 32955 new macau landmark macao sar 31143 orion-x\u2019 ltd russian federation 24788 orient thai airlines thailand 24229 pankh russian federation 32162 paramount airways vi india 37181 pinnacle air pvt ltd india f10384 reliance transport & travels pvt ltd india f11013 rockcreek aviation united states f10401 shotgun ranch united states f10393 saib llc united states 26471 sakavia service georgia 32298 scandi hist flight norway 29833 sky gate jordan 33512 tahmid air kazakhstan 29649 ub air pvt ltd united states 30383 ukrainian helicopter ukraine 26821 vertical-t company russian federation latvia crco identification no. operator name state of the operator 28309 aeroklub aist russian federation 37312 aero transporte sa peru 35251 aircompany grodno belarus 23085 air baltic coorporation latvia 31027 ferafort investment united arab emirates 35448 henny, j belgium 37294 marimax jets ltd. russian federation 19962 mil latvia latvia 24839 rusair joint stock russian federation 37697 sky guinee airlines russian federation 21470 smartlynx airlines latvia 36339 tarco air sudan 35294 tri star avtn co united states 34617 wings4us austria lithuania crco identification no. operator name state of the operator 26887 aerocentrum spol czech republic 37287 association b-jet lt lithuania 23729 aurela lithuania 31300 avion express lithuania 36910 europos vartai, vsi lithuania 38814 jendela mobiliengese germany 34813 meridian airways nigeria 22249 mil lithuania lithuania 31219 qanot-sharq uzbekistan 35831 sakhalinskie (sat) russian federation 32679 samal air kazakhstan 25815 scat kazakhstan 34582 small planet (ey) lithuania 30296 star up peru 32583 star1 airlines lithuania 27781 triton avtn services united states luxembourg crco identification no. operator name state of the operator 36598 aero north intl ltd china 24391 aero-charter ukraine ukraine 36613 bullfinch ltd bermuda 724 cargolux luxembourg f11328 ebay inc united states 26356 emerald avtn usa united states 37613 fleet unlimited united states 26052 global jet luxembour luxembourg 25247 husky canada 38885 loue air s.a. luxembourg 1781 luxair luxembourg 6051 range flyers united states 37485 strategic air sa luxembourg 25108 tradewinds airlines united states 38821 uni-top airlines china 29957 west air luxembourg luxembourg 32947 yangtze river exp china hungary crco identification no. operator name state of the operator 29545 avia crew leasing united states 25569 abc air hungary hungary 32787 aerolimousine russia russian federation 28525 airquarius contracts south africa 28215 air doktor kft. hungary 34259 air highnesses ltd. armenia 34786 air transport serv hungary 36490 albion holdings ltd united kingdom 31616 baltyka ltd. ukraine 21621 blackburn intl.hu hungary 29227 cityline hungary kft hungary 32389 eastern express kazakhstan 20273 farnair air hungary hungary 36479 jetex flt sup. dubai united arab emirates 24336 krunk aviation ukraine 1803 malev hungary 31411 plaza centers ltd. hungary 37039 rollins air honduras 38354 sky aviation (ind) indonesia 36375 sky jet europe hungary 27948 tam air jsc georgia 34398 total aero svcs ltd united kingdom 27768 travel service kft. hungary 34636 ukrspetsexport ukraine 22148 valkyrie avtn united states 30078 wizz air hungary ltd hungary 34351 yas air iran, islamic republic of malta crco identification no. operator name state of the operator 31495 airblue ltd pakistan 256 air malta malta 36714 baca hydra leasing austria 37355 brise air s.a. united arab emirates f12667 capital aerospace united states 34461 comlux malta ltd malta 34875 contractair ltd. united kingdom 32146 david friend australia 32274 dbf aviation serv 2 australia 38978 dritte xr-gmbh germany 33271 europe exec jet svcs malta 37277 fluglausnir iceland 37769 global services llc united states 32637 hardy aviation australia 30537 heavylift cargo sierra leone 37284 imageair p/l australia 36198 kasas ltd kenya 25799 kharkov aircraft ukraine 22461 king air services south africa 32978 neville dunn\u2019s aviat australia 31897 pay s air service australia 34775 royal airlines ltd pakistan 38186 royal oman police oman 39008 r & m aircraft pty australia 37109 sky airline chile 32979 srd aviation australia 31989 sukhoy oao okb russian federation 22960 s togo togo f10459 turner enterprises, inc. united states f11796 threshold ventures inc united states 38457 vesting participacoe brazil 27137 washington times avt united states 36435 wellhome air carrier south africa netherlands crco identification no. operator name state of the operator 31643 aercap ireland ltd. ireland 30998 aerovertigo 2 united states 34951 africaine daviation congo 36307 airbulance netherlands 23557 air memphis netherlands 37191 air north partnershi canada 29998 air universal ltd jordan 33613 amsterdam airlines netherlands 21363 angola air charter angola 29335 aspen i llc united states 23464 aviacon zitotrans russian federation 35323 aviodrome lelystad netherlands 39021 baires fly s.a. argentina 31611 blue airways llc armenia 33759 blue bird avtn ltd sudan 34080 brasilian aircraft netherlands 33147 business air (tx) united states 37301 corendon dutch airline b.v. netherlands 34199 canal air llc united states f11794 carpau corp united states 2386 chc airways netherlands 6984 china airlines taiwan 24134 china southern china 30777 corendon airlines turkey 34761 coventry first united states f10613 c&e holdings inc. united states f12172 digital monitoring products united states 25536 dynamic aviation group inc. united states 31592 dac-aviation canada 37643 daroco holdings llc united states 28015 dc-yhdistys finland 7398 dynamic airlines netherlands 22713 eastman chemical company united states 33648 emerson climate technologies united states 1005 elal israel 21725 emergo finance canada 36313 enerjet canada 20588 execujet s africa south africa 35663 first prop aviation greece 29640 florida west intl aw united states 38731 fly georgia georgia 30803 fokker heritage netherlands 8034 fokker services bv netherlands 11556 gabon air transport gabon 3140 garuda indonesia 24666 gcb beheer netherlands 34347 ghassan ahmed kuwait 28885 global acft services united states 12137 golden europe jet germany 3707 heerema vliegbedrijf netherlands f10255 idaho investments inc. united states 31163 interstate airline netherlands 19232 jetaway air service united states 31955 jade cargo intl china f12150 jay aviation ii llc united states 31085 jetsupport netherlands 38601 jet a company united states 5131 jm aviation holdings united states 12573 keycorp aviation center united states 1640 klm netherlands 12405 kom activity netherlands 22345 korps landelijke pol netherlands f11885 liberty global, inc united states f10294 lbn, llc/central missouri aviation, inc. united states 29439 liberty global europ netherlands 35893 linea aer. carguera colombia 35336 lodgings 2000 gibraltar 1833 martinair netherlands 23109 meisner aircraft united states 34026 mil neth transport netherlands 37631 mk air pty ltd australia 1770 nationaal lucht- en ruimtevaartlaboratorium netherlands 278 nippon cargo japan 2023 northwest airlines united states f10349 oshkosh corporation united states f10928 oxbow falcon llc united states f10346 omi management us lp united states 37004 oshkosh corporation united states f12245 prime city holdings limited bvi virgin islands, british f13142 promega corporation united states 34344 paradigm jet mgmt united states 449 path united states 37434 pegasus tech united states 22139 polar air cargo ww united states 38487 rck aviation united states 32167 sama leltayaran company limited saudi arabia 35234 samco aircraft corp netherlands 32631 sextant holdings united states 2440 shell aircraft united kingdom 31729 silver air ltd united arab emirates 20544 skyline aviation netherlands 6050 skywest airlines australia 31449 soc. de conservation netherlands 30351 solid air netherlands 2723 transavia airlines netherlands 38200 travel air (papua) papua new guinea 30852 tui ned. arkefly netherlands 37890 universal health mgm united states 19198 universal weather uk united kingdom 23316 wilmington trust cy united states 31532 xojet united states norway crco identification no. operator name state of the operator 32769 aerosyncro aviation ab sweden 28884 aeronautica suntrans venezuela, bolivarian republic of 30308 airwing as norway 35709 air manas russian federation 33869 alci antartic south africa f12790 alpine aviation inc united states 33563 al thani, abdullah qatar 32992 amazon sky sac peru 36140 armstrong-sumin h b united states 37320 avia express sweden sweden 550 bergen air transport norway 36304 blueway offshore nor norway 37084 bristow norway as * norway f10118 chouest air, inc. united states 36851 chc heli. australia australia 32128 crescini g united states 5071 croix rouge switzerland 28088 duke energy business services llc united states 38211 donghai jet company china 37853 field aviation cy canada 32166 flyfort norway 34355 flyjet kazakhstan kazakhstan f10772 gpluss united states 27731 guard systems asa norway 34076 heliswiss intl switzerland 25570 hesnes air norway f12850 hoak travel inc united states 28864 jazz air canada f11458 majestic equipment services llc united states 17698 marine r corp united states 31852 mfi management fur germany 34343 midair ls switzerland 32571 norsk helikopter as norway 22212 norwegian airshuttle norway 32975 plane folk llc united states 37652 rely as norway 37658 scandinavian a/sys sweden 24142 smc aviation cyprus 32653 smokeless tobacco united states 33705 sundt air mngt as norway 35288 sunshine air svcs australia 5343 wideroe flyveselskap norway 33661 winner 614 jh llc united states f10893 w. c. aviation united states austria crco identification no. operator name state of the operator 33061 avcon jet ag austria 21973 aaa cooper transport united states 28314 aaa \u2014 air alps avtn austria 209 air charter ltd switzerland 35091 air sylhet ag austria 30222 amira air austria 38061 artjet ltd bermuda 27885 austin jet holding austria 440 austrian airlines austria 35521 aviation svc. mngt united arab emirates 35434 aviation-loww gmbh austria 32825 avtn partners inc united states f11781 bcom air llc united states 31562 bfs business flight austria 27000 centre-avia airlines russian federation 3813 charter air austria 20561 comtel air austria 32053 djt aviation gmbh austria 36370 fewotel bertriebs austria 1178 flick, ingrid austria 8620 fly jet italy 15451 georgetown mngmnt united states 31326 global jet austria austria 194 glock gmbh austria 30486 hadid intnl services united arab emirates 38013 innovative propertie united states 30323 international jet austria 28512 intersky luftfahrt austria 34493 jetlines germany 27702 jetalliance flugbetriebs gmbh austria 37410 jet-share aviation canada 25637 krono air austria 32335 laret aviation ltd. switzerland f10771 lk air, inc. united states 37796 lyoness aviation austria 9965 magna international canada 1083 mil austria austria 22617 mil slovenia slovenia 39012 m b p com. & imp. brazil 28808 m.a.p. management + planning austria 29932 niki luftfahrt gmbh austria 8582 omy aviation suisse switzerland 35956 pegasus jets ltd switzerland 2168 porsche konstruktion austria 38249 rz air charter gmbh austria 3858 schaffer austria 27384 schaffer gmbh switzerland 13030 strasser gmbh austria 35104 swan view austria 25989 the flying bulls austria 28567 tupack austria 8421 tyrolean jet service austria 19210 ukraine intl airline ukraine 32735 vienna jet austria 32040 vistajet austria 26443 volga aviaexpress russian federation f10472 weeks-davies aviation, inc. united states 36939 xentra pharm ltd ireland poland crco identification no. operator name state of the operator 31588 aero power uk united kingdom 38570 air north regional australia 38414 air onix airlines ukraine 33187 air poland sp.z.o.o. poland 35191 almasria egypt 21406 amc aviation egypt 37958 arkady sp.z.o.o. poland 27743 awas avtn srvc united states 36500 a&s world acft inc russian federation 38443 bingo airways sp. poland 31322 blue jet sp.z.o.o. poland 33876 cezar przedsiebiorst poland 31191 ecc leasing company ireland 36143 enter air poland 38442 eth sa luxembourg 25625 eurolot sa poland 19732 ge capital-gecas usa united states 32532 hawker partnership united kingdom 24631 j s aviation united kingdom 32562 koral blue airlines egypt 33079 lc engineering poland 1763 lot polish airlines poland 30797 magellan pro-service poland 15423 maritime office poland 35190 midwest airlines egypt 1082 mil algeria algeria 15686 mil bulgaria bulgaria 1097 mil finland finland 6310 mil nato napma 1113 mil poland poland 11555 mil romania romania 37385 musco sports light united states 32654 ng2 s.a. poland 37290 olt express poland poland 31237 olt express regional poland 28514 pogranichnaya kaz kazakhstan 32968 polish air navig poland 29333 pyrlandia boogie sp. poland 30603 pzl mielec poland 24855 rovno universal avia ukraine 35551 saudi medical serv. saudi arabia 36308 small planet ep poland 30192 sprintair sa poland 36858 tele-fonika kable poland 38446 travel service ep poland 26078 turan air azerbaijan 22273 venkateshwara hatch india 35851 yolenal limited poland a11519 operator using tail nb: n999eh unknown portugal crco identification no. operator name state of the operator f11871 airways management services united states f12524 air bravo united states 33625 air cargo carrier gov div united states f12525 alesworth united states 23852 aries aviation canada 37971 acft consultants 2 united states 33236 aeronautic solutions south africa 37192 aeronexus corporate south africa 26220 aeronorte portugal 37357 aero contractors united states 34994 africair usa (2) united states f12949 agri commodity trade llc unknown f12788 ag holdings i corp united states 34315 airalt sl spain f11466 aircraft trust & financing corp trustee united states 35358 aires s.a. colombia 32873 airlog intl ltd united states 9568 air bear united states 35406 air by jet llc united states 12500 air tractor united states 35522 american jet intl 2 united states 35973 american logistics argentina 33621 angola air service angola 29535 associated avtn united kingdom 31591 associated av (nig) nigeria 31919 aviation company south africa 10055 aviation srvcs intl united states 36487 avionco canada 37174 av fleet holding llc united states 35174 banco pine sa brazil 35811 bank of utah united states 25881 barnett investments united states 3935 basler turbo united states f10078 basurvencia united states 38781 best fly worldwide angola 37795 blue sky properties panama 32957 border security india 28573 bra transp aereos brazil 27477 broad river avtn united states 38891 bruce leven united states 34501 buffini & company 2 united states 37409 casas bahia comercial ltda brazil f10986 challenger air corp., llc united states f10117 channellock, inc. united states 28991 construtora andrade gutierrez, s.a. brazil f12176 contran corporation united states 32382 curves international inc united states f11394 camac aviation llc united states f11249 caoa montadora de veiculos s/a brazil 35613 celestial av trading ireland 34187 cemair south africa f11421 challenger 1073 llc united states 37305 challenger 605 llc brazil 29700 chartertech partner south africa 32199 cherry air aviation united states 38270 chik-chik aeronautic angola 27516 cielos del peru sa peru 33653 cj air safaris south africa 24811 clos de berry mgmt united states 35501 cohen ricardo united states 24378 comair sales ltd south africa 32983 comair (2) united states 30053 consorcio unibanco brazil 33062 constructora sambil venezuela, bolivarian republic of 36787 construtora cowan brazil 33176 crystal air avtn united states f12527 derwick associates de venezuala united states 31528 distribuidora pharma brazil f12189 enterprise aviation \u2014 bermuda ltd united states 27988 eagle mountain intl united states 33867 embassy of india portugal 34414 empr.de meios aereos portugal 25289 euroatlantic airways portugal 30179 executive turbine south africa f10727 falcon executive aviation, inc. united states f11847 flightstream aviation llc united states 23864 faith landmark united states 31214 falconcrest avtn united states 24973 flight management united states 30684 fluirdados sa portugal 38947 fly540 ghana ghana 37242 fung wing cheung china 27761 gambia intl (2) gambia 8760 gavilan united states 36437 gemini moon trading south africa f12704 giroski aviation llc united states 30178 global equities south africa 31572 global flight supprt united states f11793 global mission llc united states f11434 grosfeld investors llc united states 36978 gunter pps llc united states 36257 gyrocam systems united states 35289 g 137 llc united states 32070 hy fly, transportes a\u00e9reos, s.a. portugal 34888 hampton crystal nigeria 29095 hmy airways inc canada 36346 hm llc united states 31879 hughes air corp canada 32590 igreja universal do reino de deus brazil 34593 ial corp united states 38058 ibeca sa cuba 32417 ibis participa\u00e7\u00f5es e servi\u00e7os ltda. brazil 32833 indigo transport united states 37805 inmobiliaria rasal guatemala 32173 interwings airchrtr south africa 34763 joyce meyer ministries united states 31628 jdl aviation llc united states 37257 jesper continental israel 33382 jetfly suisse sarl switzerland 33637 jet management inc united states 38520 jet managers inc united states f10281 jmi services inc. united states 27707 jordan aviation jordan 38883 jw construction co united states 34683 kando jet llc united states 32791 king air charter south africa 32122 kj air united states 32488 knights arilines ltd nigeria 36622 koggen ltda united states 39078 krishnapatnam india f11799 kti incorp united states 32523 k&p aviation llc united states f12528 la cadena unknown 26001 lads australia 37177 lane aviation inc united states 38064 lima delta company united states f11784 living word christian center united states 38707 l-3 comms aeromet united states 34911 l3 communications advanced aviation llc united states 31396 mariner management llc barbados 25266 mente l.l.c. united states f13250 mercantil servicios financieros c.a. united states 37666 machavia inc united states 29587 macneil aviation llc united states 37794 madrone advisors united states 38933 mahil agropecuaria brazil 35273 malaysian dca malaysia 28388 manaca taxi aerea brazil 30683 masterjet-aviacao portugal 32546 mbf healtcare mgmt united states 32317 mcc aviation south africa 34766 med-view airlines nigeria 35632 meridian avtn (co) united states 33303 mh aviation united states 37098 mh aviation services south africa 31810 ministry transport nigeria f12190 ml200 leasing llc united states 38930 money aviation south africa 29463 morgan flight united states 32691 mouriteen family tr south africa 32137 mouritzen family south africa 35533 m. dias branco s.a. brazil 23781 netjets transportes a\u00e9reos, s.a. portugal 28772 naturelink aviation south africa 39075 ngwazi air charters zambia 33092 nicon airways nigeria 33140 nolinor aviat (nln) canada f10339 nww excel ii inc. united states 30008 oceanair linhas aer brazil 38542 ovlas services sa switzerland 36786 pacific flier micronesia, federated states of 29678 partnership south africa 25069 passaredo sa brazil 33232 peacon associates united states 38880 perdiem pilots llc united states 8058 pilot international united states 28105 professional maintnc united states f10830 reyes holdings, llc united states 31995 rani s aviation united states 31003 rb sports intl cayman islands 7732 rich products united states 31958 roston aviation united states 35338 royal jet inc united states 32614 rse company united states 37646 rse company delaware united states f12718 russell aviation leasing inc united states 31277 r & r aircraft united states 2354 sata air a\u00e7ores, s.a. portugal 25573 sata internacional, s.a. portugal f12670 schweitzer engineering labs inc united states f10406 spectator, inc. and kalco corporation united states 28661 sahara aviation south africa 36028 sierra nevada snc. united states 38239 sifco sa brazil 34940 signia jets spain 31892 skyros properties south africa 36707 spartan organisation united states 9295 specialized aircraft united states 31178 spectrem air south africa 19821 sporto snc france 33551 star air cargo south africa 31587 storm avtn canada canada 35493 strategic airlines australia 22689 s ivory coast c\u00f4te d\u2019ivoire f13023 tierecel limited/corbantrade cia. ltda. united states 34375 toby limited cayman islands 388 taag \u2014 linhas a\u00e9reas de angola \u2014 angola airlines angola 2649 tacv-transportes a\u00e9reos de cabo verde, s.a. cape verde 34229 tak continental ltd united states 2656 tap-transportes a\u00e9reos portugueses, s.a. portugal 21003 taxi aereo weston brazil f11806 three valleys ranch llc united states 27408 tinairlines portugal 30033 trans capital air canada 32712 trayton aviation united states 31334 trident aviation hk kenya 32974 triumph airways ltd canada 37761 trop comercio exter brazil 31496 trush aircraft united states f12760 tstc llc united states 35718 united bank card united states 11938 uac air charter germany 32229 us aviation corp united states 31833 us europe africa tr united states 32025 valleysoft angola 30481 vitesse aviation brazil 30887 voyageur airways (2) canada f10773 wells fargo bank nw na united states 31801 wachovia financial united states 37186 waylawn israel 32618 wc ferries south africa 35256 webjet linhas aereas brazil 30546 west central air canada 36343 west coast charters united states 27218 white-airways sa portugal f11379 willow creek association united states 30536 wings avtn nigeria nigeria 7965 worldwide ferrying canada f13008 world aero fuels and services unknown f11443 x pegasus llc united states a11481 operator using tail nb: n167aa unknown a11502 operator using tail nb: n636ga unknown a11745 operator using tail nb: n686al unknown a11746 operator using tail nb: n83pp unknown a11526 operator using tail nb: prcao unknown a12895 operator using tail nb: prest korea, democratic people\u2019s republic of a12899 operator using tail nb: prmmp korea, democratic people\u2019s republic of a12905 operator using tail nb: ptpss brazil a11537 operator using tail nb: vpcba unknown a11543 operator using tail nb: vqbaa unknown a11548 operator using tail nb: vqbgg unknown a12926 operator using tail nb: xbryp mexico romania crco identification no. operator name state of the operator 37254 aar airlift united states 38504 aersale inc united states 31492 aircraft traders belgium 31265 airjet angola angola 36412 air bucharest romania 31871 air jet lda united arab emirates 26569 arp 410 airlines ukraine 29424 astral aviation ltd kenya 26750 ave.com fzc united arab emirates 30600 blue air transport aerian romania 27344 bukovyna ukraine 34021 cagdas air turkey 26254 carpatair romania 37103 ctk network aviation ghana 31415 deta air kazakhstan 2349 jetran united states 31627 jetran air s.r.l. romania 31435 kyrgyz trans avia russian federation 30390 libyavia aviation libya 31716 max avia russian federation 35518 mdlr airlines india 28204 mia lebanon 21209 miami air intl united states 32236 middle east aviation lebanon f10719 riata management llc united states 32327 red star (fze) united arab emirates 27810 romanian academy romania 26019 romanian civil aeronautical authority romania 12320 romavia romanian romania 24932 rostvertol russian federation 26056 santay air turkey 10864 s cameroon cameroon 2658 tarom romania 39073 trident jet leasing ireland 33564 vega air company ukraine 28579 victoria avtn united kingdom 27298 vision airlines united states f11849 26 north aviation united states a12826 operator using tail nb: n801lr united states slovenia crco identification no. operator name state of the operator 129 adria airways slovenia 32878 arthel sarl france 32720 citic gen aviation china 35546 csi aviation svcs united states 36624 irtysh-air kazakhstan 35867 region avia airlines russian federation 20012 solinair d.o.o. slovenia slovakia crco identification no. operator name state of the operator 36800 aelis group a.s. slovakia 29083 aeromist kharkiv ukraine 36293 airexplore ltd. slovakia 20805 air slovakia bwj slovakia 36260 avia am leasing lithuania 23803 beriev acrft company russian federation 34446 bottlespring ltd cyprus 23544 caa slovak republic slovakia 28497 danube wings slovakia 29582 dubnica air ltd slovakia 31950 eagle air (sl) ltd sierra leone 31730 eastern slovakia 30601 eastern airways (fd) swaziland 38208 eastern airways(pty) swaziland 30547 filair 2 congo 38541 georgian llc georgia 22395 government slovakia slovakia 30935 ilyich iron & steel ukraine 33181 jump-tandem s.r.o. slovakia 30337 kam air afghanistan 20528 mil slovakia slovakia 36456 mokrance steel mills slovakia 37603 sayegh aviation europe, ltd slovakia 23224 seagle air slovakia 28436 sky europe airlines slovakia 25176 slovak airlines slovakia 35142 ssim, a.s. slovakia 27064 steel kosice slovakia 36243 travel service slov slovakia 35083 utair europe s.r.o. slovakia 36633 vjekoslav mihajlovic serbia finland crco identification no. operator name state of the operator 27696 airfix aviation ltd finland 3167 air niamey niger 380 alticor united states 24494 atyrau aue joly kazakhstan f10892 best friends air united states 38637 best jets intl united states 838 blue1 finland 31399 carlbad enterprises ukraine 35898 extreme crafts vi united states 1167 finnair oy finland 9834 fin aviation academy finland 27086 flybe finland oy finland 26295 gazavia joint stock russian federation 37664 hangar aviation mgmt united states 5922 jetflite finland 25610 kazair west kazakhstan 31987 lone ranger jets llc united states 26102 magadanavialising russian federation 8930 metropolitan life united states 37724 nordic global air oy finland 32127 river aviation finland 30246 tupolev oao russian federation 33207 utair-express ltd russian federation 28491 zao ak bylina russian federation a11515 operator using tail nb: n966e unknown sweden crco identification no. operator name state of the operator 455 avia express sweden ab sweden 31883 air nelson (2) new zealand 35376 air sweden aviation sweden 35786 aj produkter ab sweden 20289 ake jansson sweden 38079 alise aviation llc. united states 36103 allegiant air llc united states 37047 alnaser airlines jordan 30326 amapola flyg ab sweden 21131 atran-aviatrans russian federation 29292 avitrans nordic ab sweden 23804 bh airlines bosnia and herzegovina 12084 birgma sweden ab sweden 32341 blue aero france 24912 blue chip jet sweden 38682 bravo airlines ukraine 30391 business aviation uk ukraine f10123 comcast corporation/classic services united states f10545 corning incorporated united states f10112 cci pilot services ii, llc united states f11023 chailease finance (bvi) corp. virgin islands, british 38870 cimber a/s denmark 32004 cingular wireless united states 26939 city airline ab sweden 38659 city airline ab 2 sweden 37937 clyde air ab sweden 38080 comair (3) united states 36076 comtran international inc united states 30875 dls air united states 22647 eastair ab sweden 38727 exec jet enterprise taiwan 31463 expo aviation pvt 2 sri lanka 31837 eznis airways mongolia 23513 fly logic sweden 35824 fleetleader ab sweden 8697 flygande veteraner sweden 38448 flyglinjen vatterbyg sweden 35907 forschungszentrum germany 31506 global avtn partners russian federation 37393 global investment switzerland 22830 golden air flyg ab sweden 23882 hastens sangar ab sweden 27706 internal ministry uk ukraine f12232 jeffrey j hauser united states 34845 jet arrow switzerland 39062 jet plaid llc united states 32414 jordan consulting united states 3839 kinnarps sweden 5790 kustbevakningen sweden 35590 k/s hawker denmark 34960 largus aviation ab sweden 21450 malm\u00f6 aviation ab sweden 35390 mca airlines sweden 1103 mil hungary hungary 1116 mil sweden sweden 23589 mil/civ sweden sweden 30511 norwegian air shuttle sweden ab sweden 24970 nova airlines ab sweden 30120 nex time jet ab sweden 2041 occidental petroleum united states 33709 pmi global svcs inc united states 37993 professional air united states 24567 rainier avtn united states 25966 saab ab sweden 13488 saab aerotech sweden 35916 samoa technologies united states 38353 sappi manufactoring south africa 2351 sas sweden 25043 sa express south africa 30470 scandinavian medicop sweden 34500 sfs holding ab sweden 37442 shotgun ranch llc united states 38691 skyways express ab 2 sweden 7491 snas couriers bahrain 38038 sol lineas aereas sa argentina 21918 south african expres south africa 35483 spitfire investments united kingdom 36334 tam ab sweden 30408 tandoro switzerland 34708 tor air ab sweden 29020 transmile air svcs 2 malaysia 23235 tuifly nordic ab sweden 29367 viking airlines ab sweden 33688 vapsi sweden 7778 vartiolentolaivue finland 32740 vastgota sweden 32336 wade air australia 20170 west air sweden ab sweden united kingdom crco identification no. operator name state of the operator 10342 aero air, llc united states 37236 agropecuaria santana do deserto ltda. brazil 33319 aircraft associates inc united states f10008 airbill inc. united states f10023 alpha technologies, inc. united states f12107 american credit acceptance united states f11014 american resources united states 35644 amy\u2019s kitchen inc. united states f10035 anadarko petroleum corporation united states 35895 andromeda ltd bermuda 32958 avenir worldwide. united arab emirates 35933 avmet united kingdom 8740 abbott laboratories united states 27976 abco aviation incorporated united states 32962 abg air ltd united kingdom 39081 abg resource pvt ltd india 29096 ace-ina flight ops united states 30786 acft sarl luxembourg f11778 acg acquisition 169 llc united states 35080 acropolis avnt ltd united kingdom 35443 ac travel llc united states 31406 adl leasing united states 37390 advanced air mgmt(2) united states 27832 adventair united states 24201 aec intern. ltd switzerland f11874 aeg air a.v.v. aruba 30690 aergo beta leasing ireland 27739 aeromedical evac saudi arabia 31549 aeronaval united states 36924 aeron civil panama panama 36365 aerorutas sata argentina 29326 aeroservicios eje mexico 21273 aerosmith penny united states 36773 african airlines inv south africa 31032 aim avtn united states 38900 aircaft mngt svcs united kingdom 33754 aircraft africa co south africa 37072 aircraft holdings united kingdom f11330 aircraft properties llc c/o goodman properties united states 38908 aircrew direct united kingdom 35078 airlift intl (ghana) ghana 33856 airmid avtn svcs ltd india 10639 airstar group united states 38429 airstar leasing ltd united kingdom 33141 airtime llc united states 28150 air alpha jeddah saudi arabia 29508 air ambulance supprt united states 35354 air asia x malaysia 201 air canada canada 34225 air charter profsnl united states 551 air group (van nuys) united states 24148 air harrods ltd united kingdom 237 air india india 241 air jamaica jamaica 26351 air kilroe ltd t/a eastern airways united kingdom 264 air new zealand new zealand 38444 air nigeria nigeria 31662 air nova inc united states 33259 air partners corp canada 25802 air partner private jets ltd united kingdom 5633 air transat canada 21690 alg transp uk office united states 30184 alii aviation united states 31951 allegiance air south africa 38790 allfast fastening united states 34807 almojil aviation united arab emirates 36074 al fozan holding co. saudi arabia 33143 al rushaid aviation united states 31508 al salam 319 ltd. cayman islands 36145 al shohra pvt jet jordan 23373 al tameer saudi arabia 33938 amac corporate jet switzerland 35757 amber avtn (uk) ltd. united kingdom 364 ambrion aviation united kingdom 369 american airlines united states 372 american express united states 375 american int group united states 31782 ameriprise financial united states 31943 amgen united states 37598 ams ltd united kingdom 31016 andaman aviation united arab emirates 36383 anderson air ltd. canada 4944 anheuser busch united states 25743 anschutz united states f11351 apc aviation inc united states 35836 apec assets limited virgin islands, british 28676 aprilia holdings inc cayman islands 37233 arabian jets saudi arabia 28325 aramark united states 4999 aramco saudi arabia united states 32054 arik air ltd nigeria 31512 arinc direct united states 38283 arirang aviation united kingdom 34018 arkiva ltd. ireland 33376 armad bermuda 36765 arm investment mng nigeria 38871 ashley aviation ltd india 35141 ashok leyland ltd india 38999 asian express airl. united kingdom 31554 asia universal jet latvia 38121 asp aviation ltd united kingdom 28558 astraeus ltd united kingdom 34730 astra fire ltd united kingdom 35917 astrojet ltd united kingdom 36976 atalanta air united states 31345 atlantic airlines ltd united kingdom 27139 atlantic avtn 2 united states 32213 atlantic bridge av 2 united kingdom 35166 at&t management services, l.p. united states 436 aurigny air united kingdom 31623 avalon capital group united states 38338 avantha holding ltd india 32163 avcard uk united kingdom 38720 avfuel corp united states 31940 aviacor \u2014 aircraft russian federation 30645 aviamax germany 35661 aviation dynamix llc united states 39072 aviation hold. svcs united kingdom 35868 avia funds mngmt lithuania 27087 avioneta united states 36095 avion llc united states 36193 avitrans inc united states 26701 avmax group canada 35910 avmet international united states 29445 avn air united states 27329 avplan trip support united states 37441 avpro inc (3) united states 33188 avtn devlpment intl ireland 33680 avtn eqpment leasing united kingdom 33050 avtrade uk united kingdom 35255 avx taxi aereo brazil 37011 av consultants aspen united states 31787 av8jet united kingdom 18980 azerbaijan airlines azerbaijan 38878 azikel group n500az united kingdom 29496 a j walter aviation united kingdom f11440 a & c business services inc united states 35068 beacon capital partners, llc united states 8974 berwind corporation united states 32764 bharat forge limited india f10089 bloomberg services llc united states f10801 blue ridge air, inc. united states 629 bristow helicopters ltd united kingdom f200001 british midland regional limited united kingdom 32705 baa jet management china 32767 bac leasing ltd united kingdom 7579 bae systems, inc. united states 481 bae systems (operations) ltd united kingdom 22433 bahrain amiri flight bahrain f11305 banc of america leasing & capital llc united states 498 bangladesh biman bangladesh f12870 bank of america na c/o jet aviation business jets united states 6323 banline aviation united kingdom 37657 barbican holdings united kingdom 1015 baseops united states 6989 bass enterprises united states 36153 bayham limited saudi arabia 12669 ba cityflyer ltd united kingdom 37956 bbam avtn svcs ltd ireland 29975 bcc equipment lease united states 34052 bdk air limited canada 21482 bechtel united states 6890 becton dickinson united states 27039 beehawk aviation united states 32447 begal air united kingdom 36478 beijing cap airlines china 34866 bell geospace united kingdom 9170 bel air united kingdom 33770 benslow bermuda ltd. switzerland 36587 bentley forbes united states 37353 berta finance ltd belize 31598 beta leasing ireland f12839 beyond ventures llc united states 36482 bgst llc united states 36410 bharat hotels ltd india 38422 bhoja air pakistan 31303 big dog avtn united states f11350 bissell leasing co llc united states f10656 bjs jet solution (flexjet) unknown f11785 bkf aviation limited united states 38344 bks family office united kingdom 31242 black diamond avtn united states 3166 black & decker united states f12964 blatti aviation inc united states 37860 bluejets ltd united kingdom 38822 blue islands ltd united kingdom 36940 blue sky leasing ltd united kingdom f200002 bmibaby limited united kingdom 38941 bmi regional ltd united kingdom 38671 bnt intl corp united states 38499 bollinger shipyards united states f11795 bombardier aerospace corp united states 10970 bombardier flexjet united states 342 bombardier inc canada 37506 bombardier-maribel united states 30590 bond offshore helicopters ltd united kingdom 29396 booth creek mgmt united states 35778 boreh international united arab emirates 32750 boultbee avtn 3 united kingdom 38220 bow & arrow aviation united states 32952 bpg properties united states f12965 bp capital lp united states 32635 bramptonia ltd united kingdom 32340 bravo aviation united kingdom 22234 breco intl united kingdom 34320 briarwood prod. ltd united kingdom 30940 bridge aviation united kingdom 29373 bridgtown plant united kingdom 36768 brilliant media united kingdom 33190 bristol air ltd. saudi arabia 18137 bristol flying centr united kingdom 590 british airways plc united kingdom 634 british midland airways ltd united kingdom 29157 brokerage & managmt united states 22676 broome wellington united kingdom 29940 broom p avtn svcs united states 9701 brunswick united states 37278 bua delaware inc united states 31448 buckhead united states f11800 business aircraft leasing inc united states 36409 business jet consult united states 36607 business universe virgin islands, british f10174 bvg viajes sa de cv mexico 33472 byecross iom ltd united kingdom 29107 bzl bermuda limited bermuda 36342 bz air ltd united kingdom 31878 b&d aviation united states 36004 b2 managment ltd. bahrain f10103 canadian utilities limited canada 37741 casam int egypt f10770 charles schwab united states 3769 chevron u.s.a.inc. united states f10121 cleveland browns transportation llc united states 11816 coca cola refreshments united states f11882 colson & colson general contractor united states f13144 colsultatio s.a argentina f11184 columbus networks usa inc. united states f10778 computer sciences corporation united states f10124 conanicut aviation united states 10627 control techniques ltd united kingdom 35440 crescent heights, inc. united states 30369 caesars entertainmnt united states 33215 california jet share united states 12499 calspan united states 32717 cameron henkind united states 4018 campbell soup united states 29956 can pacific railway canada 22953 cape clear capital united states 36417 capital aviation pte singapore 37579 capital management united states 22724 cardinal health avtn united states 4029 cargill united states 39067 cartek dev. inc. virgin islands, british 32273 casbah switzerland 34066 castle 2003-2 ireland ltd ireland 6625 caterpillar united states 5800 cathay pacific china 24738 cathton holdings ltd canada 34930 catreus limited united kingdom 34153 cayley aviation bermuda 37117 ca, inc. united states 31570 cbair united states 29199 cbas (pvt) ltd india 33257 cbmm brazil f10110 cbs mass media corporation united states f11409 cbx aviation llc united states 28483 cb applications united states f10927 cef 2002 aircraft llc d/b/a ceridian corporation united states 31445 celestial airways united kingdom 34118 celeus investments brazil 36333 cello aviation ltd united kingdom f10114 cfg service corp, inc. united states 23394 chamarac united states 39016 charter air (iom)ltd united kingdom 28796 chartwell aviation united states 1808 chc scotia ltd united kingdom 37291 chicago jet group united states 35823 childress klein mgmt united states 38506 china eastern exec china 31541 christie avtn australia 7526 cigna united states 37889 cirrus aviation (us) united states 27210 citigroup united states 31361 cit aerospace int. ireland 37077 cit group location france 31867 clearwater aviation united kingdom 28482 clearwater fine food canada 33553 cloudscape inc united states 31057 cloud air service bermuda 32365 cnl group services united states 37774 cobian medrano jose mexico f11105 coca cola enterprise united states f12966 cockrell resources inc united states 34041 coldstream sarl luxembourg 9049 colleen united states 27981 colt intl canada 28719 colt intl houston united states 30312 comlux avtn switzerland 2577 computaplane united kingdom f11810 comstock asset management lc united states 4742 condor avtn united kingdom 2138 conocophillips avtn united states 31320 consolidated charter united states 32850 consolidated press 2 australia 35826 constellation leasing llc united states 8187 continental airlines united states 8953 cooper aerial united kingdom 38166 coordinates ops united states 33096 copart inc united states 33877 coracle aviation switzerland 23765 corporate flight mgt united states 34548 corporate jet reali. united kingdom 31680 corp jet mgmt virgin islands, british 38982 corvallis aero svc united states 31929 cor aviation united states 36493 cosmos air llc united states 30051 costa azzoura saudi arabia 26988 costco wholesale united states 25039 cougar helicopters canada 29350 countrywide home united states 37273 cove avtn partners united states 9248 crane company united states 37073 crompton greaves ltd india 31211 csc transportation united states 33204 ctc avtn jet svcs united kingdom f11401 cvs/caremark corporation united states 33885 cyber space nigeria 11175 czar aviation ltd united kingdom 36790 c2c air charters united states 30955 dal briar corporation united states f10140 devon realty advisors, llc united states f10888 diamond a administration llc united states f10171 dominion resources services inc. united states 30922 daidalos aviation ukraine 37414 dallah al-baraka hol saudi arabia 36557 dangote industries nigeria 29548 dartassan ireland 30278 darwin airline switzerland 36006 dar jana group saudi arabia 27123 datel direct ltd united kingdom f11325 delaware challenger operations llc united states 35844 deleaud gilbert united states 2808 dennis vanguard intl united kingdom 32849 desert air chtr inc united states 38341 desert air 3 ltd switzerland 35715 dhl air ltd united kingdom 32847 diago continental united arab emirates 35507 diamond air charter united kingdom 38765 diamond capital inv united states 36177 directv group united states 34630 direct aviation mngt united kingdom 35923 disney aviation united states 8334 ditco sa bermuda f12814 djt operations i llc united states 34559 dominion air ltd nigeria 944 donington aviation united kingdom 37038 dorstone holdings brazil 31583 dtc llc united states 6064 dubai air wing united arab emirates 11968 duke of westminster united kingdom 9784 dunavant enterprises united states 28590 dunview switzerland f13575 eleventh street aviation, llc united states f10178 enterprise rent-a-car, enterprise holdings united states f11204 essar shipping ports & logistics ltd (espl) india f12480 essar shipping & logistics ltd united kingdom 30494 executive jet group limited united kingdom 23881 executive jet management united states 22252 eagle aircraft united states 37787 eagle avtn inc united states 35754 eassda united kingdom 35500 eastar jet korea, republic of 32095 eastway aviation llc united states 23226 easyjet airline company ltd united kingdom 32462 easy aviation united kingdom 38310 ecb aviation pty ltd south africa 10068 edrees mustafa saudi arabia 13008 eds usa united states 29883 efb aviation united states f12872 egret management llc united states 996 egyptair egypt 29824 eie eagle united kingdom 27085 elas professional netherlands f12745 elk mountain ventures inc united states 29935 elmet avtn united states 29879 el-seif engineering saudi arabia 4025 embraer brazil 36502 embraer aaf aircraft south africa 9807 emirates intl united arab emirates 35162 emmanuel group united states 34060 empecom corporation cyprus 33488 enbridge canada 30014 energem aviation south africa 23576 enna \u2014 algerie algeria 27894 entrepreneurial asst united states 35529 eon aviation pvt ltd singapore 31041 epc holdings 644 united states 29929 etihad airways united arab emirates 37275 european acft sales denmark 34927 european skybus united kingdom 36196 eu-flight-service germany 14846 eva air taiwan 29654 ewa west united states 32264 execujet asia australia 28272 execujet charter switzerland 29471 execujet europe switzerland 36643 execujet new zealand new zealand 34017 executive avtn ltd united kingdom 32109 executive chartr usa united states 37101 executive flight div qatar 26147 executive jets ltd saudi arabia 31993 executive jet svcs nigeria 32605 exec jet management united kingdom 1076 exxonmobil av svcs united states 27686 e*trade group united states f12666 falcon fifty llc united states 36874 fambran enterprises llc united states 35797 felham enterprises inc united states f10932 felham enterprises ltd new zealand 23081 fertitta enterprises united states f10761 firefly entertainment inc. united states f12184 firstenergy service company united states f10192 first data corporation united states f10193 five star aviation, llc united states 37694 fly vectra ltd united kingdom f10210 foreign manufactures finance corp united states f10877 fortune brands, inc. united states f10836 fox paine and company, llc united states 21858 frost administrative services, inc. united states f10215 fry\u2019s electronics, inc. united states 22523 faa united states 33646 fairmont aviation united states 7382 falconair ltd south africa 35375 falcon 50 llc united states 33587 fanar aviation ltd bermuda 36124 fayair ltd united states 8430 fayair (jersey) united kingdom 34494 fci aviation llc united kingdom 12811 fegotila ltd bermuda 37269 fenway aviation brazil 31156 ferncroft united kingdom 38525 fga 9 ltd united kingdom 32784 fighter collection united kingdom 36876 first future air svc india 28957 fjl leasing united states 9695 fjr private flight united arab emirates 18781 fj900 united states 35930 flairjet ltd united kingdom f10974 flights inc. bermuda 34554 flightworks united kingdom 38413 flight assist uk ltd united kingdom 19907 flight consultancy united kingdom 5453 flybe ltd united kingdom 38743 flygtag ltd united kingdom 10992 flying lion united states 35925 flying m llc united states 10276 flynn financial united states f12979 fly beckys management llc united states f10202 fl aviation corporation united states 34064 fl510 switzerland 11369 ford europe ltd united kingdom 21529 forest aviation ltd united kingdom 7521 formula one mngmt united kingdom 34647 foster aviation united kingdom 6573 four star united states 22109 franklin templeton united states f12717 freeman air charter services united states 22740 frewton ltd united kingdom 22293 frontliner inc united states 37166 fs aviation llp united kingdom 32164 futura travels india f10914 galt aviation, llc united states f10217 gannett co., inc. united states 33031 gemini ltd united states f10219 general avileasing, inc. united states f11240 glenbrook iii llc united states f10227 global pacific aviation, inc. united states f12247 good think limited cayman island virgin islands, british 38737 green bay packaging inc. united states f10234 guidara nordeste participacoes ltda brazil f10984 guitar center, inc. united states 24116 gallagher enterprise united states 34737 galleria aviation united states 7618 gama aviation ltd united kingdom 38961 gambia bird airline gambia 7573 gantt aviation united states 38747 garden air llc united states 34865 garuda aviation australia f12727 general avileasing inc united states 1277 general dynamics united states f11377 general electric capital corp united states 32209 general technics united kingdom 35922 gen avtn flying svcs united states 36098 gexair ltd. united kingdom 32292 ge commercial av svc ireland 1278 ge corporate air trp united states 25841 gf air united states 36716 ghaith aviation saudi arabia 31328 ghana intl airlines ghana 33100 ghk company llc united states 35880 giancarlo trimarchi venezuela, bolivarian republic of 36916 giger, r switzerland f13141 giii aircraft management, llc united states 30058 giv airways llc united kingdom f11424 gkmg partners llc united states f11354 glen west 300 inc trustee united states 39093 global aircraft llc united states 36040 global business ass. malaysia 36785 global elite jets saudi arabia 33907 global estate & aviation ltd united states 38943 global express group united states 35699 global fleet oil gas united kingdom 33121 global trip support united states 30025 globespan airways ltd t/a flyglobespan united kingdom 35355 golden falcon 348 united arab emirates 32293 goodrich corp united states 36312 gottbetter & partner united states 22982 government of niger niger 32437 go xls ltd united kingdom 28048 graham capital united states 33773 graham capital mgmt united states 3259 grainger united states 30778 granard ltd united kingdom 36620 grand a aircraft llc united states 38796 gratefield ltd bermuda 6179 greenaap consultants united states 35286 greentech united states 31982 green flag aviation sudan f12804 grey falcon llc united states 315 grussair llc united states 30895 gscp (nj) inc united states 32596 gsc partners united states 23240 gtc managemt burbank united states 30632 guild investments united states 1356 gulfstream savannah united states 1365 gulf air bahrain 38749 gulf coast aviation united states 32656 gulf global svcs ltd united kingdom 36387 gulf wings united arab emirates 34936 gx aviation united states 31931 g c aviation, inc. united states 34836 g200 ltd bermuda 33864 g5 aviation south africa 25615 g5 executive switzerland 34978 g550 limited virgin islands, british 32412 hamilton aviation inc. united states 5601 hamlin jet ltd united kingdom 29387 harbert aviation united states 35935 harrinford ltd united states f11872 heckmann enterprises inc. united states f10240 hess corporation united states f10247 hewlett-packard company united states 35165 hicks holdings llc united states f12673 hindalco industries limited india f11137 hubbard broadcasting united states f10254 hunt consolidated inc. united states 24874 hac (hangar acquisition corporation) united states 12127 hamilton companies united states 29388 hangar 8 ltd united kingdom 9954 harris united states 21857 harsco united states 5152 harth trading est saudi arabia 33302 haverford suisse switzerland 529 hawker beechcraft united states 38607 hawker beechcraft 2 united states 33023 hawker west canada 32824 hbc aviation united kingdom 31777 hb-jem switzerland 28603 hcc service co united states 38724 head start avtn sys cyprus 8352 heinz company united states 8583 heliswiss switzerland 31253 heritage jets (fl) united states 1423 hershey company united states 26380 hertz corp united states 38709 hevelca societe united states 36953 highland awys ltd united kingdom 24583 hill air company i llc united states 35827 hitachi capital united kingdom 23203 holly corp united states 32171 holrob acft company united states 24776 home depot united states 8849 honeywell morristown united states 35466 horizon air llp united kingdom 6663 hornbill skyways malaysia 24604 hundred percent avtn united kingdom f10896 h. h. aviation llc united states 15438 inflite engineering services limited united kingdom 28726 international jet management united states 36005 irving oil transport inc. canada 17402 ibm united states f11457 ica global services llc united states 9962 iceland frozen foods united kingdom 35622 icon two ltd united kingdom f11412 igt united states 36144 ilc aviation gmbh austria f11456 imaginary images inc united states f10257 ims health united states 32114 indo pacific avtn india 32394 infinity aviation united arab emirates 35931 inflite avtn (iom) united kingdom 38619 insperity inc united states 34771 intercont. airways gambia 37023 international flight belgium 31503 international jetclub ltd united kingdom 34321 intl avtn leasing united kingdom 34440 intl flight res united states 33831 intl trip planning united states 31858 invemed avtn srvcs united states 38539 ipek international belize 38651 irkut corporation russian federation 26959 iscar israel israel 28061 island avtn usa united states 31918 ism aviation united kingdom 23317 itt industries united states f11372 ivanhoe aviation holdings llc united states 27301 ivanhoe aviation 2 singapore 38462 izy air nigeria f10265 jackson national life united states f10555 janah management company ltd united kingdom f10276 jepson associates inc. united states 28548 jet aviation business jet (hk) ltd china f10285 justravl aircraft management, inc. united states 32671 jannaire llp united kingdom 1559 japan airlines japan 35830 japc inc united states 27693 jato avtn united kingdom f11801 jcg aviation llc united states 36350 jcpenney co. inc. united states 493 jc bamford excavators ltd united kingdom f10275 jeld-wen, inc. united states 21889 jeppesen dataplan 2 united states 37076 jerand holdings virgin islands, british 24165 jetclub ltd switzerland 36498 jetflite intl llc united states 36494 jetselect, llc united states 30733 jetsteff aviation united kingdom 36274 jetstream worldwide china 38712 jets avtn svcs virgin islands, british 24997 jet airways india india 31908 jet air group jsc russian federation 36501 jet avtn flt svcs united states 31555 jet centre ltd united kingdom 31952 jet icu air ambulnce united states 21727 jet link israel 29290 jet midwest united states 33417 jet stream aviation saudi arabia 7532 jet2.com ltd united kingdom f11392 jhd aircraft sales co llc united states f10970 jhs management, llc. united states 23153 jindal steel india 32363 jlj equipment leasin united states 36480 johannesburg limited ireland 7628 johnson franklin united states 6281 johnson sc and son united states 32069 john mason acft svcs united kingdom 26509 joluk avtn united states 24536 jp morgan chase cy united states 37941 jra flight solutions united states 27049 j max air services united kingdom f10286 kansas city life insurance company united states 35938 knightsdene limited united kingdom 4335 kraft foods global inc. united states f11096 kacalp united states 26537 kangra aviation (fa) south africa 36270 kaupthing singer united kingdom 34670 keepflying llp united kingdom 3735 kenya airways kenya 24347 kerzner intl. united states f12815 kh aviation llc united states 32845 kilmer management canada 37723 kinch aviation svcs united kingdom 33034 kings airlines (2) nigeria 21519 kings aviation united kingdom 32210 klein tools united states 26927 knickerbocker united states 20894 kohler united states f11415 koury aviation inc united states f12222 ktr capital partners united states 33039 kubase aviation india 34192 kudos aviation ltd united kingdom 1673 kuwait airways kuwait f10496 leucadia aviation, inc. united states f10298 levi, ray & shoup, inc. united states f10299 limerick aviation, llc united states 35327 limonia ltd united kingdom f12478 longfellow management services llc united states 33756 labraid limited croatia 36286 lac aviation united kingdom f11022 lake capital llc united states 31324 las vegas sands united states 1703 learjet united states 30542 ledair canada canada 34956 legacy aviation limited united arab emirates 36957 level 3 comms united states f10880 lfg aviation australia 34322 lg electronics inc. korea, republic of 26996 liberty avtn company united kingdom 33298 liberty media llc united states 12275 liberty mutual united states 1727 libyan arab airlines libya 31756 lightair united states 36328 linksair ltd united kingdom 37068 link air svcs united kingdom 32145 link aviation united kingdom 1850 lisanne united states 1823 lockheed martin corp united states f12798 lockheed sales & rentals inc united states 1755 loganair ltd united kingdom 34736 loid global ltd russian federation 32192 london corporate jet united kingdom 23603 london executive aviation ltd united kingdom f12750 lone wolf aviation llc united states 33068 long charter air united states 36073 lowcountry trading united states 35829 lowes companies inc united states 27766 lowe\u2019s companies united states 38109 lufthansa tech sofia bulgaria 37926 lughnasa mgmt llc united states 35806 lunar jets ltd united kingdom 28751 lydd air ltd united kingdom f10610 l.a.w. aviation, llc united states f10980 maltese falcon, llc united states 37311 marcus evans avians ltd united kingdom f13119 mariner air llc united states f10312 mccormick and company inc. united states 27893 merck & co., inc. united states f10314 metromedia company united states 36335 metrojet limited us hong kong sar 36336 metrojet (mpamcl) hong kong sar f10315 mexico transportes aereos s.a de c.v. mexico f10817 michel moreno united states f12938 motorola mobility, inc. united states f12471 mr adam zachary cherry united states f12519 multiflight charter services llp unknown 33931 macsteel jet svcs bermuda 38695 madis management virgin islands, british 39059 mail handling intl united kingdom 32533 maiton air llp united kingdom 32569 majestic executive united arab emirates 35087 malamatinas greece 1801 malaysian airlines malaysia 36992 mann aviation llc united states 3901 marathon oil united states 28276 marbyia exec. flight saudi arabia 34154 marco polo avtn ltd. cayman islands 34616 marquez brothers av united states 35178 marriott intl united states 1828 marshall cambridge united kingdom 22811 masco united states 33151 mass holding netherlands 38632 mathis brothers united states 30499 mathys hugo switzerland 9088 matthews aviation united kingdom 31670 matthews john united kingdom 37112 maxair (nigeria) nigeria 32516 mazama finance united states f10308 mbg, llc united states 28682 mbi aviation united states 31708 mcair services united kingdom 34826 mcap europe ltd ireland 4260 mccain foods canada 26848 mcdonald\u2019s corp united states 39007 mcneely charter svc united states f11393 mdl consulting associates llc united states 28439 media consulting services united states 12177 mellon bank united states 35776 meridian (ghana) ghana 31538 merlin aviation switzerland 31076 metro jet usa united states 11068 mgm mirage united states 26475 midamerican energy united states 30837 midroc aviation saudi arabia 9082 midwest aviation ne united states 27573 mid roc leasing saudi arabia 36881 mid south aviation united states 37895 mid south jets inc united states 30093 mig russian aircraft russian federation 25846 milburn world travel united kingdom 12626 million air charter united states 2294 mil uk raf united kingdom 37426 mineralogy pty ltd. united states 32550 minnesota choice aviation iv llc united states 39056 mirmidones-grati avt united states 21245 mk airlines ltd united kingdom 33855 mobyhold limited united kingdom 38024 modern road makers india f11427 moelis & company manager llc united states 36267 monaco sports mngmt united kingdom 1922 monarch airlines ltd united kingdom 3508 monsanto united states 31348 morgan stanley mgmt united states 32228 morgan\u2019s machine united states 2996 motorola austin tx united states 4341 motorola mobility united states 32202 mountain avtn ltd united kingdom f10319 mp air, inc. united states 32777 mp aviation llp united kingdom 8099 msf aviation cayman islands 23928 multiflight ltd united kingdom 36762 murray air united kingdom 34926 murray air ltd malta 31584 mvoc united states 36987 mwm ag switzerland 32579 mysky llp united kingdom 29444 m c group united states f10305 m.j. air, llc united states f10327 national gypsum company united states 38627 nextera energy inc. united states f12496 noble services switzerland, llc united states f10338 nordstrom, inc. united states f12013 norfolk southern corp. united states 28895 nac aviation united kingdom 23230 nasa united states f10324 nascar, inc. united states 36849 national air cargo group inc united states 35849 national avtn comp. india 6764 national jets united states 9900 nationwide mutual united states 7853 natural environment united kingdom 8721 nauthiz pty ltd australia 20472 ncc services united states 38835 nebula iii ltd uae united arab emirates 38874 neptune avtn svcs united states 31095 netjets aviation inc united states 32049 newjetco europe united kingdom 36325 news america inc united states 36522 new orion air group united states 38267 new prime inc united states 31086 nigerian eagle airlines nigeria 34560 noble foods limited united kingdom 33712 noble foods ltd united kingdom 33203 noclaf limited united kingdom 33473 nok air thailand 36355 nola aviation virgin islands, british f11329 norlease inc united states 33099 north amer jet llc united states 31004 nova corporate svcs united kingdom 39066 novoair ltd bangladesh f12708 now presence llc united states 31489 ns aviation bermuda f11326 n14fx trust c/o wilmington trust co united states 31771 n526ee united states 31910 n700gb united states 31781 n846qm united states 31780 n941am united states 33974 ocean sky aircraft mamagement ltd united kingdom f10342 olayan financing company saudi arabia f10509 operadora de vuelos ejecutivas, s.a. de c.v. mexico f10348 orient wonder internationl ltd bermuda f12461 osmotica leasing llc united states f10917 oaklr aviation services llc united states 21845 oakmont united states 31679 oasis services united states 33108 ocean sky aviation united kingdom 33502 ocean sky (turkey) turkey 31793 ocean sky (uk) ltd united kingdom 28254 olayan fin. cpy. greece 22820 oman air oman 22436 oman royal flight oman 28683 omnicare management united states 37779 oncam aviation ltd united kingdom 17692 onur air turkey 22888 on time avtn united states f11444 opa llc united states 25897 open road airways united states 37336 oranto petroleum nigeria 30217 orion air pte singapore 36783 oryx jet ltd united kingdom 37383 osprey air lease llc united states f10603 oto development, llc united states 35176 pacific jet aviation, llc united states 36857 pacific stream united kingdom f10820 palm beach aviation, inc. united states f10351 paramount pictures corporation united states f11009 park rise investments ltd virgin islands, british f10356 peabody energy united states f10609 pegasus south, llc united states f10595 pfizer inc. united states 38050 pilante limited virgin islands, british f10918 pilgrim air united states f11181 pilot corporation united states f10979 pinjet aviation, llc united states f11276 powdr aviation, inc united states f10369 professional jet management, inc. united states 2088 pakistan international airlines pakistan 28158 palace intl united kingdom 30002 palm tree aviation bermuda 35530 pamir airways afghanistan f10642 pam management serv. llc united states 948 pan maritime ltd united kingdom 30968 pan-gulf avtn united kingdom 33154 paragon global flt s united kingdom 32132 parkridge aviation united kingdom 36085 park house avtn ltd bermuda 38394 pascan express inc canada 36875 patronus aviation virgin islands, british 31009 pattison airways canada 36792 pb air llc united states 27187 pdgaus germany 34044 pd air operation ltd germany 34075 peakview llc united states f12723 peak enterprises llc united states 30697 pearsons assets grp singapore 33882 pegasus elite avtn united states 22294 penske jet, inc. united states 37153 perfect 10 antenna united states f12694 perini corp united states 36038 perolux sarl luxembourg 37762 petterson don united states 22283 phelps dodge corp united states 32057 pinnacle operations united states 21824 planes and parts canada 22309 polet russian federation 32061 polygon air united states 30970 pool aviation nw ltd united kingdom 33115 potash corp (2) canada f10729 ppd development, llc united states 30220 ppl aviation llc united states 22434 presidential flt uae united arab emirates 31920 prestbury two united kingdom 38271 prestige intl holdin united arab emirates 33762 prestige jet rental united arab emirates 35276 prestige jp ltd united kingdom 37638 primevalue trading canada 38147 prime air svcs ltd nigeria 37897 prime jet (co) united states 36789 prime legacy mgmt united states 29430 prime legacy mngmt united states 31222 private aircraft int israel 36797 private jet group lebanon 35665 privilege airways india 3751 procter&gamble united states f12698 professional jet iii llc united states 33080 propinvest asset mgm united kingdom 35365 pro flite united states 33780 ptb (emerald) pty united kingdom 32329 punj lloyd india 32487 p.m. air canada 2196 qantas airways australia 21912 qatar airways qatar 33331 quadra aviation lp united kingdom 31585 qualcomm united states 30948 quinn aviation united kingdom 35924 qwest communications united states 36105 rampart aviation united states f10376 raytheon company united states f10378 red white & blue pictures, inc. united states f10975 regions financial corporation united states 36945 russian copper company holdings ltd russian federation 29692 rabbit run united states 37367 radcool investments south africa 32174 ravello enterprises united states 26191 ravenheat manufactrg united kingdom 30485 rc aviation llp united states 29739 rdv properties (arc) united states 38333 redwood avtn co. united states f12825 red hawk aviation llc united states 29515 red line air llc united states 31859 relational investors united states 9674 remo investments united kingdom f12740 renair 315 llc united states 37662 reynolds jet mgmt united states 33614 richard hayward united kingdom 35143 richmond american united states 7403 richmor aviation united states 29947 riverside aviation llc united states 35940 rizon jet uk ltd united kingdom 5547 rjr winston salem united states 30422 rl wings llc united states 31650 robinson avtn united states 8271 rockwell collins united states 36351 rockwell collins llc united states 26146 rock air ltd saudi arabia 38421 rock-tenn company united states 21667 ross investments united states 31832 rowley m united kingdom 28988 royal bank scotland united kingdom 2296 royal brunei brunei darussalam 29599 royal jet united arab emirates 2297 royal jordanian airlines jordan 30527 rp aviation united states 34828 runway asset mngt south africa 36882 r & g aviation llc united states f12590 r. lacy services, ltd. united states f1467 sails in concert, inc. united states 20467 samaritan\u2019s purse united states f12147 sanridge operating company united states 3991 sioux company ltd switzerland 30904 skyflight united states f11112 sky aviation ltd. gibraltar 34281 sky aviation services united arab emirates f10405 snapper consulting inc. brazil 30582 space exploration united states f12459 spitfire usa limited united states 36081 starbucks corporation united states f10410 starwood asset management, llc united states f10899 sterling aviation llc united states 30329 saga airlines turkey 29648 sagitta llc united states 38892 sam flier services united states 38645 santos dumont ltd ireland 34319 sapofina avtn ltd. virgin islands, british 32608 savannah aviation united states 37012 sa express (2) south africa 12627 scandi airleasing sweden f10894 scb falcon, llc united states 3236 scottish & newcastle united kingdom 22305 seaflight avtn bermuda 36492 seagrave aviation united states 33214 seeno construction united states f11025 sela holding company ltd saudi arabia 26695 select plant hire united kingdom 36444 seton david kenya 37439 sevcs aereos ilsa mexico f11250 sgsf capital venture llc united states 36843 sg finans as norway 22418 shamrock avtn nj united states 38490 shanghai deer jet china 22814 sharjah rulers flt united arab emirates 33126 shaw communications canada 35777 shaw wallace india 32093 shearwater air united states 27163 sheridan avtn united states 29727 shukra united kingdom f11453 siarex society inc united states 38910 sibiti 1 inc belize 28022 siebel systems uk united kingdom 36604 sierra aviation lp united states 32002 sierra stellar united states 33581 signal aviation ltd united kingdom 2463 singapore airlines singapore 39068 sitm jet ltd united kingdom 7867 sixt germany 35145 ska international united arab emirates 37703 skiva air armenia 37740 skybird air ltd nigeria 30241 skyblue aviation united kingdom 34695 skybus inc united states 35065 skybus llc united states 32526 skyexpress jsc russian federation 33042 skyhopper united kingdom 38190 skyjet aviation svcs nigeria 35728 skylane lp united kingdom 39057 skyline enterprises united states 23638 skyservice business canada 32337 skystead united arab emirates 33788 skytravel llc united states 38350 skywayaero inc. united states 31074 skyway russia russian federation 32553 skyworks capital united states 34918 sky aeronautical ireland 29880 sky aviation saudi arabia 31208 sky beyond holdings singapore 38711 sky unlimited wezup netherlands 36037 sk telecomm korea, republic of 30794 sleepwell avtn united kingdom 38895 sobha puravankara india 6404 sony aviation united states 36182 sophar property virgin islands, british 38491 southern avtn svcs united states 17330 southern cross av fl united states 2316 south african airways south africa 36653 south afr. breweries south africa 32897 spc aviation ltd united kingdom 34137 special ops ltd. saudi arabia 25246 specsavers avtn united kingdom 31762 sportsmens avtn grp united states 28904 spx corporation united states 5216 srilankan airlines sri lanka 30500 standard & poors united states 36639 stars away aviation south africa 38586 star aero holdings united states 32446 star aviation srvcs united arab emirates 35816 star peru peru 32554 sta (2006) llp united kingdom 32993 stc bermuda ltd. egypt 33469 stephen r. lloyd united kingdom 30889 stirling avtn united kingdom 17378 stockholm aircraft netherlands 27889 stuller settings united states 28152 st aviation united states 24644 st merryn air united kingdom 24529 subprice united kingdom 9182 suckling airways (cambridge) ltd t/a scotairways united kingdom 20474 summit avtn usa 2 united states 29813 suncor energy canada f11402 suntrust equipment finance & leasing corp united states 31354 sunwing airlines canada 32807 sun tv network india 8963 surewings united kingdom 28720 suzuki del caribe puerto rico 34329 svcs aereos denim mexico 5683 swagelok united states 38217 swedewings ab sweden 38435 swift aviation ltd united kingdom 28494 swiss switzerland 38361 syberjet aircraft united states 31527 symphony millenium bermuda 2642 syrian arab airlines syrian arab republic 22649 s botswana botswana 22593 s brunei sultan brunei darussalam 27535 s president sudan sudan 29242 s tanzania tanzania, united republic of f12492 target corporation unknown f13146 tejria services limited (bermuda) bermuda f11003 tendencia asset management cayman islands f10439 tesoro aviation company united states 38565 tetran assets ltd virgin islands, british 25363 the boeing company united states f12612 the private jet company united kingdom f10831 the richard e. jacobs group, llc united states f12238 the whitewind company us united states f11873 tillford limited bermuda f12235 top delight worldwide ltd virgin islands, british f10446 tour air, inc. united states f12231 translatin s.a. united states f10452 truman arnold companies united states f12479 tyremax pty ltd australia f10990 ty-tex exploration inc. united states 26684 tag aviation uk ltd united kingdom 33802 tail wind ltd. singapore 36754 tak aviation nigeria 33497 tak services ltd avv jordan f12709 tampa bay airlines llc c/o blumbergexcelsior corp united states 35547 tam aviation azerbaijan 27291 tarrant advisors united states 38625 tashi corporation united states 31697 tas corp united states 4189 taubman united states 32242 taylor energy company llc united states 36827 tcc air services inc united states 38545 team aero united states 36108 team viper united kingdom 37359 tekloc united states 29164 telus communications canada 37446 tempest capital united kingdom 28114 texas avtn sales&lsn united states 15677 textron united states 27034 thomas cook airlines ltd united kingdom 35441 thomas enterprises united states f10971 thomas william h. united states 37352 thomas & betts united states 30131 thomson airways ltd united kingdom 31218 thunder air uk ltd united kingdom 35153 thun ab sweden 27799 tidewater united states 4744 titan airways ltd united kingdom 36184 tnt express (uk) united kingdom f12990 tokeco incorporated united states 36462 top aces inc canada 32110 top aircraft united states 9705 tower house consults united kingdom 33891 town & country food united states 32029 tpg aviation south africa 38996 tp aero united states 34674 transcont. wings virgin islands, british 26670 transmeridian avtn united states 37267 transworld av trade united kingdom 5759 trans can pipelines canada 30585 trans euro air united kingdom 31673 travelers indemnity co united states 33923 trek-air b.v. netherlands 29593 trident jet jersey united kingdom 28999 trident leasing ireland 37551 trident petroleum egypt 36495 trimel investment united states 33853 trinity aviation ltd united kingdom 38580 triple a aviation luxembourg 36471 triple s aviation llc united states 13174 trustair ltd united kingdom 26165 trygon ltd united kingdom 32832 tuck aviation united states 21887 tudor investments united states 24731 turkmenistan turkmenistan 28983 twinwood transport. cayman islands 7971 tw air bermuda f10460 unisys corporation united states 2795 universal weather and aviation, inc. united states 22512 uganda exec flight uganda 12105 uim aircraft united states 32889 uniqe air (uk) united kingdom 2782 united airlines united states 35763 united airways (bd) bangladesh 4090 united company the united states 21505 united construction turkey 34059 united west airlines united states 33177 univ avn middle east united arab emirates 34914 usa jet airlines 3 united states f10462 us bank na trustee united states 34260 us marshals service united states 35834 utflight united states 18224 uzbekistan airways uzbekistan 30637 vale s/a brazil f10591 vulcan materials company united states 37678 valeant pharmaceut united states 8962 valero services, inc united states 33003 vedanta alumina ltd india 38968 verhill corporate virgin islands, british 7861 verizon corporate services group united states 35720 vicis capital l.l.c united states 34107 viper aviation llc united states 37019 vipjet limited ireland 8142 virgin atlantic airways ltd united kingdom 30418 vmd aviation united states 36911 volito aviation deux sweden 34977 v1 flt sup. intl united states f12485 waco air supply united states f10471 wayne a reaud united states 2634 western air charter inc united kingdom f10629 weyerhaeuser company united states f10479 wichita air services, inc. united states f10482 windsor media inc. united states f11514 windway capital corp unknown f10881 worldwide business jets corp united states f10483 world harvest church flight operations united states f12248 world noble limited cayman island virgin islands, british 35911 wallan aviation 2 saudi arabia 25432 wal-mart stores united states 30900 warner road avtn united states 35511 warwickshire blue united kingdom 38924 war enterprises united states f10470 waste management, inc united states 36041 watsco holdings inc united states 31377 wa developments united kingdom 35535 wells fargo bank (2) united states 2885 westair flying united kingdom 36283 western air chtr kx united states 34328 westfield llc united states 2890 westland united kingdom 25990 westshore avtn mgmt united states 34873 weststar avtn svcs malaysia 22445 white cloud united states 38210 white mountain avtn united states 28542 white rose avtn united states 32120 wilderness point ass united states 35983 williams aviation united kingdom 3021 williams companies united states 1162 williams grand prix united kingdom f11390 willis lease finance corp united states 36185 wilmington trust(ei) ireland 37196 wincor aviation united kingdom 38987 windsor jet mngt united states 34008 winged bull aviation united kingdom 36815 wing avtn chtr svc united states 25648 wing avtn usa united states 29596 winnepeg c/o reyes united states 37767 win aviation ltd. united kingdom 32802 wiv air-2 llc united states 31438 wood j m united kingdom 30474 world is yours united kingdom 22444 worthington industry united states 32152 wyndham worldwide united states f10485 xerox corporation united states 24421 xamex investments united states 32609 xiamen aviation avv russian federation 38359 yaas united states 34976 yh aviation ltd switzerland 37033 yum restaurant svcs united states f10983 zachry industrial inc. united states f10488 ziff brothers investment, llc united states f10490 zimmer inc. united states f11242 zoe air south africa f12223 zc aviation united states 34953 zenith capital ltd switzerland f11027 zenith insurance company united states 5943 zeno air united states 38819 zest aviation pvt india 38977 zweite xr-gmbh germany 35380 19th hole corp united kingdom 1905 3m company united states 36971 350 s.r.o. slovakia 38182 4274 aviation united states 34746 51 north limited united kingdom 30021 57 aviation services llc united states 6803 711 cody inc united states f12809 73mr llc united states 27726 994748 ontario inc canada a11749 operator using tail nb: cflhq unknown a11758 operator using tail nb: gocse unknown a11482 operator using tail nb: n192nc unknown a11485 operator using tail nb: n22ng unknown a11486 operator using tail nb: n254ga unknown a11743 operator using tail nb: n289mu unknown a11493 operator using tail nb: n44eg unknown a11494 operator using tail nb: n450lc unknown a11499 operator using tail nb: n588at unknown a11507 operator using tail nb: n86lf unknown a12844 operator using tail nb: n886dt united states a11513 operator using tail nb: n928gc unknown a11518 operator using tail nb: n995be unknown a11532 operator using tail nb: vpbat unknown a12656 operator using tail nb: vpcby cayman islands a11538 operator using tail nb: vpcjm unknown a11540 operator using tail nb: vpcro unknown a11544 operator using tail nb: vqbam unknown a12914 operator using tail nb: vtdha india a11747 operator using tail nb: vtrak unknown a12916 operator using tail nb: ww1 unknown a12924 operator using tail nb: xargb mexico ( 1 ) oj l 275, 25.10.2003, p. 32. ( 2 ) oj l 8, 13.1.2009, p. 3. ( 3 ) oj c 36, 13.2.2009, p. 11. details of the methodology used for establishing the preliminary list have been made available on the commission website: http://ec.europa.eu/environment/climat/aviation_en.htm. ( 4 ) oj l 344, 27.12.2005, p. 15. top", "document_date": "2013-02-12", "publication_date": "2013-02-12", "order_id": 1595, "document_type": "http://publications.europa.eu/resource/authority/resource-type/CONS_TEXT", "title": "Commission Regulation (EC) No 748/2009 of 5 August 2009 on the list of aircraft operators which performed an aviation activity listed in Annex I to Directive 2003/87/EC on or after 1 January 2006 specifying the administering Member State for each aircraft operator (Text with EEA relevance) ", "most_common_words": {"unknown": 715, "air": 535, "using": 726, "states": 1904, "united": 2364, "kingdom": 368, "tail": 642, "aviation": 567, "llc": 415, "operator": 790}, "word_counts": {"cyber security": 0, "protection": 0, "digital technologies": 0, "security": 3, "surveillance systems": 0, "cybercrime": 0, "digitalisation": 0, "egovernment": 0, "information security": 0, "ict": 6, "internet": 1, "cyber attack": 0, "internet of things": 0, "cloud": 3, "personal data": 0, "digital": 1, "hacker": 0, "cybersecurity": 0, "digital age": 0, "big data": 0, "data protection": 0, "ddos": 0, "cyber": 1, "privacy": 0}}